Workbook

Sheet 附件1
A1: 西藏自治区察隅县帮扶资金统计及使用情况汇总表 （截至2026年6月20日数据）
A2: 序号 | B2: 地市名称 | C2: 县区名称 | D2: 帮扶资金使用情况（万元） （保留小数点后面2位）
D3: 合计 | E3: 第一阶段 （包括2013年至2015年使用的各级财政专项扶贫资金、援藏资金、定点帮扶资金、地方政府债券资金、社会捐赠资金） | H3: 第二阶段 （包括2016年至2020年使用的各级财政涉农统筹整合资金（专项扶贫资金）、援藏资金、定点帮扶资金、地方政府债券资金、社会捐赠资金） | K3: 第三阶段 （包括2021年至2023年使用的各级财政衔接推进乡村振兴补助资金、涉农统筹整合资金（县级）、援藏资金、定点帮扶资金、地方政府债券资金、社会捐赠资金）
E4: 小计 | F4: 形成资产类 | G4: 未形成资产类 | H4: 小计 | I4: 形成资产类 | J4: 未形成资产类 | K4: 小计 | L4: 形成资产类 | M4: 未形成资产类
A5: 填表说明： | D5: 应为该县（区）所有帮扶资金总数 | E5: 应为该县（区）2013年至2015年帮扶资金小计数 | F5: 帮扶资金在使用过程中形成固定资产、权益类资产、生物性资产、低值易耗品、无形资产等的所有项目实际投入资金总数 | G5: 帮扶资金在使用过程中未形成资产的所有项目实际投入资金总数 | H5: 应为该县（区）2016年至2020年帮扶资金小计数 | I5: 帮扶资金在使用过程中形成固定资产、权益类资产、生物性资产、低值易耗品、无形资产等的所有项目实际投入资金总数 | J5: 帮扶资金在使用过程中未形成资产的所有项目实际投入资金总数 | K5: 应为该县（区）2021年至2023年帮扶资金小计数 | L5: 帮扶资金在使用过程中形成固定资产、权益类资产、生物性资产、低值易耗品、无形资产等的所有项目实际投入资金总数 | M5: 帮扶资金在使用过程中未形成资产的所有项目实际投入资金总数
A6: 1 | B6: 林芝市 | C6: 察隅县 | D6: =(E6+H6+K6) -> 324637.59 | E6: =(F6+G6) -> 19872.425 | F6: =198724250.74/10000 -> 19872.425 | G6: 0 | H6: =(I6+J6) -> 199879.74 | I6: =1837192850.72528/10000 -> 183719.29 | J6: =161604500/10000 -> 16160.45 | K6: =(L6+M6) -> 104885.43 | L6: =988974809.04/10000 -> 98897.481 | M6: =59879520/10000 -> 5987.952

Sheet 附件2
A1: 西藏自治区察隅县帮扶项目清单 （截至2026年6月30日数据）
A2: 序号 | B2: 地市名称 | C2: 县区名称 | D2: 项目年度 | E2: 项目名称 | F2: 是否为为形成资产项目 | G2: 是否为帮扶产业项目 | H2: 帮扶项目资金批复情况（元） | AG2: 帮扶项目资金使用情况（元） | BF2: 是否已确权 | BG2: 资料来源类型 | BH2: 项目申报主体
H3: 合计 | I3: 政策性资金 | AF3: 其他渠道资金（如企业自筹、信贷资金等非政策性资金） | AG3: 合计 | AH3: 政策性资金 | BE3: 其他渠道资金（如企业自筹、信贷资金等非政策性资金）
I4: 政策性资金小计 | J4: 专项扶贫资金 | O4: 统筹整合涉农资金 | T4: 财政衔接推进乡村振兴 补助资金 | Y4: 援藏资金 | AC4: 定点帮扶资金 | AD4: 地方政府债劵资金 | AE4: 社会捐赠（财政入账） | AH4: 政策性资金小计 | AI4: 专项扶贫资金 | AN4: 统筹整合涉农资金 | AS4: 财政衔接推进乡村振兴 补助资金 | AX4: 援藏资金 | BB4: 定点帮扶资金 | BC4: 地方政府债劵资金 | BD4: 社会捐赠（财政入账）
J5: 小计 | K5: 中央 | L5: 省级 | M5: 市级 | N5: 县级 | O5: 小计 | P5: 中央 | Q5: 省级 | R5: 市级 | S5: 县级 | T5: 小计 | U5: 中央 | V5: 省级 | W5: 市级 | X5: 县级 | Y5: 小计 | Z5: 省级 | AA5: 市级 | AB5: 县级 | AI5: 小计 | AJ5: 中央 | AK5: 省级 | AL5: 市级 | AM5: 县级 | AN5: 小计 | AO5: 中央 | AP5: 省级 | AQ5: 市级 | AR5: 县级 | AS5: 小计 | AT5: 中央 | AU5: 省级 | AV5: 市级 | AW5: 县级 | AX5: 小计 | AY5: 省级 | AZ5: 市级 | BA5: 县级
A6: 填表说明： | D6: 以项目批复中批复年度为准 | E6: 以项目批复中项目名称为准 | F6: 在“是/否”中选择 | G6: 在“是/否”中选择 | J6: 以项目批复中项目计划投资总金额为准 （保留小数点后面2位） | AH6: 该数据与附表1形成资产类金额数据一致 | AI6: 以项目竣工决算中核算实际投资金额为准 （保留小数点后面2位） | BF6: 在“是/否”中选择 | BG6: 财评、合同、立项等
A7: 合计 | H7: =SUM(H8:H602) -> 3.2856581e+09 | I7: =SUM(I8:I602) -> 3.2533117e+09 | J7: =SUM(J8:J602) -> 2.1904187e+08 | K7: =SUM(K8:K602) -> 89403700 | L7: =SUM(L8:L602) -> 15300000 | M7: =SUM(M8:M602) -> 86495000 | N7: =SUM(N8:N602) -> 27843169 | O7: =SUM(O8:O602) -> 1.1710255e+09 | ... BE7: =SUM(BE8:BE602) -> 25822939
A8: 1 | B8: 林芝市 | C8: 察隅县 | D8: 2017 | E8: 察隅县察瓦龙乡汽修市场建设项目 | F8: 是 | G8: 是 | H8: =I8+AF8 -> 13832800 | I8: =O8+J8+T8+Y8+AE8+AC8+AD8 -> 13832800 | J8: =N8+M8+L8+K8 -> 0 | O8: =S8+R8+Q8+P8 -> 13832800 | Q8: 13832800 | T8: =U8+V8+W8+X8 -> 0 | Y8: =AA8+Z8+AB8 -> 0 | AG8: =AH8+BE8 -> 13081530 | AH8: =AN8+AI8+AS8+AX8+BD8+BB8+BC8 -> 13081530 | AI8: =AM8+AL8+AK8+AJ8 -> 0 | AN8: =AR8+AQ8+AP8+AO8 -> 13081530 | AP8: 13081530 | AS8: =AW8+AV8+AU8+AT8 -> 0 | AX8: =AZ8+AY8+BA8 -> 0 | BE8: 0 | BF8: 是 | BG8: 确权资料
A9: 2 | B9: 林芝市 | C9: 察隅县 | D9: 2017 | E9: 察隅县下察隅镇布巴村等三个行政村猕猴桃种植建设项目 | F9: 是 | G9: 是 | H9: =I9+AF9 -> 21304200 | I9: =O9+J9+T9+Y9+AE9+AC9+AD9 -> 14843900 | J9: =N9+M9+L9+K9 -> 0 | O9: =S9+R9+Q9+P9 -> 14843900 | S9: 14843900 | T9: =U9+V9+W9+X9 -> 0 | Y9: =AA9+Z9+AB9 -> 0 | AF9: 6460300 | AG9: =AH9+BE9 -> 21009370 | AH9: =AN9+AI9+AS9+AX9+BD9+BB9+BC9 -> 14843900 | AI9: =AM9+AL9+AK9+AJ9 -> 0 | AN9: =AR9+AQ9+AP9+AO9 -> 14843900 | AR9: 14843900 | AS9: =AW9+AV9+AU9+AT9 -> 0 | AX9: =AZ9+AY9+BA9 -> 0 | BE9: =21009369.65-AH9 -> 6165469.7 | BF9: 否 | BG9: 只有电子数据，来源超1000万财评，2019年
A10: 3 | B10: 林芝市 | C10: 察隅县 | D10: 2018 | E10: 察隅县察瓦龙乡岗藏村机耕道建设项目 | F10: 是 | G10: 否 | H10: =I10+AF10 -> 361600 | I10: =O10+J10+T10+Y10+AE10+AC10+AD10 -> 361600 | J10: =N10+M10+L10+K10 -> 0 | O10: =S10+R10+Q10+P10 -> 361600 | S10: 361600 | T10: =U10+V10+W10+X10 -> 0 | Y10: =AA10+Z10+AB10 -> 0 | AG10: =AH10+BE10 -> 356668 | AH10: =AN10+AI10+AS10+AX10+BD10+BB10+BC10 -> 356668 | AI10: =AM10+AL10+AK10+AJ10 -> 0 | AN10: =AR10+AQ10+AP10+AO10 -> 356668 | AR10: 356668 | AS10: =AW10+AV10+AU10+AT10 -> 0 | AX10: =AZ10+AY10+BA10 -> 0 | BF10: 是 | BG10: 确权资料，确权金额和台账审定金额一致，有支付凭证 | BH10: 察隅县脱贫攻坚指挥部综合组
A11: 4 | B11: 林芝市 | C11: 察隅县 | D11: 2018 | E11: 察隅县下察隅镇共同村阿美组易地扶贫搬迁安置项目 | F11: 是 | G11: 否 | H11: =I11+AF11 -> 9922100 | I11: =O11+J11+T11+Y11+AE11+AC11+AD11 -> 9922100 | J11: =N11+M11+L11+K11 -> 0 | O11: =S11+R11+Q11+P11 -> 0 | T11: =U11+V11+W11+X11 -> 0 | Y11: =AA11+Z11+AB11 -> 9922100 | AA11: 9922100 | AG11: =AH11+BE11 -> 9787823.5 | AH11: =AN11+AI11+AS11+AX11+BD11+BB11+BC11 -> 9787823.5 | AI11: =AM11+AL11+AK11+AJ11 -> 0 | AN11: =AR11+AQ11+AP11+AO11 -> 0 | AS11: =AW11+AV11+AU11+AT11 -> 0 | AX11: =AZ11+AY11+BA11 -> 9787823.5 | AZ11: 9787823.5 | BF11: 否 | BG11: 立项批复+50-1000万台账 | BH11: 县安居办
A12: 5 | B12: 林芝市 | C12: 察隅县 | D12: 2019 | E12: 察隅县竹瓦根镇沙通坝建材市场建设项目 | F12: 是 | G12: 是 | H12: =I12+AF12 -> 24760000 | I12: =O12+J12+T12+Y12+AE12+AC12+AD12 -> 24760000 | J12: =N12+M12+L12+K12 -> 0 | O12: =S12+R12+Q12+P12 -> 24760000 | P12: 24760000 | T12: =U12+V12+W12+X12 -> 0 | Y12: =AA12+Z12+AB12 -> 0 | AG12: =AH12+BE12 -> 23047426 | AH12: =AN12+AI12+AS12+AX12+BD12+BB12+BC12 -> 23047426 | AI12: =AM12+AL12+AK12+AJ12 -> 0 | AN12: =AR12+AQ12+AP12+AO12 -> 23047426 | AO12: 23047426 | AS12: =AW12+AV12+AU12+AT12 -> 0 | AX12: =AZ12+AY12+BA12 -> 0 | BE12: 0 | BF12: 是 | BG12: 确权资料+超过1千万的财评台账（21年）
A13: 6 | B13: 林芝市 | C13: 察隅县 | D13: 2019 | E13: 察隅县古拉乡石榴种植项目 | F13: 是 | G13: 是 | H13: =I13+AF13 -> 500000 | I13: =O13+J13+T13+Y13+AE13+AC13+AD13 -> 500000 | J13: =N13+M13+L13+K13 -> 0 | O13: =S13+R13+Q13+P13 -> 500000 | Q13: 500000 | T13: =U13+V13+W13+X13 -> 0 | Y13: =AA13+Z13+AB13 -> 0 | AG13: =AH13+BE13 -> 500000 | AH13: =AN13+AI13+AS13+AX13+BD13+BB13+BC13 -> 500000 | AI13: =AM13+AL13+AK13+AJ13 -> 0 | AN13: =AR13+AQ13+AP13+AO13 -> 500000 | AP13: 500000 | AS13: =AW13+AV13+AU13+AT13 -> 0 | AX13: =AZ13+AY13+BA13 -> 0 | BE13: 0 | BF13: 是 | BG13: 确权资料 | BH13: 古拉乡人民政府
A14: 7 | B14: 林芝市 | C14: 察隅县 | D14: 2019 | E14: 察隅县竹瓦根镇生猪养殖项目 | F14: 是 | G14: 是 | H14: =I14+AF14 -> 500000 | I14: =O14+J14+T14+Y14+AE14+AC14+AD14 -> 500000 | J14: =N14+M14+L14+K14 -> 0 | O14: =S14+R14+Q14+P14 -> 500000 | Q14: 500000 | T14: =U14+V14+W14+X14 -> 0 | Y14: =AA14+Z14+AB14 -> 0 | AG14: =AH14+BE14 -> 500000 | AH14: =AN14+AI14+AS14+AX14+BD14+BB14+BC14 -> 500000 | AI14: =AM14+AL14+AK14+AJ14 -> 0 | AN14: =AR14+AQ14+AP14+AO14 -> 500000 | AP14: 500000 | AS14: =AW14+AV14+AU14+AT14 -> 0 | AX14: =AZ14+AY14+BA14 -> 0 | BE14: 0 | BF14: 是 | BG14: 确权资料
A15: 8 | B15: 林芝市 | C15: 察隅县 | D15: 2019 | E15: 察隅县本土生态农产品加工项目 | F15: 是 | G15: 是 | H15: =I15+AF15 -> 2500000 | I15: =O15+J15+T15+Y15+AE15+AC15+AD15 -> 2500000 | J15: =N15+M15+L15+K15 -> 0 | O15: =S15+R15+Q15+P15 -> 2500000 | P15: 1787800 | Q15: 712200 | T15: =U15+V15+W15+X15 -> 0 | Y15: =AA15+Z15+AB15 -> 0 | AG15: =AH15+BE15 -> 2399270.3 | AH15: =AN15+AI15+AS15+AX15+BD15+BB15+BC15 -> 2399270.3 | AI15: =AM15+AL15+AK15+AJ15 -> 0 | AN15: =AR15+AQ15+AP15+AO15 -> 2399270.3 | AO15: 1687070.3 | AP15: 712200 | AS15: =AW15+AV15+AU15+AT15 -> 0 | AX15: =AZ15+AY15+BA15 -> 0 | BE15: 0 | BF15: 是 | BG15: 确权资料+50-1000万台账
A16: 9 | B16: 林芝市 | C16: 察隅县 | D16: 2019 | E16: 察隅县察瓦龙乡邓许村机耕道建设项目 | F16: 是 | G16: 否 | H16: =I16+AF16 -> 731100 | I16: =O16+J16+T16+Y16+AE16+AC16+AD16 -> 731100 | J16: =N16+M16+L16+K16 -> 0 | O16: =S16+R16+Q16+P16 -> 731100 | S16: 731100 | T16: =U16+V16+W16+X16 -> 0 | Y16: =AA16+Z16+AB16 -> 0 | AG16: =AH16+BE16 -> 695200 | AH16: =AN16+AI16+AS16+AX16+BD16+BB16+BC16 -> 695200 | AI16: =AM16+AL16+AK16+AJ16 -> 0 | AN16: =AR16+AQ16+AP16+AO16 -> 695200 | AR16: 695200 | AS16: =AW16+AV16+AU16+AT16 -> 0 | AX16: =AZ16+AY16+BA16 -> 0 | BF16: 是 | BG16: 确权资料，需要核定台账695200审定依据，50-1000万里面没有写审定金额 | BH16: 察隅县脱贫攻坚指挥部办公室
A17: 10 | B17: 林芝市 | C17: 察隅县 | D17: 2019 | E17: 察隅县察瓦龙乡洪东村机耕道建设项目 | F17: 是 | G17: 否 | H17: =I17+AF17 -> 203500 | I17: =O17+J17+T17+Y17+AE17+AC17+AD17 -> 203500 | J17: =N17+M17+L17+K17 -> 0 | O17: =S17+R17+Q17+P17 -> 203500 | S17: 203500 | T17: =U17+V17+W17+X17 -> 0 | Y17: =AA17+Z17+AB17 -> 0 | AG17: =AH17+BE17 -> 193600 | AH17: =AN17+AI17+AS17+AX17+BD17+BB17+BC17 -> 193600 | AI17: =AM17+AL17+AK17+AJ17 -> 0 | AN17: =AR17+AQ17+AP17+AO17 -> 193600 | AR17: 193600 | AS17: =AW17+AV17+AU17+AT17 -> 0 | AX17: =AZ17+AY17+BA17 -> 0 | BF17: 是 | BG17: 确权资料（确权金额和台账审定金额一致，但是没有支付财评） | BH17: 县脱贫攻坚指挥部办公室（扶贫办）
A18: 11 | B18: 林芝市 | C18: 察隅县 | D18: 2019 | E18: 察隅县察瓦龙乡康然村等村组道路建设项目 | F18: 是 | G18: 否 | H18: =I18+AF18 -> 11760200 | I18: =O18+J18+T18+Y18+AE18+AC18+AD18 -> 11760200 | J18: =N18+M18+L18+K18 -> 0 | O18: =S18+R18+Q18+P18 -> 11760200 | P18: 7063200 | Q18: 4697000 | T18: =U18+V18+W18+X18 -> 0 | Y18: =AA18+Z18+AB18 -> 0 | AG18: =AH18+BE18 -> 11541052 | AH18: =AN18+AI18+AS18+AX18+BD18+BB18+BC18 -> 11541052 | AI18: =AM18+AL18+AK18+AJ18 -> 0 | AN18: =AR18+AQ18+AP18+AO18 -> 11541052 | AO18: 7063200 | AP18: 4477851.5 | AS18: =AW18+AV18+AU18+AT18 -> 0 | AX18: =AZ18+AY18+BA18 -> 0 | BF18: 是 | BG18: 确权资料+超过1千万的财评台账（20年） | BH18: 和超过1千万的财评台账20年，记录差1分钱，确权是和台账审定金额一致。
A19: 12 | B19: 林芝市 | C19: 察隅县 | D19: 2019 | E19: 察隅县察瓦龙乡康然村机耕道建设项目 | F19: 是 | G19: 否 | H19: =I19+AF19 -> 1039200 | I19: =O19+J19+T19+Y19+AE19+AC19+AD19 -> 1039200 | J19: =N19+M19+L19+K19 -> 0 | O19: =S19+R19+Q19+P19 -> 1039200 | S19: 1039200 | T19: =U19+V19+W19+X19 -> 0 | Y19: =AA19+Z19+AB19 -> 0 | AG19: =AH19+BE19 -> 970801.92 | AH19: =AN19+AI19+AS19+AX19+BD19+BB19+BC19 -> 970801.92 | AI19: =AM19+AL19+AK19+AJ19 -> 0 | AN19: =AR19+AQ19+AP19+AO19 -> 970801.92 | AR19: 970801.92 | AS19: =AW19+AV19+AU19+AT19 -> 0 | AX19: =AZ19+AY19+BA19 -> 0 | BF19: 是 | BG19: 确权资料+50-1000万台账+财评 | BH19: 察隅县扶贫开发办公室
A20: 13 | B20: 林芝市 | C20: 察隅县 | D20: 2019 | E20: 察隅县察瓦龙乡龙普村机耕道建设项目 | F20: 是 | G20: 否 | H20: =I20+AF20 -> 125700 | I20: =O20+J20+T20+Y20+AE20+AC20+AD20 -> 125700 | J20: =N20+M20+L20+K20 -> 0 | O20: =S20+R20+Q20+P20 -> 125700 | S20: 125700 | T20: =U20+V20+W20+X20 -> 0 | Y20: =AA20+Z20+AB20 -> 0 | AG20: =AH20+BE20 -> 119600 | AH20: =AN20+AI20+AS20+AX20+BD20+BB20+BC20 -> 119600 | AI20: =AM20+AL20+AK20+AJ20 -> 0 | AN20: =AR20+AQ20+AP20+AO20 -> 119600 | AR20: 119600 | AS20: =AW20+AV20+AU20+AT20 -> 0 | AX20: =AZ20+AY20+BA20 -> 0 | BF20: 是 | BG20: 确权资料+立项批复，审定金额来源不明，已经按119600元确权 | BH20: 察隅县扶贫开发办公室
A21: 14 | B21: 林芝市 | C21: 察隅县 | D21: 2019 | E21: 察隅县察瓦龙乡梦扎村机耕道建设项目 | F21: 是 | G21: 否 | H21: =I21+AF21 -> 475000 | I21: =O21+J21+T21+Y21+AE21+AC21+AD21 -> 475000 | J21: =N21+M21+L21+K21 -> 0 | O21: =S21+R21+Q21+P21 -> 475000 | P21: 129695 | S21: 345305 | T21: =U21+V21+W21+X21 -> 0 | Y21: =AA21+Z21+AB21 -> 0 | AG21: =AH21+BE21 -> 451700 | AH21: =AN21+AI21+AS21+AX21+BD21+BB21+BC21 -> 451700 | AI21: =AM21+AL21+AK21+AJ21 -> 0 | AN21: =AR21+AQ21+AP21+AO21 -> 451700 | AO21: 129695 | AR21: 322005 | AS21: =AW21+AV21+AU21+AT21 -> 0 | AX21: =AZ21+AY21+BA21 -> 0 | BF21: 是 | BG21: 确权资料，台账审定金额来源待确定，已经按268900元确权 | BH21: 察隅县扶贫开发办公室
A22: 15 | B22: 林芝市 | C22: 察隅县 | D22: 2019 | E22: 察隅县古拉乡俄玉村过境路段硬化建设项目 | F22: 是 | G22: 否 | H22: =I22+AF22 -> 1046000 | I22: =O22+J22+T22+Y22+AE22+AC22+AD22 -> 1046000 | J22: =N22+M22+L22+K22 -> 0 | O22: =S22+R22+Q22+P22 -> 1046000 | P22: 1046000 | T22: =U22+V22+W22+X22 -> 0 | Y22: =AA22+Z22+AB22 -> 0 | AG22: =AH22+BE22 -> 950604.85 | AH22: =AN22+AI22+AS22+AX22+BD22+BB22+BC22 -> 950604.85 | AI22: =AM22+AL22+AK22+AJ22 -> 0 | AN22: =AR22+AQ22+AP22+AO22 -> 950604.85 | AO22: 950604.85 | AS22: =AW22+AV22+AU22+AT22 -> 0 | AX22: =AZ22+AY22+BA22 -> 0 | BF22: 是 | BG22: 确权资料+50-1000万台账
A23: 16 | B23: 林芝市 | C23: 察隅县 | D23: 2019 | E23: 察隅县古拉乡关龙村二期入户道路建设项目 | F23: 是 | G23: 否 | H23: =I23+AF23 -> 1757800 | I23: =O23+J23+T23+Y23+AE23+AC23+AD23 -> 1757800 | J23: =N23+M23+L23+K23 -> 0 | O23: =S23+R23+Q23+P23 -> 1757800 | P23: 57730 | S23: 1700070 | T23: =U23+V23+W23+X23 -> 0 | Y23: =AA23+Z23+AB23 -> 0 | AG23: =AH23+BE23 -> 1652598.7 | AH23: =AN23+AI23+AS23+AX23+BD23+BB23+BC23 -> 1652598.7 | AI23: =AM23+AL23+AK23+AJ23 -> 0 | AN23: =AR23+AQ23+AP23+AO23 -> 1652598.7 | AO23: 57730 | AR23: 1594868.7 | AS23: =AW23+AV23+AU23+AT23 -> 0 | AX23: =AZ23+AY23+BA23 -> 0 | BF23: 是 | BG23: 确权资料+50-1000万台账 | BH23: 察隅县扶贫开发办公室
A24: 17 | B24: 林芝市 | C24: 察隅县 | D24: 2019 | E24: 察隅县古拉乡南雪村过境路段硬化建设项目 | F24: 是 | G24: 否 | H24: =I24+AF24 -> 653000 | I24: =O24+J24+T24+Y24+AE24+AC24+AD24 -> 653000 | J24: =N24+M24+L24+K24 -> 0 | O24: =S24+R24+Q24+P24 -> 653000 | P24: 653000 | T24: =U24+V24+W24+X24 -> 0 | Y24: =AA24+Z24+AB24 -> 0 | AG24: =AH24+BE24 -> 617709.05 | AH24: =AN24+AI24+AS24+AX24+BD24+BB24+BC24 -> 617709.05 | AI24: =AM24+AL24+AK24+AJ24 -> 0 | AN24: =AR24+AQ24+AP24+AO24 -> 617709.05 | AO24: 617709.05 | AS24: =AW24+AV24+AU24+AT24 -> 0 | AX24: =AZ24+AY24+BA24 -> 0 | BF24: 是 | BG24: 确权资料+50-1000万台账 | BH24: 县交通运输局
A25: 18 | B25: 林芝市 | C25: 察隅县 | D25: 2019 | E25: 察隅县古拉乡特色经济林果种植建设项目 | F25: 是 | G25: 是 | H25: =I25+AF25 -> 9436700 | I25: =O25+J25+T25+Y25+AE25+AC25+AD25 -> 9436700 | J25: =N25+M25+L25+K25 -> 0 | O25: =S25+R25+Q25+P25 -> 9436700 | P25: 9436700 | T25: =U25+V25+W25+X25 -> 0 | Y25: =AA25+Z25+AB25 -> 0 | AG25: =AH25+BE25 -> 8814526.2 | AH25: =AN25+AI25+AS25+AX25+BD25+BB25+BC25 -> 8814526.2 | AI25: =AM25+AL25+AK25+AJ25 -> 0 | AN25: =AR25+AQ25+AP25+AO25 -> 8814526.2 | AO25: 8814526.2 | AS25: =AW25+AV25+AU25+AT25 -> 0 | AX25: =AZ25+AY25+BA25 -> 0 | BE25: 0 | BF25: 是 | BG25: 确权资料
A26: 19 | B26: 林芝市 | C26: 察隅县 | D26: 2019 | E26: 察隅县上察隅镇土地综合治理项目 | F26: 是 | G26: 否 | H26: =I26+AF26 -> 3700000 | I26: =O26+J26+T26+Y26+AE26+AC26+AD26 -> 3700000 | J26: =N26+M26+L26+K26 -> 0 | O26: =S26+R26+Q26+P26 -> 3700000 | Q26: 2383600 | S26: 1316400 | T26: =U26+V26+W26+X26 -> 0 | Y26: =AA26+Z26+AB26 -> 0 | AG26: =AH26+BE26 -> 3395288.4 | AH26: =AN26+AI26+AS26+AX26+BD26+BB26+BC26 -> 3395288.4 | AI26: =AM26+AL26+AK26+AJ26 -> 0 | AN26: =AR26+AQ26+AP26+AO26 -> 3395288.4 | AP26: 2383600 | AR26: 1011688.4 | AS26: =AW26+AV26+AU26+AT26 -> 0 | AX26: =AZ26+AY26+BA26 -> 0 | BF26: 是 | BG26: 确权资料+50-1000万台账
A27: 20 | B27: 林芝市 | C27: 察隅县 | D27: 2019 | E27: 察隅县就业创业孵化基地维修改造工程 | F27: 是 | G27: 是 | H27: =I27+AF27 -> 500000 | I27: =O27+J27+T27+Y27+AE27+AC27+AD27 -> 500000 | J27: =N27+M27+L27+K27 -> 0 | O27: =S27+R27+Q27+P27 -> 500000 | P27: 500000 | T27: =U27+V27+W27+X27 -> 0 | Y27: =AA27+Z27+AB27 -> 0 | AG27: =AH27+BE27 -> 453000 | AH27: =AN27+AI27+AS27+AX27+BD27+BB27+BC27 -> 453000 | AI27: =AM27+AL27+AK27+AJ27 -> 0 | AN27: =AR27+AQ27+AP27+AO27 -> 453000 | AO27: 453000 | AS27: =AW27+AV27+AU27+AT27 -> 0 | AX27: =AZ27+AY27+BA27 -> 0 | BE27: 0 | BF27: 是 | BG27: 确权资料+立项批复 | BH27: 县人力资源和社会保障局
A28: 21 | B28: 林芝市 | C28: 察隅县 | D28: 2019 | E28: 察隅县易地扶贫集中安置点温室配套建设项目 | F28: 是 | G28: 是 | H28: =I28+AF28 -> 1434600 | I28: =O28+J28+T28+Y28+AE28+AC28+AD28 -> 1434600 | J28: =N28+M28+L28+K28 -> 0 | O28: =S28+R28+Q28+P28 -> 1434600 | P28: 940900 | Q28: 493700 | T28: =U28+V28+W28+X28 -> 0 | Y28: =AA28+Z28+AB28 -> 0 | AG28: =AH28+BE28 -> 1212126.3 | AH28: =AN28+AI28+AS28+AX28+BD28+BB28+BC28 -> 1212126.3 | AI28: =AM28+AL28+AK28+AJ28 -> 0 | AN28: =AR28+AQ28+AP28+AO28 -> 1212126.3 | AO28: 940900 | AP28: 271226.34 | AS28: =AW28+AV28+AU28+AT28 -> 0 | AX28: =AZ28+AY28+BA28 -> 0 | BE28: 0 | BF28: 是 | BG28: 确权资料
A29: 22 | B29: 林芝市 | C29: 察隅县 | D29: 2019 | E29: 察隅县竹瓦根镇扎拉村土地平整建设项目 | F29: 是 | G29: 否 | H29: =I29+AF29 -> 2800000 | I29: =O29+J29+T29+Y29+AE29+AC29+AD29 -> 2800000 | J29: =N29+M29+L29+K29 -> 0 | O29: =S29+R29+Q29+P29 -> 2800000 | P29: 819108.28 | S29: 1980891.7 | T29: =U29+V29+W29+X29 -> 0 | Y29: =AA29+Z29+AB29 -> 0 | AG29: =AH29+BE29 -> 2621588.9 | AH29: =AN29+AI29+AS29+AX29+BD29+BB29+BC29 -> 2621588.9 | AI29: =AM29+AL29+AK29+AJ29 -> 0 | AN29: =AR29+AQ29+AP29+AO29 -> 2621588.9 | AO29: 819108.28 | AR29: 1802480.6 | AS29: =AW29+AV29+AU29+AT29 -> 0 | AX29: =AZ29+AY29+BA29 -> 0 | BF29: 是 | BG29: 确权资料+50-1000万台账 | BH29: 竹瓦根镇人民政府
A30: 23 | B30: 林芝市 | C30: 察隅县 | D30: 2019 | E30: 察隅县上察隅镇仕中桥梁新建工程 | F30: 是 | G30: 否 | H30: =I30+AF30 -> 29434900 | I30: =O30+J30+T30+Y30+AE30+AC30+AD30 -> 29434900 | J30: =N30+M30+L30+K30 -> 0 | O30: =S30+R30+Q30+P30 -> 29434900 | P30: 497291.72 | Q30: 18234900 | S30: 10702708 | T30: =U30+V30+W30+X30 -> 0 | Y30: =AA30+Z30+AB30 -> 0 | AG30: =AH30+BE30 -> 29434900 | AH30: =AN30+AI30+AS30+AX30+BD30+BB30+BC30 -> 29434900 | AI30: =AM30+AL30+AK30+AJ30 -> 0 | AN30: =AR30+AQ30+AP30+AO30 -> 29434900 | AO30: 497291.72 | AP30: 18234900 | AR30: 10702708 | AS30: =AW30+AV30+AU30+AT30 -> 0 | AX30: =AZ30+AY30+BA30 -> 0 | BF30: 是 | BG30: 确权资料（确权金额和台账审定金额一致，但是没有支付财评） | BH30: 县交通运输局
A31: 24 | B31: 林芝市 | C31: 察隅县 | D31: 2019 | E31: 察隅县下察隅镇嘎腰村生产道路及桥梁建设项目 | F31: 是 | G31: 否 | H31: =I31+AF31 -> 800000 | I31: =O31+J31+T31+Y31+AE31+AC31+AD31 -> 800000 | J31: =N31+M31+L31+K31 -> 0 | O31: =S31+R31+Q31+P31 -> 800000 | P31: 200000 | Q31: 600000 | T31: =U31+V31+W31+X31 -> 0 | Y31: =AA31+Z31+AB31 -> 0 | AG31: =AH31+BE31 -> 800000 | AH31: =AN31+AI31+AS31+AX31+BD31+BB31+BC31 -> 800000 | AI31: =AM31+AL31+AK31+AJ31 -> 0 | AN31: =AR31+AQ31+AP31+AO31 -> 800000 | AO31: 200000 | AP31: 600000 | AS31: =AW31+AV31+AU31+AT31 -> 0 | AX31: =AZ31+AY31+BA31 -> 0 | BF31: 是 | BG31: 确权资料（确权金额和台账审定金额一致，但是没有支付财评） | BH31: 下察隅人民政府
A32: 25 | B32: 林芝市 | C32: 察隅县 | D32: 2019 | E32: 察隅县上察隅镇竹巴村温室大棚建设项目 | F32: 是 | G32: 是 | H32: =I32+AF32 -> 352000 | I32: =O32+J32+T32+Y32+AE32+AC32+AD32 -> 352000 | J32: =N32+M32+L32+K32 -> 0 | O32: =S32+R32+Q32+P32 -> 352000 | S32: 352000 | T32: =U32+V32+W32+X32 -> 0 | Y32: =AA32+Z32+AB32 -> 0 | AG32: =AH32+BE32 -> 352000 | AH32: =AN32+AI32+AS32+AX32+BD32+BB32+BC32 -> 352000 | AI32: =AM32+AL32+AK32+AJ32 -> 0 | AN32: =AR32+AQ32+AP32+AO32 -> 352000 | AR32: 352000 | AS32: =AW32+AV32+AU32+AT32 -> 0 | AX32: =AZ32+AY32+BA32 -> 0 | BE32: 0 | BF32: 是 | BG32: 确权资料，确权金额和台账审定金额一致，但是没有支付财评 | BH32: 上察隅镇人民政府
A33: 26 | B33: 林芝市 | C33: 察隅县 | D33: 2019 | E33: 察隅县竹瓦根镇嘎达村新建蓄水池项目 | F33: 是 | G33: 否 | H33: =I33+AF33 -> 216000 | I33: =O33+J33+T33+Y33+AE33+AC33+AD33 -> 216000 | J33: =N33+M33+L33+K33 -> 0 | O33: =S33+R33+Q33+P33 -> 216000 | P33: 216000 | T33: =U33+V33+W33+X33 -> 0 | Y33: =AA33+Z33+AB33 -> 0 | AG33: =AH33+BE33 -> 216000 | AH33: =AN33+AI33+AS33+AX33+BD33+BB33+BC33 -> 216000 | AI33: =AM33+AL33+AK33+AJ33 -> 0 | AN33: =AR33+AQ33+AP33+AO33 -> 216000 | AO33: 216000 | AS33: =AW33+AV33+AU33+AT33 -> 0 | AX33: =AZ33+AY33+BA33 -> 0 | BF33: 是 | BG33: 确权资料 | BH33: 竹瓦根镇人民政府
A34: 27 | B34: 林芝市 | C34: 察隅县 | D34: 2019 | E34: 察隅县竹瓦根镇知美村、曲瓦村新建温室大棚项目 | F34: 是 | G34: 是 | H34: =I34+AF34 -> 584000 | I34: =O34+J34+T34+Y34+AE34+AC34+AD34 -> 584000 | J34: =N34+M34+L34+K34 -> 0 | O34: =S34+R34+Q34+P34 -> 584000 | P34: 6080 | S34: 577920 | T34: =U34+V34+W34+X34 -> 0 | Y34: =AA34+Z34+AB34 -> 0 | AG34: =AH34+BE34 -> 584000 | AH34: =AN34+AI34+AS34+AX34+BD34+BB34+BC34 -> 584000 | AI34: =AM34+AL34+AK34+AJ34 -> 0 | AN34: =AR34+AQ34+AP34+AO34 -> 584000 | AO34: 6080 | AR34: 577920 | AS34: =AW34+AV34+AU34+AT34 -> 0 | AX34: =AZ34+AY34+BA34 -> 0 | BE34: 0 | BF34: 是 | BG34: 确权资料+项目资料 | BH34: 竹瓦根镇人民政府
A35: 28 | B35: 林芝市 | C35: 察隅县 | D35: 2019 | E35: 察隅县竹瓦根镇龙古村灌溉水渠改建工程 | F35: 是 | G35: 否 | H35: =I35+AF35 -> 1574100 | I35: =O35+J35+T35+Y35+AE35+AC35+AD35 -> 1574100 | J35: =N35+M35+L35+K35 -> 0 | O35: =S35+R35+Q35+P35 -> 1574100 | P35: 289500 | S35: 1284600 | T35: =U35+V35+W35+X35 -> 0 | Y35: =AA35+Z35+AB35 -> 0 | AG35: =AH35+BE35 -> 1415805.4 | AH35: =AN35+AI35+AS35+AX35+BD35+BB35+BC35 -> 1415805.4 | AI35: =AM35+AL35+AK35+AJ35 -> 0 | AN35: =AR35+AQ35+AP35+AO35 -> 1415805.4 | AO35: 289500 | AR35: 1126305.4 | AS35: =AW35+AV35+AU35+AT35 -> 0 | AX35: =AZ35+AY35+BA35 -> 0 | BF35: 是 | BG35: 确权资料+50-1000万台账
A36: 29 | B36: 林芝市 | C36: 察隅县 | D36: 2019 | E36: 察隅县下察隅镇共同村昂美组公路改建工程 | F36: 是 | G36: 否 | H36: =I36+AF36 -> 22890900 | I36: =O36+J36+T36+Y36+AE36+AC36+AD36 -> 22890900 | J36: =N36+M36+L36+K36 -> 0 | O36: =S36+R36+Q36+P36 -> 22890900 | S36: 22890900 | T36: =U36+V36+W36+X36 -> 0 | Y36: =AA36+Z36+AB36 -> 0 | AG36: =AH36+BE36 -> 22890900 | AH36: =AN36+AI36+AS36+AX36+BD36+BB36+BC36 -> 22890900 | AI36: =AM36+AL36+AK36+AJ36 -> 0 | AN36: =AR36+AQ36+AP36+AO36 -> 22890900 | AR36: 22890900 | AS36: =AW36+AV36+AU36+AT36 -> 0 | AX36: =AZ36+AY36+BA36 -> 0 | BF36: 是 | BG36: 确权资料+立项批复，审定金额来源不明，已经按22890900元确权
A37: 30 | B37: 林芝市 | C37: 察隅县 | D37: 2019 | E37: 察隅县下察隅镇自更村水渠建设工程 | F37: 是 | G37: 否 | H37: =I37+AF37 -> 945400 | I37: =O37+J37+T37+Y37+AE37+AC37+AD37 -> 945400 | J37: =N37+M37+L37+K37 -> 0 | O37: =S37+R37+Q37+P37 -> 945400 | P37: 945400 | T37: =U37+V37+W37+X37 -> 0 | Y37: =AA37+Z37+AB37 -> 0 | AG37: =AH37+BE37 -> 944500 | AH37: =AN37+AI37+AS37+AX37+BD37+BB37+BC37 -> 944500 | AI37: =AM37+AL37+AK37+AJ37 -> 0 | AN37: =AR37+AQ37+AP37+AO37 -> 944500 | AO37: 146620 | AP37: 797880 | AS37: =AW37+AV37+AU37+AT37 -> 0 | AX37: =AZ37+AY37+BA37 -> 0 | BF37: 是 | BG37: 确权资料+立项批复+50-1000万台账，审定金额来源不明，已经按945400元确权
A38: 31 | B38: 林芝市 | C38: 察隅县 | D38: 2019 | E38: 察隅县竹瓦根镇学尼村现代设施农业建设项目 | F38: 是 | G38: 是 | H38: =I38+AF38 -> 7500000 | I38: =O38+J38+T38+Y38+AE38+AC38+AD38 -> 7500000 | J38: =N38+M38+L38+K38 -> 0 | O38: =S38+R38+Q38+P38 -> 7500000 | P38: 7500000 | T38: =U38+V38+W38+X38 -> 0 | Y38: =AA38+Z38+AB38 -> 0 | AG38: =AH38+BE38 -> 7420825 | AH38: =AN38+AI38+AS38+AX38+BD38+BB38+BC38 -> 7420825 | AI38: =AM38+AL38+AK38+AJ38 -> 0 | AN38: =AR38+AQ38+AP38+AO38 -> 7420825 | AO38: 7420825 | AS38: =AW38+AV38+AU38+AT38 -> 0 | AX38: =AZ38+AY38+BA38 -> 0 | BE38: 0 | BF38: 是 | BG38: 确权资料+50-1000万台账
A39: 32 | B39: 林芝市 | C39: 察隅县 | D39: 2019 | E39: 林芝市察隅县2019年农村饮水安全巩固提升工程 | F39: 是 | G39: 否 | H39: =I39+AF39 -> 6954800 | I39: =O39+J39+T39+Y39+AE39+AC39+AD39 -> 6954800 | J39: =N39+M39+L39+K39 -> 0 | O39: =S39+R39+Q39+P39 -> 6954800 | P39: 2780000 | Q39: 4174800 | T39: =U39+V39+W39+X39 -> 0 | Y39: =AA39+Z39+AB39 -> 0 | AG39: =AH39+BE39 -> 6221460 | AH39: =AN39+AI39+AS39+AX39+BD39+BB39+BC39 -> 6221460 | AI39: =AM39+AL39+AK39+AJ39 -> 0 | AN39: =AR39+AQ39+AP39+AO39 -> 6221460 | AO39: 2780000 | AP39: 3441460 | AS39: =AW39+AV39+AU39+AT39 -> 0 | AX39: =AZ39+AY39+BA39 -> 0 | BF39: 是 | BG39: 确权资料+50-1000万台账 | BH39: 察隅县水利局
A40: 33 | B40: 林芝市 | C40: 察隅县 | D40: 2019 | E40: 察隅县古拉乡则巴村俄库组道路整治工程建 | F40: 是 | G40: 否 | H40: =I40+AF40 -> 965400 | I40: =O40+J40+T40+Y40+AE40+AC40+AD40 -> 965400 | J40: =N40+M40+L40+K40 -> 0 | O40: =S40+R40+Q40+P40 -> 965400 | P40: 965400 | T40: =U40+V40+W40+X40 -> 0 | Y40: =AA40+Z40+AB40 -> 0 | AG40: =AH40+BE40 -> 945500 | AH40: =AN40+AI40+AS40+AX40+BD40+BB40+BC40 -> 945500 | AI40: =AM40+AL40+AK40+AJ40 -> 0 | AN40: =AR40+AQ40+AP40+AO40 -> 945500 | AO40: 945500 | AS40: =AW40+AV40+AU40+AT40 -> 0 | AX40: =AZ40+AY40+BA40 -> 0 | BF40: 是 | BG40: 确权资料+50-1000万台账（审定金额无）+本项目按照945500确权 | BH40: 古拉乡人民政府
A41: 34 | B41: 林芝市 | C41: 察隅县 | D41: 2019 | E41: 察隅县古玉乡玉和村达达组主干道建设项目 | F41: 是 | G41: 否 | H41: =I41+AF41 -> 3924900 | I41: =O41+J41+T41+Y41+AE41+AC41+AD41 -> 3924900 | J41: =N41+M41+L41+K41 -> 0 | O41: =S41+R41+Q41+P41 -> 3924900 | P41: 3576800 | Q41: 348100 | T41: =U41+V41+W41+X41 -> 0 | Y41: =AA41+Z41+AB41 -> 0 | AG41: =AH41+BE41 -> 3854479.6 | AH41: =AN41+AI41+AS41+AX41+BD41+BB41+BC41 -> 3854479.6 | AI41: =AM41+AL41+AK41+AJ41 -> 0 | AN41: =AR41+AQ41+AP41+AO41 -> 3854479.6 | AO41: 3576800 | AP41: 277679.57 | AS41: =AW41+AV41+AU41+AT41 -> 0 | AX41: =AZ41+AY41+BA41 -> 0 | BF41: 是 | BG41: 确权资料
A42: 35 | B42: 林芝市 | C42: 察隅县 | D42: 2020 | E42: 察隅县产业扶贫竹巴村茶叶种植项目 | F42: 是 | G42: 是 | H42: =I42+AF42 -> 3600000 | I42: =O42+J42+T42+Y42+AE42+AC42+AD42 -> 2400000 | J42: =N42+M42+L42+K42 -> 0 | O42: =S42+R42+Q42+P42 -> 2400000 | P42: 2400000 | S42: 0 | T42: =U42+V42+W42+X42 -> 0 | Y42: =AA42+Z42+AB42 -> 0 | AF42: 1200000 | AG42: =AH42+BE42 -> 3600000 | AH42: =AN42+AI42+AS42+AX42+BD42+BB42+BC42 -> 2400000 | AI42: =AM42+AL42+AK42+AJ42 -> 0 | AN42: =AR42+AQ42+AP42+AO42 -> 2400000 | AO42: 2400000 | AS42: =AW42+AV42+AU42+AT42 -> 0 | AX42: =AZ42+AY42+BA42 -> 0 | BE42: 1200000 | BF42: 是 | BG42: 确权资料，按360万确权+项目资料 | BH42: 察隅县扶贫开发投资有限公司
A43: 36 | B43: 林芝市 | C43: 察隅县 | D43: 2020 | E43: 古拉乡安巴村石榴种植项目 | F43: 是 | G43: 是 | H43: =I43+AF43 -> 1370000 | I43: =O43+J43+T43+Y43+AE43+AC43+AD43 -> 1370000 | J43: =N43+M43+L43+K43 -> 0 | O43: =S43+R43+Q43+P43 -> 1370000 | S43: 1370000 | T43: =U43+V43+W43+X43 -> 0 | Y43: =AA43+Z43+AB43 -> 0 | AG43: =AH43+BE43 -> 1336574 | AH43: =AN43+AI43+AS43+AX43+BD43+BB43+BC43 -> 1336574 | AI43: =AM43+AL43+AK43+AJ43 -> 0 | AN43: =AR43+AQ43+AP43+AO43 -> 1336574 | AR43: 1336574 | AS43: =AW43+AV43+AU43+AT43 -> 0 | AX43: =AZ43+AY43+BA43 -> 0 | BE43: 0 | BF43: 是 | BG43: 确权资料
A44: 37 | B44: 林芝市 | C44: 察隅县 | D44: 2020 | E44: 察隅县察瓦龙乡龙布村羊肚菌种植项目 | F44: 是 | G44: 是 | H44: =I44+AF44 -> 500000 | I44: =O44+J44+T44+Y44+AE44+AC44+AD44 -> 500000 | J44: =N44+M44+L44+K44 -> 0 | O44: =S44+R44+Q44+P44 -> 350000 | Q44: 350000 | T44: =U44+V44+W44+X44 -> 150000 | U44: 150000 | Y44: =AA44+Z44+AB44 -> 0 | AG44: =AH44+BE44 -> 500000 | AH44: =AN44+AI44+AS44+AX44+BD44+BB44+BC44 -> 500000 | AI44: =AM44+AL44+AK44+AJ44 -> 0 | AN44: =AR44+AQ44+AP44+AO44 -> 350000 | AP44: 350000 | AS44: =AW44+AV44+AU44+AT44 -> 150000 | AT44: 150000 | AX44: =AZ44+AY44+BA44 -> 0 | BE44: 0 | BF44: 是 | BG44: 确权资料 | BH44: 察瓦龙乡人民政府
A45: 38 | B45: 林芝市 | C45: 察隅县 | D45: 2020 | E45: 察隅县察瓦龙乡龙布村灵芝种植项目 | F45: 是 | G45: 是 | H45: =I45+AF45 -> 500000 | I45: =O45+J45+T45+Y45+AE45+AC45+AD45 -> 500000 | J45: =N45+M45+L45+K45 -> 0 | O45: =S45+R45+Q45+P45 -> 350000 | Q45: 350000 | T45: =U45+V45+W45+X45 -> 150000 | U45: 150000 | Y45: =AA45+Z45+AB45 -> 0 | AG45: =AH45+BE45 -> 500000 | AH45: =AN45+AI45+AS45+AX45+BD45+BB45+BC45 -> 500000 | AI45: =AM45+AL45+AK45+AJ45 -> 0 | AN45: =AR45+AQ45+AP45+AO45 -> 350000 | AP45: 350000 | AS45: =AW45+AV45+AU45+AT45 -> 150000 | AT45: 150000 | AX45: =AZ45+AY45+BA45 -> 0 | BE45: 0 | BF45: 是 | BG45: 确权资料 | BH45: 察瓦龙乡人民政府
A46: 39 | B46: 林芝市 | C46: 察隅县 | D46: 2020 | E46: 察隅县下察隅镇京都村柑橘项目 | F46: 是 | G46: 是 | H46: =I46+AF46 -> 600000 | I46: =O46+J46+T46+Y46+AE46+AC46+AD46 -> 600000 | J46: =N46+M46+L46+K46 -> 0 | O46: =S46+R46+Q46+P46 -> 600000 | Q46: 600000 | T46: =U46+V46+W46+X46 -> 0 | Y46: =AA46+Z46+AB46 -> 0 | AG46: =AH46+BE46 -> 593600 | AH46: =AN46+AI46+AS46+AX46+BD46+BB46+BC46 -> 593600 | AI46: =AM46+AL46+AK46+AJ46 -> 0 | AN46: =AR46+AQ46+AP46+AO46 -> 593600 | AP46: 593600 | AS46: =AW46+AV46+AU46+AT46 -> 0 | AX46: =AZ46+AY46+BA46 -> 0 | BE46: 0 | BF46: 是 | BG46: 确权资料+50-1000万财评统计表（没有审定金额），台账审定金额来源待查 | BH46: 察隅县扶贫开发办公室
A47: 40 | B47: 林芝市 | C47: 察隅县 | D47: 2020 | E47: 察隅县察瓦龙乡拉卡村软籽石榴种植项目 | F47: 是 | G47: 是 | H47: =I47+AF47 -> 1660000 | I47: =O47+J47+T47+Y47+AE47+AC47+AD47 -> 1660000 | J47: =N47+M47+L47+K47 -> 0 | O47: =S47+R47+Q47+P47 -> 662400 | Q47: 662400 | T47: =U47+V47+W47+X47 -> 997600 | U47: 997600 | Y47: =AA47+Z47+AB47 -> 0 | AG47: =AH47+BE47 -> 1660000 | AH47: =AN47+AI47+AS47+AX47+BD47+BB47+BC47 -> 1660000 | AI47: =AM47+AL47+AK47+AJ47 -> 0 | AN47: =AR47+AQ47+AP47+AO47 -> 662400 | AP47: 662400 | AS47: =AW47+AV47+AU47+AT47 -> 997600 | AT47: 997600 | AX47: =AZ47+AY47+BA47 -> 0 | BE47: 0 | BF47: 是 | BG47: 确权资料
A48: 41 | B48: 林芝市 | C48: 察隅县 | D48: 2020 | E48: 察隅县察瓦龙乡龙普村软籽石榴种植项目 | F48: 是 | G48: 是 | H48: =I48+AF48 -> 3910700 | I48: =O48+J48+T48+Y48+AE48+AC48+AD48 -> 3910700 | J48: =N48+M48+L48+K48 -> 0 | O48: =S48+R48+Q48+P48 -> 1458200 | Q48: 1458200 | T48: =U48+V48+W48+X48 -> 2452500 | U48: 2452500 | Y48: =AA48+Z48+AB48 -> 0 | AG48: =AH48+BE48 -> 3910700 | AH48: =AN48+AI48+AS48+AX48+BD48+BB48+BC48 -> 3910700 | AI48: =AM48+AL48+AK48+AJ48 -> 0 | AN48: =AR48+AQ48+AP48+AO48 -> 1458200 | AP48: 1458200 | AS48: =AW48+AV48+AU48+AT48 -> 2452500 | AT48: 2452500 | AX48: =AZ48+AY48+BA48 -> 0 | BE48: 0 | BF48: 是 | BG48: 确权资料（确权金额和台账审定金额不一致，但是没有支付财评） | BH48: 察隅县农业农村局
A49: 42 | B49: 林芝市 | C49: 察隅县 | D49: 2020 | E49: 察隅县察瓦龙乡昌西村软籽石榴种植项目 | F49: 是 | G49: 是 | H49: =I49+AF49 -> 1736400 | I49: =O49+J49+T49+Y49+AE49+AC49+AD49 -> 1736400 | J49: =N49+M49+L49+K49 -> 0 | O49: =S49+R49+Q49+P49 -> 720000 | Q49: 720000 | T49: =U49+V49+W49+X49 -> 1016400 | U49: 1016400 | Y49: =AA49+Z49+AB49 -> 0 | AG49: =AH49+BE49 -> 1736400 | AH49: =AN49+AI49+AS49+AX49+BD49+BB49+BC49 -> 1736400 | AI49: =AM49+AL49+AK49+AJ49 -> 0 | AN49: =AR49+AQ49+AP49+AO49 -> 720000 | AP49: 720000 | AS49: =AW49+AV49+AU49+AT49 -> 1016400 | AT49: 1016400 | AX49: =AZ49+AY49+BA49 -> 0 | BE49: 0 | BF49: 是 | BG49: 确权资料，审定金额待定 | BH49: 察隅县农业农村局
A50: 43 | B50: 林芝市 | C50: 察隅县 | D50: 2020 | E50: 古玉乡然乌学村农田灌溉水利设施建设项目 | F50: 是 | G50: 否 | H50: =I50+AF50 -> 800000 | I50: =O50+J50+T50+Y50+AE50+AC50+AD50 -> 800000 | J50: =N50+M50+L50+K50 -> 0 | O50: =S50+R50+Q50+P50 -> 560000 | Q50: 560000 | T50: =U50+V50+W50+X50 -> 240000 | V50: 240000 | Y50: =AA50+Z50+AB50 -> 0 | AG50: =AH50+BE50 -> 779600 | AH50: =AN50+AI50+AS50+AX50+BD50+BB50+BC50 -> 779600 | AI50: =AM50+AL50+AK50+AJ50 -> 0 | AN50: =AR50+AQ50+AP50+AO50 -> 560000 | AP50: 560000 | AS50: =AW50+AV50+AU50+AT50 -> 219600 | AU50: 219600 | AX50: =AZ50+AY50+BA50 -> 0 | BF50: 是 | BG50: 确权资料+50-1000万台账，本项目确权金额和台账金额一致，但审定金额来源需核实
A51: 44 | B51: 林芝市 | C51: 察隅县 | D51: 2020 | E51: 察隅县古拉乡俄玉村农田灌溉水渠建设项目 | F51: 是 | G51: 否 | H51: =I51+AF51 -> 1430000 | I51: =O51+J51+T51+Y51+AE51+AC51+AD51 -> 1430000 | J51: =N51+M51+L51+K51 -> 0 | O51: =S51+R51+Q51+P51 -> 1000000 | Q51: 1000000 | T51: =U51+V51+W51+X51 -> 430000 | V51: 430000 | Y51: =AA51+Z51+AB51 -> 0 | AG51: =AH51+BE51 -> 1388080.1 | AH51: =AN51+AI51+AS51+AX51+BD51+BB51+BC51 -> 1388080.1 | AI51: =AM51+AL51+AK51+AJ51 -> 0 | AN51: =AR51+AQ51+AP51+AO51 -> 1000000 | AP51: 1000000 | AS51: =AW51+AV51+AU51+AT51 -> 388080.15 | AU51: 388080.15 | AX51: =AZ51+AY51+BA51 -> 0 | BF51: 是 | BG51: 确权资料+50-1000万台账 | BH51: 察隅县扶贫开发办公室
A52: 45 | B52: 林芝市 | C52: 察隅县 | D52: 2020 | E52: 察隅县下察隅镇拉丁、布巴村农村饮水安全巩固提升工程 | F52: 是 | G52: 否 | H52: =I52+AF52 -> 1677900 | I52: =O52+J52+T52+Y52+AE52+AC52+AD52 -> 1677900 | J52: =N52+M52+L52+K52 -> 0 | O52: =S52+R52+Q52+P52 -> 1677900 | P52: 1677900 | T52: =U52+V52+W52+X52 -> 0 | Y52: =AA52+Z52+AB52 -> 0 | AG52: =AH52+BE52 -> 1579876.4 | AH52: =AN52+AI52+AS52+AX52+BD52+BB52+BC52 -> 1579876.4 | AI52: =AM52+AL52+AK52+AJ52 -> 0 | AN52: =AR52+AQ52+AP52+AO52 -> 1579876.4 | AO52: 1579876.4 | AS52: =AW52+AV52+AU52+AT52 -> 0 | AX52: =AZ52+AY52+BA52 -> 0 | BF52: 是 | BG52: 确权资料+50-1000万台账
A53: 46 | B53: 林芝市 | C53: 察隅县 | D53: 2020 | E53: 察隅县古玉乡博学村堆拉组水渠建设项目 | F53: 是 | G53: 否 | H53: =I53+AF53 -> 600000 | I53: =O53+J53+T53+Y53+AE53+AC53+AD53 -> 600000 | J53: =N53+M53+L53+K53 -> 0 | O53: =S53+R53+Q53+P53 -> 600000 | P53: 600000 | T53: =U53+V53+W53+X53 -> 0 | Y53: =AA53+Z53+AB53 -> 0 | AG53: =AH53+BE53 -> 600000 | AH53: =AN53+AI53+AS53+AX53+BD53+BB53+BC53 -> 600000 | AI53: =AM53+AL53+AK53+AJ53 -> 0 | AN53: =AR53+AQ53+AP53+AO53 -> 600000 | AO53: 600000 | AS53: =AW53+AV53+AU53+AT53 -> 0 | AX53: =AZ53+AY53+BA53 -> 0 | BF53: 疑似确权 | BG53: 确权资料 | BH53: 古玉乡人民政府
A54: 47 | B54: 林芝市 | C54: 察隅县 | D54: 2020 | E54: 察隅县2020年农村饮水安全设施维修改造工程 | F54: 是 | G54: 否 | H54: =I54+AF54 -> 3500000 | I54: =O54+J54+T54+Y54+AE54+AC54+AD54 -> 3500000 | J54: =N54+M54+L54+K54 -> 0 | O54: =S54+R54+Q54+P54 -> 3500000 | Q54: 700000 | S54: 2800000 | T54: =U54+V54+W54+X54 -> 0 | Y54: =AA54+Z54+AB54 -> 0 | AG54: =AH54+BE54 -> 3412694 | AH54: =AN54+AI54+AS54+AX54+BD54+BB54+BC54 -> 3412694 | AI54: =AM54+AL54+AK54+AJ54 -> 0 | AN54: =AR54+AQ54+AP54+AO54 -> 3412694 | AP54: 700000 | AR54: 2712694 | AS54: =AW54+AV54+AU54+AT54 -> 0 | AX54: =AZ54+AY54+BA54 -> 0 | BF54: 是 | BG54: 确权资料+50-1000万台账 | BH54: 察隅县水利局
A55: 48 | B55: 林芝市 | C55: 察隅县 | D55: 2020 | E55: 察隅县下察隅镇布巴村石围墙建设项目 | F55: 是 | G55: 否 | H55: =I55+AF55 -> 269200 | I55: =O55+J55+T55+Y55+AE55+AC55+AD55 -> 269200 | J55: =N55+M55+L55+K55 -> 0 | O55: =S55+R55+Q55+P55 -> 269200 | S55: 269200 | T55: =U55+V55+W55+X55 -> 0 | Y55: =AA55+Z55+AB55 -> 0 | AG55: =AH55+BE55 -> 269200 | AH55: =AN55+AI55+AS55+AX55+BD55+BB55+BC55 -> 269200 | AI55: =AM55+AL55+AK55+AJ55 -> 0 | AN55: =AR55+AQ55+AP55+AO55 -> 269200 | AR55: 269200 | AS55: =AW55+AV55+AU55+AT55 -> 0 | AX55: =AZ55+AY55+BA55 -> 0 | BF55: 是 | BG55: 确权资料，台账审定金额来源待确定，已经按269200确权
A56: 49 | B56: 林芝市 | C56: 察隅县 | D56: 2020 | E56: 察隅县下察隅镇竹尼片区农田围墙建设项目 | F56: 是 | G56: 否 | H56: =I56+AF56 -> 1726800 | I56: =O56+J56+T56+Y56+AE56+AC56+AD56 -> 1726800 | J56: =N56+M56+L56+K56 -> 0 | O56: =S56+R56+Q56+P56 -> 1726800 | S56: 1726800 | T56: =U56+V56+W56+X56 -> 0 | Y56: =AA56+Z56+AB56 -> 0 | AG56: =AH56+BE56 -> 1662051.9 | AH56: =AN56+AI56+AS56+AX56+BD56+BB56+BC56 -> 1662051.9 | AI56: =AM56+AL56+AK56+AJ56 -> 0 | AN56: =AR56+AQ56+AP56+AO56 -> 1662051.9 | AR56: 1662051.9 | AS56: =AW56+AV56+AU56+AT56 -> 0 | AX56: =AZ56+AY56+BA56 -> 0 | BF56: 是 | BG56: 确权资料+50-1000万台账+立项批复
A57: 50 | B57: 林芝市 | C57: 察隅县 | D57: 2020 | E57: 察隅县竹瓦根镇雄久村基础设施建设项目 | F57: 是 | G57: 否 | H57: =I57+AF57 -> 1000000 | I57: =O57+J57+T57+Y57+AE57+AC57+AD57 -> 1000000 | J57: =N57+M57+L57+K57 -> 0 | O57: =S57+R57+Q57+P57 -> 700000 | Q57: 700000 | T57: =U57+V57+W57+X57 -> 300000 | V57: 300000 | Y57: =AA57+Z57+AB57 -> 0 | AG57: =AH57+BE57 -> 889389.09 | AH57: =AN57+AI57+AS57+AX57+BD57+BB57+BC57 -> 889389.09 | AI57: =AM57+AL57+AK57+AJ57 -> 0 | AN57: =AR57+AQ57+AP57+AO57 -> 700000 | AP57: 700000 | AS57: =AW57+AV57+AU57+AT57 -> 189389.09 | AU57: 189389.09 | AX57: =AZ57+AY57+BA57 -> 0 | BF57: 是 | BG57: 确权资料+50-1000万台账 | BH57: 竹瓦根镇人民政府
A58: 51 | B58: 林芝市 | C58: 察隅县 | D58: 2020 | E58: 察隅县察瓦龙乡扎那村机耕道建设项目 | F58: 是 | G58: 否 | H58: =I58+AF58 -> 292400 | I58: =O58+J58+T58+Y58+AE58+AC58+AD58 -> 292400 | J58: =N58+M58+L58+K58 -> 0 | O58: =S58+R58+Q58+P58 -> 292400 | Q58: 292400 | T58: =U58+V58+W58+X58 -> 0 | Y58: =AA58+Z58+AB58 -> 0 | AG58: =AH58+BE58 -> 283900 | AH58: =AN58+AI58+AS58+AX58+BD58+BB58+BC58 -> 283900 | AI58: =AM58+AL58+AK58+AJ58 -> 0 | AN58: =AR58+AQ58+AP58+AO58 -> 283900 | AP58: 283900 | AS58: =AW58+AV58+AU58+AT58 -> 0 | AX58: =AZ58+AY58+BA58 -> 0 | BF58: 是 | BG58: 确权资料，确权金额和台账审定金额一致，但是没有支付财评 | BH58: 察隅县扶贫开发办公室
A59: 52 | B59: 林芝市 | C59: 察隅县 | D59: 2020 | E59: 察隅县察瓦龙乡龙布村安全饮水工程建设项目 | F59: 是 | G59: 否 | H59: =I59+AF59 -> 2958600 | I59: =O59+J59+T59+Y59+AE59+AC59+AD59 -> 2958600 | J59: =N59+M59+L59+K59 -> 0 | O59: =S59+R59+Q59+P59 -> 2000000 | Q59: 2000000 | T59: =U59+V59+W59+X59 -> 958600 | V59: 958600 | Y59: =AA59+Z59+AB59 -> 0 | AG59: =AH59+BE59 -> 2820671.9 | AH59: =AN59+AI59+AS59+AX59+BD59+BB59+BC59 -> 2820671.9 | AI59: =AM59+AL59+AK59+AJ59 -> 0 | AN59: =AR59+AQ59+AP59+AO59 -> 2000000 | AP59: 2000000 | AS59: =AW59+AV59+AU59+AT59 -> 820671.88 | AU59: 820671.88 | AX59: =AZ59+AY59+BA59 -> 0 | BF59: 是 | BG59: 确权资料
A60: 53 | B60: 林芝市 | C60: 察隅县 | D60: 2020 | E60: 察隅县古拉乡俄玉村土地提升改造项目 | F60: 是 | G60: 否 | H60: =I60+AF60 -> 1500000 | I60: =O60+J60+T60+Y60+AE60+AC60+AD60 -> 1500000 | J60: =N60+M60+L60+K60 -> 0 | O60: =S60+R60+Q60+P60 -> 1200000 | Q60: 1200000 | T60: =U60+V60+W60+X60 -> 300000 | V60: 300000 | Y60: =AA60+Z60+AB60 -> 0 | AG60: =AH60+BE60 -> 1449424.8 | AH60: =AN60+AI60+AS60+AX60+BD60+BB60+BC60 -> 1449424.8 | AI60: =AM60+AL60+AK60+AJ60 -> 0 | AN60: =AR60+AQ60+AP60+AO60 -> 1200000 | AP60: 1200000 | AS60: =AW60+AV60+AU60+AT60 -> 249424.84 | AU60: 249424.84 | AX60: =AZ60+AY60+BA60 -> 0 | BF60: 是 | BG60: 确权资料+50-1000万台账 | BH60: 察隅县扶贫开发办公室
A61: 54 | B61: 林芝市 | C61: 察隅县 | D61: 2020 | E61: 察隅县上察隅镇格拥村茶叶种植项目 | F61: 是 | G61: 是 | H61: =I61+AF61 -> 3058500 | I61: =O61+J61+T61+Y61+AE61+AC61+AD61 -> 3058500 | J61: =N61+M61+L61+K61 -> 0 | O61: =S61+R61+Q61+P61 -> 3058500 | Q61: 3058500 | T61: =U61+V61+W61+X61 -> 0 | Y61: =AA61+Z61+AB61 -> 0 | AG61: =AH61+BE61 -> 2951204.7 | AH61: =AN61+AI61+AS61+AX61+BD61+BB61+BC61 -> 2951204.7 | AI61: =AM61+AL61+AK61+AJ61 -> 0 | AN61: =AR61+AQ61+AP61+AO61 -> 2951204.7 | AP61: 2951204.7 | AS61: =AW61+AV61+AU61+AT61 -> 0 | AX61: =AZ61+AY61+BA61 -> 0 | BE61: 0 | BF61: 是 | BG61: 确权资料+50-1000万台账 | BH61: 察隅县农业农村局
A62: 55 | B62: 林芝市 | C62: 察隅县 | D62: 2020 | E62: 察隅县古拉乡关龙村人居环境综合整治项目 | F62: 是 | G62: 否 | H62: =I62+AF62 -> 9500000 | I62: =O62+J62+T62+Y62+AE62+AC62+AD62 -> 9500000 | J62: =N62+M62+L62+K62 -> 0 | O62: =S62+R62+Q62+P62 -> 0 | T62: =U62+V62+W62+X62 -> 9500000 | U62: 9500000 | Y62: =AA62+Z62+AB62 -> 0 | AG62: =AH62+BE62 -> 9217227.3 | AH62: =AN62+AI62+AS62+AX62+BD62+BB62+BC62 -> 9217227.3 | AI62: =AM62+AL62+AK62+AJ62 -> 0 | AN62: =AR62+AQ62+AP62+AO62 -> 0 | AS62: =AW62+AV62+AU62+AT62 -> 9217227.3 | AT62: 9217227.3 | AX62: =AZ62+AY62+BA62 -> 0 | BF62: 否 | BG62: 立项批复+50-1000万台账 | BH62: 县脱贫攻坚指挥部办公室（扶贫办）
A63: 56 | B63: 林芝市 | C63: 察隅县 | D63: 2020 | E63: 察隅县察瓦龙乡扎那村软籽石榴种植项目 | F63: 是 | G63: 是 | H63: =I63+AF63 -> 1400000 | I63: =O63+J63+T63+Y63+AE63+AC63+AD63 -> 1400000 | J63: =N63+M63+L63+K63 -> 0 | O63: =S63+R63+Q63+P63 -> 588000 | Q63: 588000 | T63: =U63+V63+W63+X63 -> 812000 | U63: 812000 | Y63: =AA63+Z63+AB63 -> 0 | AG63: =AH63+BE63 -> 1253700.2 | AH63: =AN63+AI63+AS63+AX63+BD63+BB63+BC63 -> 1253700.2 | AI63: =AM63+AL63+AK63+AJ63 -> 0 | AN63: =AR63+AQ63+AP63+AO63 -> 588000 | AP63: 588000 | AS63: =AW63+AV63+AU63+AT63 -> 665700.18 | AT63: 665700.18 | AX63: =AZ63+AY63+BA63 -> 0 | BE63: 0 | BF63: 是 | BG63: 确权资料
A64: 57 | B64: 林芝市 | C64: 察隅县 | D64: 2021 | E64: 察隅县上察隅镇到户产业温室大棚维修项目 | F64: 是 | G64: 否 | H64: =I64+AF64 -> 230600 | I64: =O64+J64+T64+Y64+AE64+AC64+AD64 -> 230600 | J64: =N64+M64+L64+K64 -> 0 | O64: =S64+R64+Q64+P64 -> 230600 | S64: 230600 | T64: =U64+V64+W64+X64 -> 0 | Y64: =AA64+Z64+AB64 -> 0 | AG64: =AH64+BE64 -> 230600 | AH64: =AN64+AI64+AS64+AX64+BD64+BB64+BC64 -> 230600 | AI64: =AM64+AL64+AK64+AJ64 -> 0 | AN64: =AR64+AQ64+AP64+AO64 -> 230600 | AR64: 230600 | AS64: =AW64+AV64+AU64+AT64 -> 0 | AX64: =AZ64+AY64+BA64 -> 0 | BF64: 否 | BG64: 无资料
A65: 58 | B65: 林芝市 | C65: 察隅县 | D65: 2021 | E65: 察隅县察瓦龙乡大流沙石榴种植项目 | F65: 是 | G65: 是 | H65: =I65+AF65 -> 2010000 | I65: =O65+J65+T65+Y65+AE65+AC65+AD65 -> 2010000 | J65: =N65+M65+L65+K65 -> 0 | O65: =S65+R65+Q65+P65 -> 0 | T65: =U65+V65+W65+X65 -> 2010000 | U65: 2010000 | Y65: =AA65+Z65+AB65 -> 0 | AG65: =AH65+BE65 -> 2010000 | AH65: =AN65+AI65+AS65+AX65+BD65+BB65+BC65 -> 2010000 | AI65: =AM65+AL65+AK65+AJ65 -> 0 | AN65: =AR65+AQ65+AP65+AO65 -> 0 | AS65: =AW65+AV65+AU65+AT65 -> 2010000 | AT65: 2010000 | AX65: =AZ65+AY65+BA65 -> 0 | BE65: 0 | BF65: 否 | BG65: 立项批复+还未财评 | BH65: 察隅县乡村振兴局
A66: 59 | B66: 林芝市 | C66: 察隅县 | D66: 2021 | E66: 察隅县察瓦龙乡阿丙村石榴种植项目三期 | F66: 是 | G66: 是 | H66: =I66+AF66 -> 1460000 | I66: =O66+J66+T66+Y66+AE66+AC66+AD66 -> 1460000 | J66: =N66+M66+L66+K66 -> 0 | O66: =S66+R66+Q66+P66 -> 0 | T66: =U66+V66+W66+X66 -> 1460000 | U66: 1460000 | Y66: =AA66+Z66+AB66 -> 0 | AG66: =AH66+BE66 -> 1299328.3 | AH66: =AN66+AI66+AS66+AX66+BD66+BB66+BC66 -> 1299328.3 | AI66: =AM66+AL66+AK66+AJ66 -> 0 | AN66: =AR66+AQ66+AP66+AO66 -> 0 | AS66: =AW66+AV66+AU66+AT66 -> 1299328.3 | AT66: 1299328.3 | AX66: =AZ66+AY66+BA66 -> 0 | BE66: 0 | BF66: 否 | BG66: 概批+50-1000万财评台账
A67: 60 | B67: 林芝市 | C67: 察隅县 | D67: 2021 | E67: 察隅县察瓦龙乡格布、龙布等村入户道路建设项目 | F67: 是 | G67: 否 | H67: =I67+AF67 -> 2136400 | I67: =O67+J67+T67+Y67+AE67+AC67+AD67 -> 2136400 | J67: =N67+M67+L67+K67 -> 0 | O67: =S67+R67+Q67+P67 -> 0 | T67: =U67+V67+W67+X67 -> 2136400 | X67: 2136400 | Y67: =AA67+Z67+AB67 -> 0 | AG67: =AH67+BE67 -> 2001888.5 | AH67: =AN67+AI67+AS67+AX67+BD67+BB67+BC67 -> 2001888.5 | AI67: =AM67+AL67+AK67+AJ67 -> 0 | AN67: =AR67+AQ67+AP67+AO67 -> 0 | AS67: =AW67+AV67+AU67+AT67 -> 2001888.5 | AW67: 2001888.5 | AX67: =AZ67+AY67+BA67 -> 0 | BF67: 否 | BG67: 立项批复+50-1000万台账 | BH67: 察隅县乡村振兴局
A68: 61 | B68: 林芝市 | C68: 察隅县 | D68: 2021 | E68: 察隅县上察隅镇仕中、阿扎等村入户道路项目 | F68: 是 | G68: 否 | H68: =I68+AF68 -> 3700000 | I68: =O68+J68+T68+Y68+AE68+AC68+AD68 -> 3700000 | J68: =N68+M68+L68+K68 -> 0 | O68: =S68+R68+Q68+P68 -> 0 | T68: =U68+V68+W68+X68 -> 3700000 | X68: 3700000 | Y68: =AA68+Z68+AB68 -> 0 | AG68: =AH68+BE68 -> 3594286.6 | AH68: =AN68+AI68+AS68+AX68+BD68+BB68+BC68 -> 3594286.6 | AI68: =AM68+AL68+AK68+AJ68 -> 0 | AN68: =AR68+AQ68+AP68+AO68 -> 0 | AS68: =AW68+AV68+AU68+AT68 -> 3594286.6 | AW68: 3594286.6 | AX68: =AZ68+AY68+BA68 -> 0 | BF68: 否 | BG68: 立项+50-1000万台账 | BH68: 察隅县乡村振兴局
A69: 62 | B69: 林芝市 | C69: 察隅县 | D69: 2022 | E69: 察隅县竹瓦根镇高寒牧区高产养殖项目二期 | F69: 是 | G69: 是 | H69: =I69+AF69 -> 3940000 | I69: =O69+J69+T69+Y69+AE69+AC69+AD69 -> 3940000 | J69: =N69+M69+L69+K69 -> 0 | O69: =S69+R69+Q69+P69 -> 3940000 | P69: 3940000 | T69: =U69+V69+W69+X69 -> 0 | Y69: =AA69+Z69+AB69 -> 0 | AG69: =AH69+BE69 -> 3833264.5 | AH69: =AN69+AI69+AS69+AX69+BD69+BB69+BC69 -> 3833264.5 | AI69: =AM69+AL69+AK69+AJ69 -> 0 | AN69: =AR69+AQ69+AP69+AO69 -> 3833264.5 | AO69: 3833264.5 | AS69: =AW69+AV69+AU69+AT69 -> 0 | AX69: =AZ69+AY69+BA69 -> 0 | BE69: 0 | BF69: 否 | BG69: 立项+50-1000万台账 | BH69: 察隅县农业农村局
A70: 63 | B70: 林芝市 | C70: 察隅县 | D70: 2022 | E70: 察隅县下察隅镇夏尼村基础设施建设项目 | F70: 是 | G70: 否 | H70: =I70+AF70 -> 3091500 | I70: =O70+J70+T70+Y70+AE70+AC70+AD70 -> 3091500 | J70: =N70+M70+L70+K70 -> 0 | O70: =S70+R70+Q70+P70 -> 0 | T70: =U70+V70+W70+X70 -> 3091500 | U70: 3091500 | Y70: =AA70+Z70+AB70 -> 0 | AG70: =AH70+BE70 -> 2934852.2 | AH70: =AN70+AI70+AS70+AX70+BD70+BB70+BC70 -> 2934852.2 | AI70: =AM70+AL70+AK70+AJ70 -> 0 | AN70: =AR70+AQ70+AP70+AO70 -> 0 | AS70: =AW70+AV70+AU70+AT70 -> 2934852.2 | AT70: 2934852.2 | AX70: =AZ70+AY70+BA70 -> 0 | BF70: 否 | BG70: 立项批复+财评+50-1000万台账 | BH70: 察隅县乡村振兴局
A71: 64 | B71: 林芝市 | C71: 察隅县 | D71: 2022 | E71: 察隅县下察隅镇沙玛村基础设施建设项目 | F71: 是 | G71: 否 | H71: =I71+AF71 -> 13204000 | I71: =O71+J71+T71+Y71+AE71+AC71+AD71 -> 13204000 | J71: =N71+M71+L71+K71 -> 0 | O71: =S71+R71+Q71+P71 -> 0 | T71: =U71+V71+W71+X71 -> 13204000 | U71: 6525000 | W71: 630000 | X71: 6049000 | Y71: =AA71+Z71+AB71 -> 0 | AG71: =AH71+BE71 -> 12709025 | AH71: =AN71+AI71+AS71+AX71+BD71+BB71+BC71 -> 12709025 | AI71: =AM71+AL71+AK71+AJ71 -> 0 | AN71: =AR71+AQ71+AP71+AO71 -> 0 | AS71: =AW71+AV71+AU71+AT71 -> 12709025 | AT71: 6525000 | AV71: 630000 | AW71: 5554025.1 | AX71: =AZ71+AY71+BA71 -> 0 | BF71: 否 | BG71: 立项批复+财评 | BH71: 察隅县乡村振兴局
A72: 65 | B72: 林芝市 | C72: 察隅县 | D72: 2022 | E72: 察隅县古玉乡巴依、玉和村犏牛养殖项目 | F72: 是 | G72: 是 | H72: =I72+AF72 -> 9758900 | I72: =O72+J72+T72+Y72+AE72+AC72+AD72 -> 9758900 | J72: =N72+M72+L72+K72 -> 0 | O72: =S72+R72+Q72+P72 -> 0 | T72: =U72+V72+W72+X72 -> 9758900 | U72: 6831230 | V72: 2927670 | Y72: =AA72+Z72+AB72 -> 0 | AG72: =AH72+BE72 -> 9452089.8 | AH72: =AN72+AI72+AS72+AX72+BD72+BB72+BC72 -> 9452089.8 | AI72: =AM72+AL72+AK72+AJ72 -> 0 | AN72: =AR72+AQ72+AP72+AO72 -> 0 | AS72: =AW72+AV72+AU72+AT72 -> 9452089.8 | AT72: 6831230 | AU72: 2620859.8 | AX72: =AZ72+AY72+BA72 -> 0 | BE72: 0 | BF72: 否 | BG72: 财评+50-1000万台账 | BH72: 察隅县乡村振兴局
A73: 66 | B73: 林芝市 | C73: 察隅县 | D73: 2016 | E73: 察隅县2022年察瓦龙乡目巴村提升改造项目 | F73: 是 | G73: 否 | H73: =I73+AF73 -> 2800000 | I73: =O73+J73+T73+Y73+AE73+AC73+AD73 -> 2800000 | J73: =N73+M73+L73+K73 -> 0 | O73: =S73+R73+Q73+P73 -> 2800000 | P73: 2800000 | T73: =U73+V73+W73+X73 -> 0 | Y73: =AA73+Z73+AB73 -> 0 | AG73: =AH73+BE73 -> 2620668.8 | AH73: =AN73+AI73+AS73+AX73+BD73+BB73+BC73 -> 2620668.8 | AI73: =AM73+AL73+AK73+AJ73 -> 0 | AN73: =AR73+AQ73+AP73+AO73 -> 2620668.8 | AO73: 2620668.8 | AS73: =AW73+AV73+AU73+AT73 -> 0 | AX73: =AZ73+AY73+BA73 -> 0 | BF73: 否 | BG73: 概批+50-1000万财评台账 | BH73: 察隅县乡村振兴局
A74: 67 | B74: 林芝市 | C74: 察隅县 | D74: 2017 | E74: 古拉乡关龙村道路延伸建设项目 | F74: 是 | G74: 否 | H74: =I74+AF74 -> 700000 | I74: =O74+J74+T74+Y74+AE74+AC74+AD74 -> 650000 | J74: =N74+M74+L74+K74 -> 0 | O74: =S74+R74+Q74+P74 -> 650000 | Q74: 650000 | T74: =U74+V74+W74+X74 -> 0 | Y74: =AA74+Z74+AB74 -> 0 | AF74: 50000 | AG74: =AH74+BE74 -> 700000 | AH74: =AN74+AI74+AS74+AX74+BD74+BB74+BC74 -> 650000 | AI74: =AM74+AL74+AK74+AJ74 -> 0 | AN74: =AR74+AQ74+AP74+AO74 -> 650000 | AP74: 650000 | AS74: =AW74+AV74+AU74+AT74 -> 0 | AX74: =AZ74+AY74+BA74 -> 0 | BE74: 50000 | BF74: 是 | BG74: 确权资料+50-1000万台账（审定金额无）+本项目按照70万确权 | BH74: 察隅县民族宗教事务局
A75: 68 | B75: 林芝市 | C75: 察隅县 | D75: 2017 | E75: 察隅县卡地村易地扶贫搬迁土地治理建设项目 | F75: 是 | G75: 否 | H75: =I75+AF75 -> 6000000 | I75: =O75+J75+T75+Y75+AE75+AC75+AD75 -> 6000000 | J75: =N75+M75+L75+K75 -> 0 | O75: =S75+R75+Q75+P75 -> 6000000 | Q75: 6000000 | T75: =U75+V75+W75+X75 -> 0 | Y75: =AA75+Z75+AB75 -> 0 | AG75: =AH75+BE75 -> 4283981.7 | AH75: =AN75+AI75+AS75+AX75+BD75+BB75+BC75 -> 4283981.7 | AI75: =AM75+AL75+AK75+AJ75 -> 0 | AN75: =AR75+AQ75+AP75+AO75 -> 4283981.7 | AP75: 4283981.7 | AS75: =AW75+AV75+AU75+AT75 -> 0 | AX75: =AZ75+AY75+BA75 -> 0 | BF75: 否 | BG75: 资料来源于"5.农业农村局及相关提交的资料\在农业农村局收到的资料\邓老师提供\17年\附件1：察隅县2017年国家投资重点项目（续建+新建项目）统计表.xlsx"，50-1000万台账有财评数据 | BH75: 扶贫办
A76: 69 | B76: 林芝市 | C76: 察隅县 | D76: 2018 | E76: 察隅县古拉乡察空片区农田整治及机耕道建设项目 | F76: 是 | G76: 否 | H76: =I76+AF76 -> 2060000 | I76: =O76+J76+T76+Y76+AE76+AC76+AD76 -> 2060000 | J76: =N76+M76+L76+K76 -> 0 | O76: =S76+R76+Q76+P76 -> 2060000 | Q76: 2060000 | T76: =U76+V76+W76+X76 -> 0 | Y76: =AA76+Z76+AB76 -> 0 | AG76: =AH76+BE76 -> 1972592.6 | AH76: =AN76+AI76+AS76+AX76+BD76+BB76+BC76 -> 1972592.6 | AI76: =AM76+AL76+AK76+AJ76 -> 0 | AN76: =AR76+AQ76+AP76+AO76 -> 1972592.6 | AP76: 1972592.6 | AS76: =AW76+AV76+AU76+AT76 -> 0 | AX76: =AZ76+AY76+BA76 -> 0 | BF76: 是 | BG76: 确权资料+50-1000万台账 | BH76: 察隅县民族宗教事务局
A77: 70 | B77: 林芝市 | C77: 察隅县 | D77: 2018 | E77: 察瓦龙乡沙布村骡马驿道建设项目 | F77: 是 | G77: 否 | H77: =I77+AF77 -> 450000 | I77: =O77+J77+T77+Y77+AE77+AC77+AD77 -> 400000 | J77: =N77+M77+L77+K77 -> 0 | O77: =S77+R77+Q77+P77 -> 400000 | Q77: 400000 | T77: =U77+V77+W77+X77 -> 0 | Y77: =AA77+Z77+AB77 -> 0 | AF77: 50000 | AG77: =AH77+BE77 -> 450000 | AH77: =AN77+AI77+AS77+AX77+BD77+BB77+BC77 -> 400000 | AI77: =AM77+AL77+AK77+AJ77 -> 0 | AN77: =AR77+AQ77+AP77+AO77 -> 400000 | AP77: 400000 | AS77: =AW77+AV77+AU77+AT77 -> 0 | AX77: =AZ77+AY77+BA77 -> 0 | BE77: 50000 | BF77: 否 | BG77: 立项批复 | BH77: 察隅县民族宗教事务局
A78: 71 | B78: 林芝市 | C78: 察隅县 | D78: 2018 | E78: 察隅县察瓦龙乡龙布村重楼种植项目 | F78: 是 | G78: 是 | H78: =I78+AF78 -> 644000 | I78: =O78+J78+T78+Y78+AE78+AC78+AD78 -> 500000 | J78: =N78+M78+L78+K78 -> 0 | O78: =S78+R78+Q78+P78 -> 500000 | Q78: 500000 | T78: =U78+V78+W78+X78 -> 0 | Y78: =AA78+Z78+AB78 -> 0 | AF78: 144000 | AG78: =AH78+BE78 -> 644000 | AH78: =AN78+AI78+AS78+AX78+BD78+BB78+BC78 -> 500000 | AI78: =AM78+AL78+AK78+AJ78 -> 0 | AN78: =AR78+AQ78+AP78+AO78 -> 500000 | AP78: 500000 | AS78: =AW78+AV78+AU78+AT78 -> 0 | AX78: =AZ78+AY78+BA78 -> 0 | BE78: 144000 | BF78: 是 | BG78: 确权资料
A79: 72 | B79: 林芝市 | C79: 察隅县 | D79: 2018 | E79: 察隅县察瓦龙乡扎恩村重楼种植项目 | F79: 是 | G79: 是 | H79: =I79+AF79 -> 644000 | I79: =O79+J79+T79+Y79+AE79+AC79+AD79 -> 500000 | J79: =N79+M79+L79+K79 -> 0 | O79: =S79+R79+Q79+P79 -> 500000 | Q79: 500000 | T79: =U79+V79+W79+X79 -> 0 | Y79: =AA79+Z79+AB79 -> 0 | AF79: 144000 | AG79: =AH79+BE79 -> 644000 | AH79: =AN79+AI79+AS79+AX79+BD79+BB79+BC79 -> 500000 | AI79: =AM79+AL79+AK79+AJ79 -> 0 | AN79: =AR79+AQ79+AP79+AO79 -> 500000 | AP79: 500000 | AS79: =AW79+AV79+AU79+AT79 -> 0 | AX79: =AZ79+AY79+BA79 -> 0 | BE79: 144000 | BF79: 是 | BG79: 确权资料
A80: 73 | B80: 林芝市 | C80: 察隅县 | D80: 2018 | E80: 察隅县察瓦龙乡苗圃基地建设项目 | F80: 是 | G80: 是 | H80: =I80+AF80 -> 516000 | I80: =O80+J80+T80+Y80+AE80+AC80+AD80 -> 500000 | J80: =N80+M80+L80+K80 -> 0 | O80: =S80+R80+Q80+P80 -> 500000 | Q80: 500000 | T80: =U80+V80+W80+X80 -> 0 | Y80: =AA80+Z80+AB80 -> 0 | AF80: 16000 | AG80: =AH80+BE80 -> 516000 | AH80: =AN80+AI80+AS80+AX80+BD80+BB80+BC80 -> 500000 | AI80: =AM80+AL80+AK80+AJ80 -> 0 | AN80: =AR80+AQ80+AP80+AO80 -> 500000 | AP80: 500000 | AS80: =AW80+AV80+AU80+AT80 -> 0 | AX80: =AZ80+AY80+BA80 -> 0 | BE80: 16000 | BF80: 是 | BG80: 确权资料
A81: 74 | B81: 林芝市 | C81: 察隅县 | D81: 2018 | E81: 察隅县上察隅镇西巴村铁皮石斛种植扩建项目 | F81: 是 | G81: 是 | H81: =I81+AF81 -> 500000 | I81: =O81+J81+T81+Y81+AE81+AC81+AD81 -> 500000 | J81: =N81+M81+L81+K81 -> 0 | O81: =S81+R81+Q81+P81 -> 500000 | Q81: 500000 | T81: =U81+V81+W81+X81 -> 0 | Y81: =AA81+Z81+AB81 -> 0 | AG81: =AH81+BE81 -> 500000 | AH81: =AN81+AI81+AS81+AX81+BD81+BB81+BC81 -> 500000 | AI81: =AM81+AL81+AK81+AJ81 -> 0 | AN81: =AR81+AQ81+AP81+AO81 -> 500000 | AP81: 500000 | AS81: =AW81+AV81+AU81+AT81 -> 0 | AX81: =AZ81+AY81+BA81 -> 0 | BE81: 0 | BF81: 是 | BG81: 确权资料+立项批复 | BH81: 上察隅人民政府
A82: 75 | B82: 林芝市 | C82: 察隅县 | D82: 2018 | E82: 察隅县古玉乡古井村藏香猪养殖项目 | F82: 是 | G82: 是 | H82: =I82+AF82 -> 648400 | I82: =O82+J82+T82+Y82+AE82+AC82+AD82 -> 500000 | J82: =N82+M82+L82+K82 -> 0 | O82: =S82+R82+Q82+P82 -> 500000 | Q82: 500000 | T82: =U82+V82+W82+X82 -> 0 | Y82: =AA82+Z82+AB82 -> 0 | AF82: 148400 | AG82: =AH82+BE82 -> 648400 | AH82: =AN82+AI82+AS82+AX82+BD82+BB82+BC82 -> 500000 | AI82: =AM82+AL82+AK82+AJ82 -> 0 | AN82: =AR82+AQ82+AP82+AO82 -> 500000 | AP82: 500000 | AS82: =AW82+AV82+AU82+AT82 -> 0 | AX82: =AZ82+AY82+BA82 -> 0 | BE82: 148400 | BF82: 是 | BG82: 确权资料
A83: 76 | B83: 林芝市 | C83: 察隅县 | D83: 2018 | E83: 察隅县古玉乡古井村藏鸡养殖项目 | F83: 是 | G83: 是 | H83: =I83+AF83 -> 556000 | I83: =O83+J83+T83+Y83+AE83+AC83+AD83 -> 500000 | J83: =N83+M83+L83+K83 -> 0 | O83: =S83+R83+Q83+P83 -> 500000 | Q83: 500000 | T83: =U83+V83+W83+X83 -> 0 | Y83: =AA83+Z83+AB83 -> 0 | AF83: 56000 | AG83: =AH83+BE83 -> 556000 | AH83: =AN83+AI83+AS83+AX83+BD83+BB83+BC83 -> 500000 | AI83: =AM83+AL83+AK83+AJ83 -> 0 | AN83: =AR83+AQ83+AP83+AO83 -> 500000 | AP83: 500000 | AS83: =AW83+AV83+AU83+AT83 -> 0 | AX83: =AZ83+AY83+BA83 -> 0 | BE83: 56000 | BF83: 是 | BG83: 确权资料
A84: 77 | B84: 林芝市 | C84: 察隅县 | D84: 2018 | E84: 察隅县竹瓦根镇扎拉村阿多专业养殖合作社项目 | F84: 是 | G84: 是 | H84: =I84+AF84 -> 714400 | I84: =O84+J84+T84+Y84+AE84+AC84+AD84 -> 500000 | J84: =N84+M84+L84+K84 -> 0 | O84: =S84+R84+Q84+P84 -> 500000 | Q84: 500000 | T84: =U84+V84+W84+X84 -> 0 | Y84: =AA84+Z84+AB84 -> 0 | AF84: 214400 | AG84: =AH84+BE84 -> 714400 | AH84: =AN84+AI84+AS84+AX84+BD84+BB84+BC84 -> 500000 | AI84: =AM84+AL84+AK84+AJ84 -> 0 | AN84: =AR84+AQ84+AP84+AO84 -> 500000 | AP84: 500000 | AS84: =AW84+AV84+AU84+AT84 -> 0 | AX84: =AZ84+AY84+BA84 -> 0 | BE84: 214400 | BF84: 是 | BG84: 确权资料
A85: 78 | B85: 林芝市 | C85: 察隅县 | D85: 2018 | E85: 察隅县竹瓦根镇桑久村藏香猪养殖项目 | F85: 是 | G85: 是 | H85: =I85+AF85 -> 530800 | I85: =O85+J85+T85+Y85+AE85+AC85+AD85 -> 500000 | J85: =N85+M85+L85+K85 -> 0 | O85: =S85+R85+Q85+P85 -> 500000 | Q85: 500000 | T85: =U85+V85+W85+X85 -> 0 | Y85: =AA85+Z85+AB85 -> 0 | AF85: 30800 | AG85: =AH85+BE85 -> 530800 | AH85: =AN85+AI85+AS85+AX85+BD85+BB85+BC85 -> 500000 | AI85: =AM85+AL85+AK85+AJ85 -> 0 | AN85: =AR85+AQ85+AP85+AO85 -> 500000 | AP85: 500000 | AS85: =AW85+AV85+AU85+AT85 -> 0 | AX85: =AZ85+AY85+BA85 -> 0 | BE85: 30800 | BF85: 是 | BG85: 确权资料
A86: 79 | B86: 林芝市 | C86: 察隅县 | D86: 2018 | E86: 察隅县古玉乡博学村犏奶牛养殖场扩建项目 | F86: 是 | G86: 是 | H86: =I86+AF86 -> 725800 | I86: =O86+J86+T86+Y86+AE86+AC86+AD86 -> 500000 | J86: =N86+M86+L86+K86 -> 0 | O86: =S86+R86+Q86+P86 -> 500000 | Q86: 500000 | T86: =U86+V86+W86+X86 -> 0 | Y86: =AA86+Z86+AB86 -> 0 | AF86: 225800 | AG86: =AH86+BE86 -> 725800 | AH86: =AN86+AI86+AS86+AX86+BD86+BB86+BC86 -> 500000 | AI86: =AM86+AL86+AK86+AJ86 -> 0 | AN86: =AR86+AQ86+AP86+AO86 -> 500000 | AP86: 500000 | AS86: =AW86+AV86+AU86+AT86 -> 0 | AX86: =AZ86+AY86+BA86 -> 0 | BE86: 225800 | BF86: 是 | BG86: 确权资料 | BH86: 古玉乡人民政府
A87: 80 | B87: 林芝市 | C87: 察隅县 | D87: 2018 | E87: 下察隅镇京都村藏香猪养殖项目 | F87: 是 | G87: 是 | H87: =I87+AF87 -> 544400 | I87: =O87+J87+T87+Y87+AE87+AC87+AD87 -> 500000 | J87: =N87+M87+L87+K87 -> 0 | O87: =S87+R87+Q87+P87 -> 500000 | Q87: 500000 | T87: =U87+V87+W87+X87 -> 0 | Y87: =AA87+Z87+AB87 -> 0 | AF87: 44400 | AG87: =AH87+BE87 -> 544400 | AH87: =AN87+AI87+AS87+AX87+BD87+BB87+BC87 -> 500000 | AI87: =AM87+AL87+AK87+AJ87 -> 0 | AN87: =AR87+AQ87+AP87+AO87 -> 500000 | AP87: 500000 | AS87: =AW87+AV87+AU87+AT87 -> 0 | AX87: =AZ87+AY87+BA87 -> 0 | BE87: 44400 | BF87: 是 | BG87: 确权资料
A88: 81 | B88: 林芝市 | C88: 察隅县 | D88: 2018 | E88: 察隅县古拉乡俄玉村藏香猪养殖项目 | F88: 是 | G88: 是 | H88: =I88+AF88 -> 500000 | I88: =O88+J88+T88+Y88+AE88+AC88+AD88 -> 500000 | J88: =N88+M88+L88+K88 -> 0 | O88: =S88+R88+Q88+P88 -> 500000 | Q88: 500000 | T88: =U88+V88+W88+X88 -> 0 | Y88: =AA88+Z88+AB88 -> 0 | AG88: =AH88+BE88 -> 500000 | AH88: =AN88+AI88+AS88+AX88+BD88+BB88+BC88 -> 500000 | AI88: =AM88+AL88+AK88+AJ88 -> 0 | AN88: =AR88+AQ88+AP88+AO88 -> 500000 | AP88: 500000 | AS88: =AW88+AV88+AU88+AT88 -> 0 | AX88: =AZ88+AY88+BA88 -> 0 | BE88: 0 | BF88: 是 | BG88: 确权资料
A89: 82 | B89: 林芝市 | C89: 察隅县 | D89: 2018 | E89: 察隅县产业扶贫毕达村茶叶种植项目 | F89: 是 | G89: 是 | H89: =I89+AF89 -> 9155300 | I89: =O89+J89+T89+Y89+AE89+AC89+AD89 -> 4577650 | J89: =N89+M89+L89+K89 -> 0 | O89: =S89+R89+Q89+P89 -> 4577650 | P89: 4577650 | T89: =U89+V89+W89+X89 -> 0 | Y89: =AA89+Z89+AB89 -> 0 | AF89: 4577650 | AG89: =AH89+BE89 -> 5661205.6 | AH89: =AN89+AI89+AS89+AX89+BD89+BB89+BC89 -> 2830602.8 | AI89: =AM89+AL89+AK89+AJ89 -> 0 | AN89: =AR89+AQ89+AP89+AO89 -> 2830602.8 | AO89: 2830602.8 | AS89: =AW89+AV89+AU89+AT89 -> 0 | AX89: =AZ89+AY89+BA89 -> 0 | BE89: 2830602.8 | BF89: 是 | BG89: 确权资料+50-1000万台账，有决算报告，但是无法判定自筹和国家投资
A90: 83 | B90: 林芝市 | C90: 察隅县 | D90: 2018 | E90: 察隅县产业扶贫松古村茶叶种植项目 | F90: 是 | G90: 是 | H90: =I90+AF90 -> 12055900 | I90: =O90+J90+T90+Y90+AE90+AC90+AD90 -> 6027950 | J90: =N90+M90+L90+K90 -> 0 | O90: =S90+R90+Q90+P90 -> 6027950 | P90: 6027950 | T90: =U90+V90+W90+X90 -> 0 | Y90: =AA90+Z90+AB90 -> 0 | AF90: 6027950 | AG90: =AH90+BE90 -> 9370785.2 | AH90: =AN90+AI90+AS90+AX90+BD90+BB90+BC90 -> 4685392.6 | AI90: =AM90+AL90+AK90+AJ90 -> 0 | AN90: =AR90+AQ90+AP90+AO90 -> 4685392.6 | AO90: 4685392.6 | AS90: =AW90+AV90+AU90+AT90 -> 0 | AX90: =AZ90+AY90+BA90 -> 0 | BE90: 4685392.6 | BF90: 是 | BG90: 确权资料+50-1000万台账+财评
A91: 84 | B91: 林芝市 | C91: 察隅县 | D91: 2018 | E91: 西藏牧野香畜禽养殖基地建设项目 | F91: 是 | G91: 是 | H91: =I91+AF91 -> 3799300 | I91: =O91+J91+T91+Y91+AE91+AC91+AD91 -> 2500000 | J91: =N91+M91+L91+K91 -> 0 | O91: =S91+R91+Q91+P91 -> 2500000 | R91: 2500000 | T91: =U91+V91+W91+X91 -> 0 | Y91: =AA91+Z91+AB91 -> 0 | AF91: 1299300 | AG91: =AH91+BE91 -> 3614662.2 | AH91: =AN91+AI91+AS91+AX91+BD91+BB91+BC91 -> 2362711.8 | AI91: =AM91+AL91+AK91+AJ91 -> 0 | AN91: =AR91+AQ91+AP91+AO91 -> 2362711.8 | AQ91: 2362711.8 | AS91: =AW91+AV91+AU91+AT91 -> 0 | AX91: =AZ91+AY91+BA91 -> 0 | BE91: 1251950.5 | BF91: 是 | BG91: 确权资料 | BH91: 察隅县扶贫开发投资有限公司
A92: 85 | B92: 林芝市 | C92: 察隅县 | D92: 2018 | E92: 察隅县察瓦龙乡卡地村软籽石榴种植基地建设项目 | F92: 是 | G92: 是 | H92: =I92+AF92 -> 1801400 | I92: =O92+J92+T92+Y92+AE92+AC92+AD92 -> 1801400 | J92: =N92+M92+L92+K92 -> 0 | O92: =S92+R92+Q92+P92 -> 1801400 | P92: 1801400 | T92: =U92+V92+W92+X92 -> 0 | Y92: =AA92+Z92+AB92 -> 0 | AG92: =AH92+BE92 -> 1716590.7 | AH92: =AN92+AI92+AS92+AX92+BD92+BB92+BC92 -> 1716590.7 | AI92: =AM92+AL92+AK92+AJ92 -> 0 | AN92: =AR92+AQ92+AP92+AO92 -> 1716590.7 | AO92: 1716590.7 | AS92: =AW92+AV92+AU92+AT92 -> 0 | AX92: =AZ92+AY92+BA92 -> 0 | BE92: 0 | BF92: 是 | BG92: 确权资料
A93: 86 | B93: 林芝市 | C93: 察隅县 | D93: 2018 | E93: 察隅县察瓦龙乡格布村软籽石榴种植基地建设项目 | F93: 是 | G93: 是 | H93: =I93+AF93 -> 1605200 | I93: =O93+J93+T93+Y93+AE93+AC93+AD93 -> 1605200 | J93: =N93+M93+L93+K93 -> 0 | O93: =S93+R93+Q93+P93 -> 1605200 | P93: 1605200 | T93: =U93+V93+W93+X93 -> 0 | Y93: =AA93+Z93+AB93 -> 0 | AG93: =AH93+BE93 -> 1605200 | AH93: =AN93+AI93+AS93+AX93+BD93+BB93+BC93 -> 1605200 | AI93: =AM93+AL93+AK93+AJ93 -> 0 | AN93: =AR93+AQ93+AP93+AO93 -> 1605200 | AO93: 1605200 | AS93: =AW93+AV93+AU93+AT93 -> 0 | AX93: =AZ93+AY93+BA93 -> 0 | BE93: 0 | BF93: 是 | BG93: 确权资料 | BH93: 本项目审定金额需要核实，实际确权金额1558200元
A94: 87 | B94: 林芝市 | C94: 察隅县 | D94: 2018 | E94: 察隅县察瓦龙乡左布村软籽石榴种植基地建设项目 | F94: 是 | G94: 是 | H94: =I94+AF94 -> 1014500 | I94: =O94+J94+T94+Y94+AE94+AC94+AD94 -> 1014500 | J94: =N94+M94+L94+K94 -> 0 | O94: =S94+R94+Q94+P94 -> 1014500 | P94: 1014500 | T94: =U94+V94+W94+X94 -> 0 | Y94: =AA94+Z94+AB94 -> 0 | AG94: =AH94+BE94 -> 952844.57 | AH94: =AN94+AI94+AS94+AX94+BD94+BB94+BC94 -> 952844.57 | AI94: =AM94+AL94+AK94+AJ94 -> 0 | AN94: =AR94+AQ94+AP94+AO94 -> 952844.57 | AO94: 952844.57 | AS94: =AW94+AV94+AU94+AT94 -> 0 | AX94: =AZ94+AY94+BA94 -> 0 | BE94: 0 | BF94: 是 | BG94: 确权资料
A95: 88 | B95: 林芝市 | C95: 察隅县 | D95: 2018 | E95: 察隅县察瓦龙乡处尼村软籽石榴种植基地建设项目 | F95: 是 | G95: 是 | H95: =I95+AF95 -> 608700 | I95: =O95+J95+T95+Y95+AE95+AC95+AD95 -> 608700 | J95: =N95+M95+L95+K95 -> 0 | O95: =S95+R95+Q95+P95 -> 608700 | P95: 608700 | T95: =U95+V95+W95+X95 -> 0 | Y95: =AA95+Z95+AB95 -> 0 | AG95: =AH95+BE95 -> 576110.99 | AH95: =AN95+AI95+AS95+AX95+BD95+BB95+BC95 -> 576110.99 | AI95: =AM95+AL95+AK95+AJ95 -> 0 | AN95: =AR95+AQ95+AP95+AO95 -> 576110.99 | AO95: 576110.99 | AS95: =AW95+AV95+AU95+AT95 -> 0 | AX95: =AZ95+AY95+BA95 -> 0 | BE95: 0 | BF95: 是 | BG95: 确权资料
A96: 89 | B96: 林芝市 | C96: 察隅县 | D96: 2018 | E96: 察隅县察瓦龙乡沙布村软籽石榴种植基地建设项目 | F96: 是 | G96: 是 | H96: =I96+AF96 -> 1480700 | I96: =O96+J96+T96+Y96+AE96+AC96+AD96 -> 1480700 | J96: =N96+M96+L96+K96 -> 0 | O96: =S96+R96+Q96+P96 -> 1480700 | P96: 1480700 | T96: =U96+V96+W96+X96 -> 0 | Y96: =AA96+Z96+AB96 -> 0 | AG96: =AH96+BE96 -> 1384495.3 | AH96: =AN96+AI96+AS96+AX96+BD96+BB96+BC96 -> 1384495.3 | AI96: =AM96+AL96+AK96+AJ96 -> 0 | AN96: =AR96+AQ96+AP96+AO96 -> 1384495.3 | AO96: 1384495.3 | AS96: =AW96+AV96+AU96+AT96 -> 0 | AX96: =AZ96+AY96+BA96 -> 0 | BE96: 0 | BF96: 是 | BG96: 确权资料
A97: 90 | B97: 林芝市 | C97: 察隅县 | D97: 2018 | E97: 察隅县古拉乡察空村软籽石榴种植基地建设项目 | F97: 是 | G97: 是 | H97: =I97+AF97 -> 5213300 | I97: =O97+J97+T97+Y97+AE97+AC97+AD97 -> 5213300 | J97: =N97+M97+L97+K97 -> 0 | O97: =S97+R97+Q97+P97 -> 5213300 | P97: 5213300 | T97: =U97+V97+W97+X97 -> 0 | Y97: =AA97+Z97+AB97 -> 0 | AG97: =AH97+BE97 -> 4400959.2 | AH97: =AN97+AI97+AS97+AX97+BD97+BB97+BC97 -> 4400959.2 | AI97: =AM97+AL97+AK97+AJ97 -> 0 | AN97: =AR97+AQ97+AP97+AO97 -> 4400959.2 | AO97: 4400959.2 | AS97: =AW97+AV97+AU97+AT97 -> 0 | AX97: =AZ97+AY97+BA97 -> 0 | BE97: 0 | BF97: 是 | BG97: 确权资料+50-1000万台账
A98: 91 | B98: 林芝市 | C98: 察隅县 | D98: 2017 | E98: 察隅县产业扶贫猕猴桃种植基地建设项目 | F98: 是 | G98: 是 | H98: =I98+AF98 -> 7719500 | I98: =O98+J98+T98+Y98+AE98+AC98+AD98 -> 5000000 | J98: =N98+M98+L98+K98 -> 5000000 | M98: 5000000 | O98: =S98+R98+Q98+P98 -> 0 | T98: =U98+V98+W98+X98 -> 0 | Y98: =AA98+Z98+AB98 -> 0 | AF98: 2719500 | AG98: =AH98+BE98 -> 6936855.6 | AH98: =AN98+AI98+AS98+AX98+BD98+BB98+BC98 -> 4748632.3 | AI98: =AM98+AL98+AK98+AJ98 -> 4748632.3 | AL98: 4748632.3 | AN98: =AR98+AQ98+AP98+AO98 -> 0 | AS98: =AW98+AV98+AU98+AT98 -> 0 | AX98: =AZ98+AY98+BA98 -> 0 | BE98: 2188223.3 | BF98: 是 | BG98: 确权资料+50-1000万财评统计表（没有审定金额） | BH98: 县扶贫开发投资有限公司
A99: 92 | B99: 林芝市 | C99: 察隅县 | D99: 2018 | E99: 察隅县古拉乡关龙村三家组道路工程建设项目 | F99: 是 | G99: 否 | H99: =I99+AF99 -> 555900 | I99: =O99+J99+T99+Y99+AE99+AC99+AD99 -> 555900 | J99: =N99+M99+L99+K99 -> 0 | O99: =S99+R99+Q99+P99 -> 555900 | P99: 555900 | T99: =U99+V99+W99+X99 -> 0 | Y99: =AA99+Z99+AB99 -> 0 | AG99: =AH99+BE99 -> 555900 | AH99: =AN99+AI99+AS99+AX99+BD99+BB99+BC99 -> 555900 | AI99: =AM99+AL99+AK99+AJ99 -> 0 | AN99: =AR99+AQ99+AP99+AO99 -> 555900 | AO99: 555900 | AS99: =AW99+AV99+AU99+AT99 -> 0 | AX99: =AZ99+AY99+BA99 -> 0 | BF99: 是 | BG99: 确权资料+50-1000万台账(没有明确审定金额），台账金额来源待核实 | BH99: 县脱贫攻坚指挥部办公室（扶贫办）
A100: 93 | B100: 林芝市 | C100: 察隅县 | D100: 2018 | E100: 察隅县察瓦龙乡扎恩村软籽石榴种植基地建设项目 | F100: 是 | G100: 是 | H100: =I100+AF100 -> 772500 | I100: =O100+J100+T100+Y100+AE100+AC100+AD100 -> 772500 | J100: =N100+M100+L100+K100 -> 0 | O100: =S100+R100+Q100+P100 -> 772500 | P100: 772500 | T100: =U100+V100+W100+X100 -> 0 | Y100: =AA100+Z100+AB100 -> 0 | AG100: =AH100+BE100 -> 772500 | AH100: =AN100+AI100+AS100+AX100+BD100+BB100+BC100 -> 772500 | AI100: =AM100+AL100+AK100+AJ100 -> 0 | AN100: =AR100+AQ100+AP100+AO100 -> 772500 | AO100: 772500 | AS100: =AW100+AV100+AU100+AT100 -> 0 | AX100: =AZ100+AY100+BA100 -> 0 | BE100: 0 | BF100: 否 | BG100: 立项批复+50-1000万台账（未注明审定金额） | BH100: 察隅县林业和草原局
...

Sheet 附件3
A1: 西藏自治区察隅县帮扶产业项目总台账 （截至2026年6月30日数据）
A2: 项目 编号 | B2: 项目 地市 | C2: 项目 县区 | D2: 项目 年度 | E2: 项目 名称 | F2: 项目申报主体 | G2: 项目实施地点 | H2: 项目主要建设内容 | I2: 计划投资（万元） | L2: 实际投资（万元） | O2: 项目 分类情况 | P2: 项目所属产业分类 | Q2: 产业“四个一批”分类 | R2: 经营性项目“四个一批”分类 | S2: 项目运营情况 | T2: 项目运营模式 | U2: 项目经营主体 | W2: 项目联农带农协议签订情况 | X2: 项目联农带农协议签订时间 | Y2: 项目联农带农协议主要内容 | Z2: 项目累计分红金额 （元） | AA2: 项目累计带动就业人数 （人） | AB2: 项目归口行业单位名称 | AC2: 备注 | AD2: 是否已经确权 | AE2: 资料来源 | AF2: 本次是否有拍摄现场照片 | AG2: 工作记录是否已写 | AH2: 方案是否已写
I3: 合计 | J3: 政策性资金 （同表2政策性资金合计数） | K3: 其他渠道资金 （如企业自筹、信贷资金等非政策性资金，同表2） | L3: 合计 | M3: 政策性资金 （同表2政策性资金合计数） | N3: 其他渠道资金 （如企业自筹、信贷资金等非政策性资金，同表2） | U3: 经营主体类别 | V3: 名称
A4: 填表说明：根据指南编码规则编号 | D4: 以项目批复中对应内容为准 | G4: 以项目批复中项目实施地点为准，例：XX乡（镇）XX 村（居） | H4: 以项目竣工决算中项目主要建设内容为准 | I4: 与表2数据一致 （保留小数点后面2位） | L4: 与表2数据一致 （保留小数点后面2位） | O4: 在“经营类、公益类、到户类“中选择 | P4: 在“青稞、小麦、饲料、牦牛、乳、羊、猪、鸡、蜂、鱼虾、藏药、茶、葡萄、苹果、猕猴桃、设施农业、乡村旅游、商贸流通、核桃、其他”中选择 | Q4: 在“巩固、升级、盘活、调整”中选择 | R4: 在“巩固、升级、盘活、调整”中选择，仅经营类项目填写 | S4: 根据实际情况填写“是/否” | T4: 在“自主运营、合作运营、委托运营“中选择 | U4: 在“农村集体经济组织、农牧民专业合作社、农户、国企、私企、个体工商户、其他”中选择 | W4: 根据实际情况填写“是/否” | X4: 例：2022.09 | Y4: 例：该项目带动建档立卡群众不低于23户79人增收，分红金额不低于500元/人/年 | AB4: 以项目实施内容对应行业单位为准 | AD4: 在“是/否”中选择 | AE4: 财评、合同、立项等 | AF4: 在“是/否”中选择 | AH4: 在“是/否”中选择
A5: 540425201320001 | B5: 林芝市 | C5: 察隅县 | D5: 2013 | E5: 察瓦龙乡昌西村石榴品种改良项目 | F5: 察瓦龙乡人民政府 | G5: 察瓦龙乡昌西村 | H5: 改良112亩5600株石榴 | I5: =J5+K5 -> 24 | J5: 24 | K5: 0 | L5: =M5+N5 -> 24 | M5: 24 | N5: 0 | O5: 经营类 | P5: 石榴 | Q5: 调整 | R5: 调整 | S5: 否 | AD5: 否 | AE5: 项目资料 | AF5: 否 | AG5: 是 | AH5: 是
A6: 540425201517002 | B6: 林芝市 | C6: 察隅县 | D6: 2015 | E6: 罗马桃花村旅游资源升级改造项目 | F6: 古玉乡人民政府\察隅县受援办 | G6: 古玉乡罗马村 | H6: 发展特色藏民族文化旅游产业，充分发挥旅游、生态自然资源的优势，带动整合闲置劳动力，逐步改变传统农牧业生产方式，进而转变成以旅游业为主的核心产业，建立村民增收的长效机制，促进产业发展，建设幸福新村。内容：1.藏家歌舞表演广场；2.驿站引水工程；3.村内道路硬化工程；4.观景平台；5.绿化种植；6.公共卫生设施等 | I6: =J6+K6 -> 500 | J6: 500 | K6: 0 | L6: =M6+N6 -> 500 | M6: 500 | N6: 0 | O6: 公益类 | P6: 乡村旅游 | Q6: 升级 | AD6: 否 | AE6: 数据统计来源于察隅县2015年援藏投资项目计划表（被审计单位文件夹，附件2：援藏项目）+项目资料 | AF6: 否 | AG6: 是
A7: 540425201517003 | B7: 林芝市 | C7: 察隅县 | D7: 2015 | E7: 察隅县古玉乡罗马村农家乐（实施过，找不到业主） | F7: 罗马村村委会 | G7: 古玉乡罗马村 | H7: 修建农家乐及庭院一座 | I7: =J7+K7 -> 200 | J7: 200 | K7: 0 | L7: =M7+N7 -> 200 | M7: 200 | N7: 0 | O7: 经营类 | P7: 乡村旅游 | Q7: 升级 | R7: 调整 | S7: 否 | T7: 委托运营 | U7: 个体工商户 | V7: 张鹏 | W7: 否 | AB7: 察隅县文化和旅游局 | AD7: 否 | AE7: 数据来源于3.现场踏勘照片-现场及一些现场拍的资料-察隅县-察隅县古玉乡帮扶产业项目统计表 | AF7: 否 | AG7: 是
A8: 540425201619002 | B8: 林芝市 | C8: 察隅县 | D8: 2016 | E8: 古拉乡核桃粮油加工坊 | F8: 察隅县扶贫开发办公室 | G8: 古拉乡 | H8: 购买榨油机及附属配套设施 | I8: =J8+K8 -> 150 | J8: 150 | K8: 0 | L8: =M8+N8 -> 60 | M8: 60 | N8: 0 | O8: 经营类 | P8: 设施农业 | Q8: 升级 | R8: 调整 | S8: 否 | AD8: 否 | AE8: 数据来源于附件8：2016年项目建设计划 | AF8: 否 | AG8: 是
A9: 540425201604002 | B9: 林芝市 | C9: 察隅县 | D9: 2016 | E9: 察隅县牦牛养殖项目 | F9: 扶贫办 | G9: 察隅县 | H9: 为131户购买牛，修建牛圈11座。（古拉乡为8户购置57头牦牛；下察隅镇19户102头修建牛圈11座；竹瓦根镇52户260头；察瓦龙乡52户养殖犏牛410头，奶牛3头，小牛136头，黄牛40头，母牛1头，牛圈1座） | I9: =J9+K9 -> 577 | J9: 577 | K9: 0 | L9: =M9+N9 -> 577 | M9: 577 | N9: 0 | O9: 到户类 | P9: 牦牛 | Q9: 盘活 | AD9: 否 | AE9: 数据来源于附件8：2016年项目建设计划 | AF9: 否 | AG9: 是
A10: 540425201606001 | B10: 林芝市 | C10: 察隅县 | D10: 2016 | E10: 察隅县养羊项目 | F10: 扶贫办 | G10: 察隅县 | H10: 为10户购置山羊550只，绵羊40只（古拉乡3户养殖山羊150只，上察隅镇2户养殖绵羊40只，察瓦龙乡5户养殖山羊400只） | I10: =J10+K10 -> 30 | J10: 30 | K10: 0 | L10: =M10+N10 -> 30 | M10: 30 | N10: 0 | O10: 到户类 | P10: 羊 | Q10: 盘活 | AD10: 否 | AE10: 数据来源于附件8：2016年项目建设计划 | AF10: 否 | AG10: 是
A11: 540425201619003 | B11: 林芝市 | C11: 察隅县 | D11: 2016 | E11: 察隅县特色种植项目 | F11: 扶贫办 | G11: 古拉乡 关龙村 竹瓦根镇 下察隅 | H11: 为9户实施特色种植项目。古拉乡6户（则巴村1户种植葡萄苗30棵，关龙村4户种植花椒苗子80棵，安巴村1户苹果苗50棵）；竹瓦根镇1户（种植天麻）；下察隅镇1户种植橘子树4亩，1户种植天麻2亩。 | I11: =J11+K11 -> 27 | J11: 27 | K11: 0 | L11: =M11+N11 -> 27 | M11: 27 | N11: 0 | O11: 到户类 | P11: 其他 | Q11: 调整 | AD11: 否 | AE11: 数据来源于附件8：2016年项目建设计划 | AF11: 是 | AG11: 是
A12: 540425201619005 | B12: 林芝市 | C12: 察隅县 | D12: 2016 | E12: 古拉乡则巴村菩提树种植及加工项目 | F12: 察隅县扶贫开发办公室 | G12: 古拉乡则巴村 | H12: 种植500颗菩提树 、修建4个树苗培育室3、种植区域土地平整 | I12: =J12+K12 -> 85 | J12: 85 | K12: 0 | L12: =M12+N12 -> 85 | M12: 85 | N12: 0 | O12: 经营类 | P12: 其他 | Q12: 调整 | R12: 调整 | S12: 否 | AC12: 已搬迁 | AD12: 否 | AE12: 数据来源于附件8：2016年项目建设计划 | AF12: 否 | AG12: 是 | AH12: 是
A13: 540425201619006 | B13: 林芝市 | C13: 察隅县 | D13: 2016 | E13: 下察隅镇辣椒种植项目 | F13: 察隅县扶贫开发办公室 | G13: 下察隅镇 | H13: 种植辣椒100亩及附属配套设施 | I13: =J13+K13 -> 60 | J13: 60 | K13: 0 | L13: =M13+N13 -> 60 | M13: 60 | N13: 0 | O13: 经营类 | P13: 其他 | Q13: 调整 | R13: 调整 | S13: 否 | AD13: 否 | AE13: 数据来源于附件8：2016年项目建设计划 | AF13: 否 | AG13: 是
A14: 540425201619007 | B14: 林芝市 | C14: 察隅县 | D14: 2016 | E14: 上察隅镇木碗加工项目 | F14: 扶贫办 | G14: 上察隅镇 | H14: 为上察隅镇木碗加工合作社配置加工设施 | I14: =J14+K14 -> 20 | J14: 20 | K14: 0 | L14: =M14+N14 -> 20 | M14: 20 | N14: 0 | O14: 公益类 | P14: 其他 | Q14: 调整 | AD14: 否 | AE14: 数据来源于附件8：2016年项目建设计划 | AF14: 否 | AG14: 是
A15: 540425201608002 | B15: 林芝市 | C15: 察隅县 | D15: 2016 | E15: 察瓦龙乡藏鸡养殖项目 | F15: 察瓦龙乡人民政府 | G15: 察瓦龙乡 | H15: 建设内容：修建9个鸡圈，购买鸡苗75只，购买饲料等 | I15: =J15+K15 -> 34 | J15: 30 | K15: 4 | L15: =M15+N15 -> 34 | M15: 30 | N15: 4 | O15: 到户类 | P15: 鸡 | Q15: 调整 | S15: 否 | AD15: 是 | AE15: 确权资料+2013年批复项目汇总表 | AG15: 无需写
A16: 540425201607004 | B16: 林芝市 | C16: 察隅县 | D16: 2016 | E16: 察瓦龙乡藏猪养殖项目 | F16: 察瓦龙乡人民政府 | G16: 察瓦龙乡 | H16: 建设内容：修建24个猪圈，化粪池24座，购买猪仔288头，每村购买种猪1头，每户购买可繁育母猪1头，购买饲料等 | I16: =J16+K16 -> 38.907 | J16: 38.907 | K16: 0 | L16: =M16+N16 -> 38.907 | M16: 38.907 | N16: 0 | O16: 到户类 | P16: 猪 | Q16: 调整 | AD16: 否 | AE16: 数据来源于3.现场踏勘照片-现场及一些现场拍的资料-察隅县-察瓦龙乡项目表（最新） | AF16: 否
A17: 540425201616005 | B17: 林芝市 | C17: 察隅县 | D17: 2016 | E17: 察瓦龙乡贫困户温室大棚建设项目 | F17: 察瓦龙乡人民政府 | G17: 察瓦龙乡邓许村、龙普村、昌西村 | H17: 察瓦龙乡修建温室大棚36座，邓许村11座，龙普村21座，昌西村4座 | I17: =J17+K17 -> 57.19 | J17: 57.19 | K17: 0 | L17: =M17+N17 -> 57.19 | M17: 57.19 | N17: 0 | O17: 公益类 | P17: 设施农业 | Q17: 升级 | AD17: 是 | AE17: 在察隅县大棚里面有张确权表 | AF17: 是 | AG17: 是
A18: 540425201608003 | B18: 林芝市 | C18: 察隅县 | D18: 2016 | E18: 察瓦龙乡贫困养鸡项目 | F18: 察瓦龙乡人民政府 | G18: 察瓦龙乡拉卡村、邓许村、昌西村、珠拉村 | H18: 察瓦龙乡扶持贫困户养鸡9户，其中拉卡5户，邓许1户，昌西1户，珠拉2户 | I18: =J18+K18 -> 12.71 | J18: 12.71 | K18: 0 | L18: =M18+N18 -> 12.71 | M18: 12.71 | N18: 0 | O18: 到户类 | P18: 鸡 | Q18: 调整 | AD18: 是 | AE18: 在察隅县养鸡里面有张确权表 | AF18: 否 | AG18: 无需写
A19: 540425201607005 | B19: 林芝市 | C19: 察隅县 | D19: 2016 | E19: 察瓦龙乡贫困户养猪项目 | F19: 察瓦龙乡人民政府 | G19: 察瓦龙乡洪东，昌西，邓许，拉卡，瓦布，学巴，扎然 | H19: 察瓦龙乡扶持贫困户养猪24户，其中拉卡6户，邓许1户，洪东6户，昌西4户，瓦布1户，扎然1户，学巴5户 | I19: =J19+K19 -> 42.06 | J19: 42.06 | K19: 0 | L19: =M19+N19 -> 42.06 | M19: 42.06 | N19: 0 | O19: 到户类 | P19: 猪 | Q19: 调整 | AD19: 是 | AE19: 在察隅县养猪里面有张确权表 | AF19: 否 | AG19: 无需写
A20: 540425201607006 | B20: 林芝市 | C20: 察隅县 | D20: 2016 | E20: 察隅县贫困户藏猪养殖项目 | F20: 察隅县农牧局 | G20: 6个乡镇 | H20: 为我县6个乡镇49个行政村291户建档立卡贫困户修建猪舍5238平方米；购置种公猪49头、种母猪291头、仔猪1272余头。 | I20: =J20+K20 -> 490.394 | J20: 474.2525 | K20: 16.1415 | L20: =M20+N20 -> 474.2525 | M20: 474.2525 | O20: 到户类 | P20: 猪 | Q20: 盘活 | AD20: 是 | AE20: 项目资料 | AF20: 否
A21: 540425201608004 | B21: 林芝市 | C21: 察隅县 | D21: 2016 | E21: 察隅县贫困户养殖鸡项目 | F21: 察隅县农牧局 | G21: 6个乡镇 | H21: 为我县6个乡镇235户建档立卡贫困户修建鸡舍4230平方米；购置鸡苗7600只（公母1：9）；购买饲料等 | I21: =J21+K21 -> 218.605 | J21: 208.605 | K21: 10 | L21: =M21+N21 -> 162.96 | M21: =1629600/10000 -> 162.96 | O21: 到户类 | P21: 鸡 | Q21: 盘活 | AD21: 是 | AE21: 项目资料 | AF21: 否 | AG21: 无需写
A22: 540425201619009 | B22: 林芝市 | C22: 察隅县 | D22: 2016 | E22: 察隅县上察隅镇迟巴村产业扶贫 | F22: 察隅县农牧局 | G22: 上察隅镇迟巴村 | H22: 购买农机具7台；购买猪仔145头，为7户群众修建猪舍140㎡，购买母猪12头，公猪5头；狗仔鸡仔370只，修建鸡舍400㎡；种植板栗核桃8亩；种植黑木耳（每户100菌袋）；种植天麻1800㎡；种植油茶、枇杷180亩 | I22: =J22+K22 -> 160.32 | J22: 160.32 | K22: 0 | L22: =M22+N22 -> 160.32 | M22: 160.32 | N22: 0 | O22: 到户类 | P22: 其他 | Q22: 调整 | S22: 否 | AD22: 否 | AE22: 立项批复，审定金额待定 | AF22: 否 | AG22: 是
A23: 540425201719010 | B23: 林芝市 | C23: 察隅县 | D23: 2017 | E23: 察隅县上察隅镇西巴村珞巴民族服饰加工项目 | F23: 上察隅镇人民政府 | G23: 上察隅镇西巴村 | H23: 修建120米玻璃展柜，购买4台缝纫机，10台编织机，购买编织材料，对原有编织房进行维修以及线路改造 | I23: =J23+K23 -> 24.62 | J23: 24.62 | K23: 0 | L23: =M23+N23 -> 24.62 | M23: 24.62 | N23: 0 | O23: 公益类 | P23: 其他 | Q23: 调整 | S23: 是 | AD23: 是 | AE23: 确权资料 | AF23: 否 | AG23: 无需写
A24: 540425201718001 | B24: 林芝市 | C24: 察隅县 | D24: 2017 | E24: 察隅县察瓦龙乡汽修市场建设项目 | F24: 察隅县扶贫开发投资有限公司 | G24: 察瓦龙乡 | H24: 汽车修理厂849㎡，商业楼2493㎡，洗车间109.12㎡，门卫室14.8㎡，公厕37.41㎡以及大门、室外给排水、室外电气、水泥硬质地面、铺装工程、土石方工程、围墙工程、停车位工程、挡土墙工程、照明工程等 | I24: =J24+K24 -> 1383.28 | J24: 1383.28 | K24: 0 | L24: =M24+N24 -> 1308.153 | M24: 1308.153 | N24: 0 | O24: 经营类 | P24: 商贸流通 | Q24: 巩固 | R24: 巩固 | S24: 是 | T24: 自主运营 | U24: 国企 | V24: 察隅县扶贫开发投资有限公司 | W24: 否 | AB24: 察隅县交通运输局 | AD24: 是 | AE24: 确权资料 | AF24: 是 | AG24: 无需写
A25: 540425201715001 | B25: 林芝市 | C25: 察隅县 | D25: 2017 | E25: 察隅县下察隅镇夏尼村猕猴桃产业园区建设项目 | F25: 察隅县农牧局 | G25: 下察隅镇夏尼村 | H25: 新建培训管理中心212.52㎡，基地入口到培训中心之间道路硬化，硬化面积630.00㎡（道路宽3.5m，长度为180m）及其他配套附属设施建设；种植猕猴桃50亩。 | I25: =J25+K25 -> 150 | J25: 150 | K25: 0 | L25: =M25+N25 -> 132.706 | M25: 132.706 | N25: 0 | O25: 经营类 | P25: 猕猴桃 | Q25: 巩固 | R25: 巩固 | S25: 是 | T25: 委托运营 | U25: 私企 | V25: 察隅县兴农猕猴桃有限公司 | W25: 是 | Y25: 项目盈利时，按照合同约定向村集体分红 | Z25: 99766 | AB25: 察隅县农业农村局​ | AD25: 否 | AE25: 立项+50-1000万台账 | AF25: 否 | AG25: 是
A26: 540425201718002 | B26: 林芝市 | C26: 察隅县 | D26: 2017 | E26: 察隅县汽修市场建设项目 | F26: 察隅县住建局 | G26: 竹瓦根镇 | H26: 1#楼工程（小车机修）2328.31平方米、2#楼工程（大车机修）2510.43平方米、门卫室及附属设施等 | I26: =J26+K26 -> 1936.76 | J26: 1936.76 | K26: 0 | L26: =M26+N26 -> 1904.5077 | M26: 1904.5077 | N26: 0 | O26: 经营类 | P26: 商贸流通 | Q26: 巩固 | R26: 巩固 | S26: 是 | T26: 自主运营 | U26: 国企 | V26: 察隅县扶贫开发投资有限公司 | W26: 否 | AB26: 察隅县交通运输局 | AD26: 否 | AE26: 立项批复+19-25年台账（19年） | AF26: 否 | AG26: 是
A27: 540425201715002 | B27: 林芝市 | C27: 察隅县 | D27: 2017 | E27: 察隅县下察隅镇布巴村等三个行政村猕猴桃种植建设项目 | F27: 下察隅镇人民政府 | G27: 下察隅镇布巴村、京都村、宗古村 | H27: 1、核定布巴村种植猕猴桃370亩，大门一座（含值班室），土地整治及改良370亩，购买种苗37000株，撒播有机肥740吨，修建240立方米（24m×10m×1m）晒水池1处，引水管1300m，修排水沟3374m（0.4m×0.4m），修筑1200m防风林，搭架立桩27750根，牵拉铁丝，安装微喷设备等内容； 2、核定京都村种植猕猴桃243亩，大门一座（含值班室），土地整治及改良243亩，购买种苗24300株，撒播有机肥243吨，网围栏6386米，修建100立方米（10m×10m×1m）晒水池2处，水管道（含1个蓄水池）1024m，搭架立桩18225根，牵拉铁丝，安装微喷设备等内容； 3、核定宗古村种植猕猴桃230亩，大门一座（含值班室），土地整治及改良230亩，购买种苗23000株，撒播有机肥230吨，修筑800米防风林，网围栏3399米，修建100立方米（10m×10m×1m）晒水池2处，引水管道（含1个蓄水池）5800m，搭架立桩17250根，牵拉铁丝，安装微喷设备，修砂石路长1000m（宽3.5m）等内容。 | I27: =J27+K27 -> 2130.42 | J27: 1484.39 | K27: 646.03 | L27: =M27+N27 -> 2100.94 | M27: 1484.39 | N27: 616.55 | O27: 经营类 | P27: 猕猴桃 | Q27: 巩固 | R27: 巩固 | S27: 是 | T27: 委托运营 | U27: 私企 | V27: 察隅县宗古农业发展有限责任公司、察隅县兴农猕猴桃有限公司、西藏林芝察隅巴布吉土地种植专业合作社 | W27: 是 | Z27: 1050407 | AB27: 察隅县农业农村局​ | AC27: 宗古村由察隅县宗古农业发展有限责任公司进行运营、京都村由察隅县兴农猕猴桃有限公司运营、布巴村由西藏林芝察隅巴布吉土地种植专业合作社运营 | AD27: 否 | AE27: 只有电子数据，来源超1000万财评，2019年 | AF27: 是 | AG27: 是
A28: 540425201719011 | B28: 林芝市 | C28: 察隅县 | D28: 2017 | E28: 察隅县古玉乡博学村传统工艺品加工坊项目 | F28: 古玉乡人民政府 | G28: 古玉乡博学村 | H28: 修建传统工艺品加工坊一座 | I28: =J28+K28 -> 36 | J28: 36 | K28: 0 | L28: =M28+N28 -> 36 | M28: 36 | N28: 0 | O28: 经营类 | P28: 商贸流通 | Q28: 巩固 | R28: 调整 | S28: 否 | W28: 否 | AB28: 察隅县农业农村局​ | AD28: 否 | AE28: 数据来源于察隅县古玉乡帮扶产业项目统计表 | AF28: 否 | AG28: 是 | AH28: 是
A29: 540425201719012 | B29: 林芝市 | C29: 察隅县 | D29: 2017 | E29: 察隅县古玉乡罗马村松茸加工坊 | F29: 古玉乡人民政府 | G29: 古玉乡罗马村 | H29: 修建业务用房一座 | I29: =J29+K29 -> 20 | J29: 20 | K29: 0 | L29: =M29+N29 -> 20 | M29: 20 | N29: 0 | O29: 经营类 | P29: 设施农业 | Q29: 升级 | R29: 调整 | S29: 否 | T29: 委托运营 | U29: 个体工商户 | V29: 白玛曲培 | W29: 否 | AB29: 察隅县农业农村局​ | AD29: 否 | AE29: 数据来源于察隅县古玉乡帮扶产业项目统计表 | AF29: 否 | AG29: 是 | AH29: 是
A30: 540425201811001 | B30: 林芝市 | C30: 察隅县 | D30: 2018 | E30: 察隅县察瓦龙乡龙布村重楼种植项目 | F30: 察瓦龙乡人民政府 | G30: 察瓦龙乡龙布村 | H30: “能人+贫困户”，栽种280000株，遮阳网、遮阳架28亩，灌溉水管及土地平整28亩；种苗及设备购置:购买种苗280000株，肥料28吨，病虫害防治及追肥28亩。 | I30: =J30+K30 -> 64.4 | J30: 50 | K30: 14.4 | L30: =M30+N30 -> 64.4 | M30: 50 | N30: 14.4 | O30: 经营类 | P30: 藏药 | Q30: 升级 | R30: 调整 | S30: 否 | AD30: 是 | AE30: 确权资料 | AF30: 否 | AG30: 无需写 | AH30: 是
A31: 540425201811002 | B31: 林芝市 | C31: 察隅县 | D31: 2018 | E31: 察隅县察瓦龙乡扎恩村重楼种植项目 | F31: 察瓦龙乡人民政府 | G31: 察瓦龙乡扎恩村 | H31: “能人+贫困户”，栽种280000株，遮阳网、遮阳架28亩，灌溉水管及土地平整28亩；种苗及设备购置:购买种苗280000株，肥料28吨，病虫害防治及追肥28亩。 | I31: =J31+K31 -> 64.4 | J31: 50 | K31: 14.4 | L31: =M31+N31 -> 64.4 | M31: 50 | N31: 14.4 | O31: 经营类 | P31: 藏药 | Q31: 升级 | R31: 调整 | S31: 否 | AD31: 是 | AE31: 确权资料 | AF31: 否 | AG31: 无需写 | AH31: 是
A32: 540425201816008 | B32: 林芝市 | C32: 察隅县 | D32: 2018 | E32: 察隅县察瓦龙乡苗圃基地建设项目 | F32: 察瓦龙乡人民政府 | G32: 察瓦龙乡 | H32: 项目模式为“能人+贫困户”，PE25灌溉水管及配套设施3000米，土地平整40亩，遮阳网、遮阳架40亩;种苗及设备购置:购买种苗3200株。 | I32: =J32+K32 -> 51.6 | J32: 50 | K32: 1.6 | L32: =M32+N32 -> 51.6 | M32: 50 | N32: 1.6 | O32: 经营类 | P32: 设施农业 | Q32: 升级 | R32: 调整 | S32: 否 | AD32: 是 | AE32: 确权资料 | AF32: 是 | AG32: 无需写 | AH32: 是
A33: 540425201819013 | B33: 林芝市 | C33: 察隅县 | D33: 2018 | E33: 察隅县上察隅镇西巴村铁皮石斛种植扩建项目 | F33: 上察隅镇人民政府 | G33: 上察隅镇西巴村 | H33: 项目模式为“村集体+贫困户”，种植仿野生苗木10亩（含采购苗木60000丛），修建蓄水池1座（长*宽*高为4m*4m*2m），铁丝网围栏1000米，沉砂池、引水渠等。 | I33: =J33+K33 -> 50 | J33: 50 | K33: 0 | L33: =M33+N33 -> 50 | M33: 50 | N33: 0 | O33: 经营类 | P33: 藏药 | Q33: 升级 | R33: 调整 | S33: 是 | T33: 委托运营 | U33: 私企 | V33: 西藏兵哥建筑工程有限公司 | W33: 是 | AD33: 是 | AE33: 确权资料+立项批复 | AF33: 否 | AG33: 无需写 | AH33: 是
A34: 540425201807007 | B34: 林芝市 | C34: 察隅县 | D34: 2018 | E34: 察隅县古玉乡古井村藏香猪养殖项目 | F34: 古玉乡人民政府 | G34: 古玉乡古井村 | H34: 项目模式为“合作社+贫困户”，扩建猪舍53.2㎡；新建铁丝网围栏1300m，办公室及厨房34.44㎡，饲料加工室17.6㎡，育猪室68.04㎡，库房14㎡，待宰室13.44㎡，水池6m3，场地平整765㎡，线路改造、屋面改造1项；采购卫生防疫500头，买种猪340头，购买加工饲料机1台，柴油发电机1台。 | I34: =J34+K34 -> 64.84 | J34: 50 | K34: 14.84 | L34: =M34+N34 -> 64.84 | M34: 50 | N34: 14.84 | O34: 经营类 | P34: 猪 | Q34: 盘活 | R34: 调整 | S34: 是 | T34: 委托运营 | U34: 农牧民专业合作社 | V34: 察隅县古玉乡古井村青冈林藏香猪养殖专业合作社 | W34: 否 | Z34: 28000 | AB34: 察隅县农业农村局​ | AD34: 是 | AE34: 确权资料 | AF34: 是 | AG34: 无需写 | AH34: 是
A35: 540425201808005 | B35: 林芝市 | C35: 察隅县 | D35: 2018 | E35: 察隅县古玉乡古井村藏鸡养殖项目 | F35: 古玉乡人民政府 | G35: 古玉乡古井村 | H35: 项目模式为“能人+贫困户”，新建鸡舍160㎡，新建消毒室、饲料加工间、仓库、职工宿舍64㎡，下蛋室4间，新建蓄水池1座，新建化粪池1座，购置铁丝围栏及立柱550m，场地平整30375m3，道路平整30420m3，铁质大门1座，线路改造1项；种鸡及设备购置费：购买种鸡（藏鸡）1500只，购置饲料加工设备1台，孵化器2台。 | I35: =J35+K35 -> 55.6 | J35: 50 | K35: 5.6 | L35: =M35+N35 -> 55.6 | M35: 50 | N35: 5.6 | O35: 经营类 | P35: 鸡 | Q35: 盘活 | R35: 调整 | S35: 是 | T35: 委托运营 | U35: 个体工商户 | V35: 察隅县兄弟藏鸡养殖场 | W35: 否 | Z35: 51700 | AB35: 察隅县农业农村局​ | AD35: 是 | AE35: 确权资料 | AF35: 是 | AG35: 无需写 | AH35: 是
A36: 540425201807008 | B36: 林芝市 | C36: 察隅县 | D36: 2018 | E36: 察隅县竹瓦根镇扎拉村阿多专业养殖合作社项目 | F36: 竹瓦根镇人民政府 | G36: 竹瓦根镇扎拉村 | H36: 项目模式为“合作社+贫困户”，平整土地2000㎡；新建猪圈20间，总建筑面积340㎡；新建化粪池1座；新建消毒室1座，建筑面积17.6㎡；PE32给水管200m，DN110排污管200m。采购猪苗100头，消毒设备（型号BG-C4）1台 | I36: =J36+K36 -> 71.44 | J36: 50 | K36: 21.44 | L36: =M36+N36 -> 71.44 | M36: 50 | N36: 21.44 | O36: 经营类 | P36: 猪 | Q36: 盘活 | R36: 盘活 | S36: 是 | T36: 委托运营 | U36: 农户 | V36: 刘勇 | AB36: 察隅县农业农村局​ | AD36: 是 | AE36: 确权资料 | AF36: 是 | AG36: 无需写 | AH36: 是
A37: 540425201807009 | B37: 林芝市 | C37: 察隅县 | D37: 2018 | E37: 察隅县竹瓦根镇桑久村藏香猪养殖项目 | F37: 竹瓦根镇人民政府 | G37: 竹瓦根镇桑久村 | H37: 项目模式为“村集体+贫困户”， 新建围墙200m，铁大门1扇，给水管100m，铜芯线100m，仓库及饲养员室1间，消毒室1间，猪圈14间，化粪池1座;设备购置:电力变压器1台，消毒设备1台，种猪1头，母猪10头，猪仔90头 | I37: =J37+K37 -> 53.08 | J37: 50 | K37: 3.08 | L37: =M37+N37 -> 53.08 | M37: 50 | N37: 3.08 | O37: 经营类 | P37: 猪 | Q37: 盘活 | R37: 调整 | S37: 是 | T37: 委托运营 | U37: 农户 | V37: 扎西次仁 | Z37: 41680 | AB37: 察隅县农业农村局​ | AD37: 是 | AE37: 确权资料 | AF37: 是 | AG37: 无需写 | AH37: 是
A38: 540425201805001 | B38: 林芝市 | C38: 察隅县 | D38: 2018 | E38: 察隅县古玉乡博学村犏奶牛养殖场扩建项目 | F38: 古玉乡人民政府 | G38: 古玉乡博学村 | H38: 项目模式为“合作社+贫困户”，新建牛圈319.64m2，建筑工程319.64m2，安装工程319.64m2，大门1座，围墙120m；购置犏奶牛：母牛20头，公牛3头。 | I38: =J38+K38 -> 72.58 | J38: 50 | K38: 22.58 | L38: =M38+N38 -> 72.58 | M38: 50 | N38: 22.58 | O38: 经营类 | P38: 乳 | Q38: 升级 | R38: 升级 | S38: 是 | T38: 委托运营 | U38: 农牧民专业合作社 | V38: 察隅县古玉乡博学村杰荣养殖专业合作社 | W38: 否 | Z38: 76100 | AB38: 察隅县农业农村局​ | AD38: 是 | AE38: 确权资料 | AF38: 否 | AG38: 无需写
A39: 540425201807010 | B39: 林芝市 | C39: 察隅县 | D39: 2018 | E39: 下察隅镇京都村藏香猪养殖项目 | F39: 下察隅镇人民政府 | G39: 下察隅镇京都村 | H39: 1.扩建猪舍面积153.88平方米；2.新建饲料库房及饲料加工房70.56平方米；3.建蓄水池1座（采用砖混结构长3m*宽4m*高1.2m）；4.买可繁育母猪60头（繁育母猪需为已生育过1窝猪仔的母猪）、种猪3头（种猪年龄1.5-2年）；5.购买加工饲料机1台（型号：9FQ40-28,动力：11-15kw）;6.购买柴油发电机1台（型号：L32-R00，功率：11-15KW）；7.新建猪舍C20混凝土硬化路面91.02平方米；8.PE水管直径75mmPE管300m,PE水管直径25mmPE管260m;9.新建简易木桥一座，采用木质结构（10米*2米）；10.原猪舍铁皮100张；11.铁丝围栏700m,围栏1.5m高，每隔3米设置一根圆钢管立柱，立柱高3m,立柱基础埋深30cm；11.新建大门2个（2m*3m）。 | I39: =J39+K39 -> 54.44 | J39: 50 | K39: 4.44 | L39: =M39+N39 -> 54.44 | M39: 50 | N39: 4.44 | O39: 经营类 | P39: 猪 | Q39: 盘活 | R39: 升级 | S39: 是 | T39: 委托运营 | U39: 农牧民专业合作社 | V39: 下察隅镇京都村阿胖养殖专业合作社 | AB39: 察隅县农业农村局​ | AD39: 是 | AE39: 确权资料 | AF39: 是 | AG39: 无需写
A40: 540425201807011 | B40: 林芝市 | C40: 察隅县 | D40: 2018 | E40: 察隅县古拉乡俄玉村藏香猪养殖项目 | F40: 古拉乡人民政府 | G40: 古拉乡俄玉村 | H40: 项目模式为“合作社+贫困户”，建设猪舍105.7㎡，育种室和隔离室164.16㎡，仓库及管理用房68.64㎡，围墙200m，供水1项，购买猪仔80头，种猪4头，能繁母猪20头，饲料、防疫及运转费用1项，供电1项。 | I40: =J40+K40 -> 50 | J40: 50 | K40: 0 | L40: =M40+N40 -> 50 | M40: 50 | N40: 0 | O40: 经营类 | P40: 猪 | Q40: 盘活 | R40: 盘活 | S40: 是 | W40: 否 | AB40: 察隅县农业农村局 | AD40: 是 | AE40: 确权资料 | AF40: 是 | AG40: 无需写 | AH40: 是
A41: 540425201812003 | B41: 林芝市 | C41: 察隅县 | D41: 2018 | E41: 察隅县产业扶贫毕达村茶叶种植项目 | F41: 察隅县扶贫开发投资有限公司 | G41: 上察隅毕达村 | H41: 土地平整：土石方工程1项，筑田埂18975.08m，挖土沟(背沟开挖）12821m；灌溉工程:管道工程1项，蓄水池1座，沉砂池1座；茶叶苗种植工程:种植1794940株；附属工程：钢丝网围栏3500m；设备及工器具购置：购买及运输除草机4部，购买及运输修剪机4台，购买及运输中耕机4台，购买及运输施肥机2台，购买、运输及安装防虫灯、黄板等设施51台，购买运输安装基地大门1个，购买安装标识牌1个。 | I41: =J41+K41 -> 915.53 | J41: 457.765 | K41: 457.765 | L41: =M41+N41 -> 566.12056 | M41: 283.06028 | N41: 283.06028 | O41: 经营类 | P41: 茶 | Q41: 升级 | R41: 升级 | S41: 否 | AC41: 项目尚未移交，还在管护中 | AD41: 是 | AE41: 确权资料+50-1000万财评统计表 | AF41: 否 | AG41: 无需写
A42: 540425201812004 | B42: 林芝市 | C42: 察隅县 | D42: 2018 | E42: 察隅县产业扶贫松古村茶叶种植项目 | F42: 察隅县扶贫开发投资有限公司 | G42: 下察隅镇松古村 | H42: 土地平整：土石方工程1项，修筑田埂24087m，挖土沟(背沟开挖）16275m；灌溉工程：管道工程1项，蓄水池1座，沉砂池1座；茶叶苗种植2598500株；附属工程：钢丝网围栏3500m，设备及工器具购置费，购买及运输除草机4部，购买及运输修剪机4台，购买及运输中耕机4台，购买及运输施肥机2台，购买、运输及安装防虫灯、黄板等设施65台，购买运输安装基地大门1个，购买安装标识牌1个。 | I42: =J42+K42 -> 1205.59 | J42: 602.795 | K42: 602.795 | L42: =M42+N42 -> 937.07852 | M42: 468.53926 | N42: 468.53926 | O42: 经营类 | P42: 茶 | Q42: 升级 | R42: 升级 | S42: 是 | AD42: 是 | AE42: 确权资料+50-1000万台账+财评 | AF42: 否 | AG42: 无需写
A43: 540425201819014 | B43: 林芝市 | C43: 察隅县 | D43: 2018 | E43: 西藏牧野香畜禽养殖基地建设项目 | F43: 察隅县扶贫开发投资有限公司 | G43: 竹瓦根镇学尼村 | H43: 新建猪舍375.06平方米、库房153.52平方米、宿舍及办公室119.31平方米、铁丝网围栏465m、病害猪隔离圈24平方米、无公害处理设施16平方米、场地硬化562.45平方米、新建大门一座，采购相关设备及相应配套设施。 | I43: =J43+K43 -> 379.93 | J43: 250 | K43: 129.93 | L43: =M43+N43 -> 361.46623 | M43: 236.27117 | N43: 125.19505 | O43: 经营类 | P43: 其他 | Q43: 盘活 | R43: 巩固 | S43: 否 | AC43: 底稿已写 | AD43: 是 | AE43: 确权资料 | AF43: 否 | AG43: 无需写
A44: 540425201812006 | B44: 林芝市 | C44: 察隅县 | D44: 2018 | E44: 察隅县茶叶产业项目（第二批） | F44: 察隅县产业发展工作领导小组办公室 | G44: 下察隅沙玛村、上察隅米古村 | H44: 在沙玛村、米古村、群众房前屋后等地点实施茶叶种植及配套附属设施建设等 | I44: =J44+K44 -> 2000 | J44: 2000 | K44: 0 | L44: =M44+N44 -> 2000 | M44: 2000 | N44: 0 | O44: 经营类 | P44: 茶 | Q44: 升级 | R44: 升级 | S44: 是 | T44: 委托运营 | U44: 私企 | V44: 林芝毛尖茶叶有限责任公司 | W44: 否 | AA44: 800 | AB44: 察隅县农业农村局​ | AC44: 与沙玛村枇杷种植水肥一体化项目同一地点实施，枇杷茶叶套种，期间补种茶叶，原茶叶数量不详 | AD44: 否 | AE44: 数据来源于附件1：2019年12月份项目月报(最终版)（新建） | AF44: 否 | AG44: 是
A45: 540425201812008 | B45: 林芝市 | C45: 察隅县 | D45: 2018 | E45: 察隅县荣玉村2018年有机茶叶种植项目 | F45: 察隅县扶贫开发投资有限公司 | G45: 上察隅镇荣玉村 | H45: 土地平整650亩，修建灌溉与排水工程，茶叶种植，第一次树苗种植1094660株，第二次补苗131359株，第三次补苗10508株，设备采购及附属设施 | I45: =J45+K45 -> 435.6 | J45: 435.6 | K45: 0 | L45: =M45+N45 -> 435.6 | M45: 435.6 | N45: 0 | O45: 经营类 | P45: 茶 | Q45: 升级 | R45: 升级 | S45: 否 | W45: 否 | AC45: 村里收取管护费，分给村民，800/亩，共计158亩。收取了22年、23年。 | AD45: 是 | AE45: 本项目资料和确权资料同名，但是内容不一样，需要核实本项目来源 | AF45: 否 | AG45: 无需写
A46: 540425201712009 | B46: 林芝市 | C46: 察隅县 | D46: 2017 | E46: 察隅县体育村2018年有机茶叶种植项目 | F46: 察隅县扶贫开发投资有限公司 | G46: 上察隅镇体育村 | H46: 土地平整244.12亩，修建灌溉与排水工程，茶叶种植、设备采购及附属设施。第一次树苗种植854420株，第二次补苗102530株，第三次补苗8202株，及附属设施等。 | I46: =J46+K46 -> 600.7 | J46: 400.47 | K46: 200.23 | L46: =M46+N46 -> 600.7 | M46: 400.47 | N46: 200.23 | O46: 经营类 | P46: 茶 | Q46: 升级 | R46: 调整 | S46: 否 | AD46: 是 | AE46: 确权资料+50-1000万财评统计表 | AF46: 否 | AG46: 无需写
A47: 540425201804004 | B47: 林芝市 | C47: 察隅县 | D47: 2018 | E47: 龙普村嘉兴组犏奶牛项目 | F47: 察隅县农业农村局 | G47: 察瓦龙乡龙普村 | H47: 为察瓦龙乡龙普村嘉兴组购置牦奶牛15头，种牛1头 | I47: =J47+K47 -> 12.5112 | J47: 12.5112 | K47: 0 | L47: =M47+N47 -> 12.5112 | M47: 12.5112 | N47: 0 | O47: 到户类 | P47: 牦牛 | Q47: 调整 | S47: 否 | AC47: 确权表主体是察瓦龙乡人民政府 | AD47: 是 | AE47: 确权资料 | AF47: 否 | AG47: 无需写
A48: 540425201820008 | B48: 林芝市 | C48: 察隅县 | D48: 2018 | E48: 察隅县察瓦龙乡卡地村软籽石榴种植基地建设项目 | F48: 察隅县林业和草原局 | G48: 察瓦龙乡卡地村 | H48: 营造林：种苗9804株，种植130.7亩，培训指导2年，有机肥98.04吨，病虫害防治130.7亩，人工修枝及管理130.7亩，工具费130.7亩（每亩配2把修枝剪、1个喷雾器）。 | I48: =J48+K48 -> 180.14 | J48: 180.14 | K48: 0 | L48: =M48+N48 -> 171.65907 | M48: 171.65907 | N48: 0 | O48: 经营类 | P48: 石榴 | Q48: 调整 | R48: 调整 | S48: 否 | AC48: 已搬迁 | AD48: 是 | AE48: 确权资料 | AF48: 否 | AG48: 无需写 | AH48: 是
A49: 540425201820009 | B49: 林芝市 | C49: 察隅县 | D49: 2018 | E49: 察隅县察瓦龙乡格布村软籽石榴种植基地建设项目 | F49: 察隅县林业和草原局 | G49: 察瓦龙乡格布村 | H49: 营造林：种苗8313株，种植184.7亩，培训指导2年，有机肥83.13吨，病虫害防治184.7亩，人工修枝及管理184.7亩，工具费184.7亩（每亩配2把修枝剪、1个喷雾器）。 | I49: =J49+K49 -> 160.52 | J49: 160.52 | K49: 0 | L49: =M49+N49 -> 160.52 | M49: 160.52 | N49: 0 | O49: 经营类 | P49: 石榴 | Q49: 调整 | R49: 盘活 | S49: 是 | T49: 委托运营 | U49: 个体工商户 | V49: 仁青 | W49: 否 | AB49: ​察隅县农业农村局 | AC49: 确权表主体是察隅县扶贫开发办公室 | AD49: 是 | AE49: 确权资料+50-1000万财评统计表 | AF49: 否 | AG49: 无需写 | AH49: 是
A50: 540425201820010 | B50: 林芝市 | C50: 察隅县 | D50: 2018 | E50: 察隅县察瓦龙乡左布村软籽石榴种植基地建设项目 | F50: 察隅县林业和草原局 | G50: 察瓦龙乡左布村 | H50: 营造林：种苗5441株，种植120.9亩，培训指导2年，有机肥54.41吨，病虫害防治120.9亩，人工修枝及管理120.9亩，工具费120.9亩（每亩配2把修枝剪、1个喷雾器） | I50: =J50+K50 -> 101.45 | J50: 101.45 | K50: 0 | L50: =M50+N50 -> 95.284457 | M50: 95.284457 | N50: 0 | O50: 经营类 | P50: 石榴 | Q50: 调整 | R50: 盘活 | S50: 否 | T50: 自主运营 | W50: 否 | AB50: 察隅县农业农村局 | AD50: 是 | AE50: 确权资料 | AF50: 是 | AG50: 无需写 | AH50: 是
A51: 540425201820011 | B51: 林芝市 | C51: 察隅县 | D51: 2018 | E51: 察隅县察瓦龙乡处尼村软籽石榴种植基地建设项目 | F51: 察隅县林业和草原局 | G51: 察瓦龙乡处尼村 | H51: 营造林：种苗2610株，种植58亩，培训指导2年，有机肥26.1吨，病虫害防治58亩，人工修枝及管理58亩，工具费58亩（每亩配2把修枝剪、1个喷雾器）。 | I51: =J51+K51 -> 60.87 | J51: 60.87 | K51: 0 | L51: =M51+N51 -> 57.611099 | M51: 57.611099 | N51: 0 | O51: 经营类 | P51: 石榴 | Q51: 调整 | R51: 调整 | S51: 否 | AC51: 已搬迁 | AD51: 是 | AE51: 确权资料 | AF51: 否 | AG51: 无需写 | AH51: 是
A52: 540425201820012 | B52: 林芝市 | C52: 察隅县 | D52: 2018 | E52: 察隅县察瓦龙乡沙布村软籽石榴种植基地建设项目 | F52: 察隅县林业和草原局 | G52: 察瓦龙乡沙布村 | H52: 营造林：种苗7866株，种植174.81亩，培训指导2年，有机肥78.66吨，病虫害防治174.81亩，人工修枝及管理174.81亩，工具费174.81亩（每亩配2把修枝剪、1个喷雾器） | I52: =J52+K52 -> 148.07 | J52: 148.07 | K52: 0 | L52: =M52+N52 -> 138.44953 | M52: 138.44953 | N52: 0 | O52: 经营类 | P52: 石榴 | Q52: 调整 | R52: 升级 | S52: 否 | T52: 自主运营 | AB52: 察隅县农业农村局 | AD52: 是 | AE52: 确权资料 | AF52: 否 | AG52: 无需写
A53: 540425201820013 | B53: 林芝市 | C53: 察隅县 | D53: 2018 | E53: 察隅县古拉乡察空村软籽石榴种植基地建设项目 | F53: 察隅县林业和草原局 | G53: 古拉乡察空村 | H53: 营造林：种苗23573株，种植428.6亩，培训指导2年，有机肥235.73吨，病虫害防治428.6亩，人工修枝及管理428.36亩，工具费428.6亩（每亩配2把修枝剪、1个喷雾器），保水剂428.6亩，网围栏4871米；给水工程：蓄水池120㎡，管网工程1项；土石方工程：客土改良2000m³，机械挖坑428.6亩。 | I53: =J53+K53 -> 521.33 | J53: 521.33 | K53: 0 | L53: =M53+N53 -> 440.09591 | M53: 440.09591 | N53: 0 | O53: 经营类 | P53: 石榴 | Q53: 调整 | R53: 调整 | S53: 否 | AC53: 已搬迁 | AD53: 是 | AE53: 确权资料 | AF53: 是 | AG53: 无需写 | AH53: 是
A54: 540425201819016 | B54: 林芝市 | C54: 察隅县 | D54: 2018 | E54: 察瓦龙乡、古拉乡2018年秋季庭院经济项目 | F54: 察隅县林业和草原局 | G54: 察瓦龙乡邓许村、扎那村、龙普村、岗藏村、康然村、前中瓦村、梦扎村、格日村、拉卡村、巴布村、目巴村、学巴村、珠拉村、洪东村、扎然村、瓦布村、古拉乡安巴村、关龙村、觉不如村、则巴村、扎兴村、日托村、俄玉村 | H54: 在察瓦龙乡、古拉乡23个村开展庭院经济项目，为23个村群众发放经济林木1.5万余株。 | I54: =J54+K54 -> 153.1 | J54: 153.1 | K54: 0 | L54: =M54+N54 -> 153.1 | M54: 153.1 | N54: 0 | O54: 到户类 | P54: 其他 | Q54: 调整 | AC54: 已搬迁 | AD54: 是 | AE54: 确权资料 | AF54: 否 | AG54: 无需写
A55: 540425201815003 | B55: 林芝市 | C55: 察隅县 | D55: 2018 | E55: 察隅县产业扶贫猕猴桃种植基地建设项目 | F55: 察隅县扶贫开发投资有限公司 | G55: 下察隅镇松古村 | H55: 生活管理用房：建筑装饰工程123.96㎡，安装工程123.96㎡；管道工程8520m，水池工程2座，道路工程1188m3，围墙945m；其他工程：混凝土立柱22500根，网围栏1290m，架设钢丝60t，土地整治300亩，树苗种植27000株，广告牌1套。 | I55: =J55+K55 -> 771.95 | J55: 500 | K55: 271.95 | L55: =M55+N55 -> 693.68556 | M55: 474.86323 | N55: 218.82233 | O55: 经营类 | P55: 猕猴桃 | Q55: 巩固 | R55: 升级 | S55: 是 | AD55: 是 | AE55: 确权资料+50-1000万财评统计表（没有审定金额） | AF55: 否 | AG55: 无需写
A56: 540425201820015 | B56: 林芝市 | C56: 察隅县 | D56: 2018 | E56: 察隅县察瓦龙乡扎恩村软籽石榴种植基地建设项目 | F56: 察隅县林业和草原局 | G56: 察瓦龙乡扎恩村 | H56: 营造林：种苗4344株，种植96.5亩，培训指导2年，有机肥43.44吨，病虫害防治96.5亩，人工修枝及管理96.5亩，工具费96.5亩（每亩配2把修枝剪、1个喷雾器） | I56: =J56+K56 -> 77.25 | J56: 77.25 | K56: 0 | L56: =M56+N56 -> 77.25 | M56: 77.25 | N56: 0 | O56: 经营类 | P56: 石榴 | Q56: 调整 | R56: 盘活 | S56: 否 | T56: 自主运营 | U56: 农村集体经济组织 | V56: 林芝市察隅县察瓦龙乡扎恩村股份经济合作社 | W56: 否 | AB56: 察隅县农业农村局 | AD56: 否 | AE56: 立项批复+50-1000万台账（未注明审定金额） | AF56: 否 | AG56: 是 | AH56: 是
A57: 540425201819017 | B57: 林芝市 | C57: 察隅县 | D57: 2018 | E57: 察隅县古玉乡古井村松茸加工房 | F57: 古玉乡人民政府 | G57: 古玉乡古井村 | H57: 修建业务用房一座 | I57: =J57+K57 -> 30 | J57: 30 | K57: 0 | L57: =M57+N57 -> 30 | M57: 30 | N57: 0 | O57: 经营类 | P57: 设施农业 | Q57: 升级 | R57: 调整 | S57: 是 | T57: 委托运营 | U57: 个体工商户 | V57: 乔君伟 | W57: 否 | AB57: 察隅县农业农村局​ | AD57: 否 | AE57: 数据来源于察隅县古玉乡帮扶产业项目统计表 | AF57: 否 | AG57: 是
A58: 540425201819018 | B58: 林芝市 | C58: 察隅县 | D58: 2018 | E58: 察隅县古玉乡然乌学村然乌学组松茸加工坊 | F58: 古玉乡人民政府 | G58: 古玉乡然乌学村 | H58: 修建业务用房一座 | I58: =J58+K58 -> 43 | J58: 40 | K58: 3 | L58: =M58+N58 -> 40 | M58: 40 | N58: 0 | O58: 经营类 | P58: 其他 | Q58: 调整 | R58: 调整 | S58: 否 | W58: 否 | AB58: 察隅县农业农村局​ | AD58: 否 | AE58: 数据来源于2013年批复项目汇总表-“林芝地区2013年批复扶贫项目汇总表” | AF58: 否 | AG58: 是 | AH58: 是
A59: 540425201820017 | B59: 林芝市 | C59: 察隅县 | D59: 2018 | E59: 察隅县察瓦龙乡昌西村软籽石榴种植基地建设项目 | F59: 察隅县林业和草原局 | G59: 察瓦龙乡昌西村 | H59: 营造林：种苗14022株，种植311.6亩，培训指导2年，有机肥140.22吨，病虫害防治311.6亩，工具费311.6亩（每亩配2把修枝剪、1个喷雾器） | I59: =J59+K59 -> 238.36 | J59: 238.36 | K59: 0 | L59: =M59+N59 -> 238.36 | M59: 238.36 | N59: 0 | O59: 经营类 | P59: 石榴 | Q59: 调整 | R59: 盘活 | S59: 是 | AD59: 否 | AE59: 确权资料，审定金额待定 | AF59: 否 | AG59: 是 | AH59: 是
A60: 540425201918003 | B60: 林芝市 | C60: 察隅县 | D60: 2019 | E60: 察隅县竹瓦根镇沙通坝建材市场建设项目 | F60: 察隅县扶贫开发投资有限公司 | G60: 竹瓦根镇 | H60: 1#楼：建筑装饰工程828.99m2，安装工程828.99m2；2#楼：建筑装饰工程671.58m2，安装工程671.58m2；3#楼：建筑装饰工程1446.48m2，安装工程1446.48m2；4#楼：建筑装饰工程671.58m2，安装工程671.58m2；5#楼：建筑装饰工程576.45m2，安装工程576.45m2；6#楼：建筑装饰工程1177.38m2，安装工程1177.38m2；主大门1座，附属工程：室外电气1项，车行硬化工程2689.82m2，人行硬化工程375.9m2，次大门1座，挡土墙工程300.74m，绿化工程1159.45m2，土石方工程1项，通透式围墙456.69m，室外给排水1项 | I60: =J60+K60 -> 2476 | J60: 2476 | K60: 0 | L60: =M60+N60 -> 2304.7426 | M60: 2304.7426 | N60: 0 | O60: 经营类 | P60: 商贸流通 | Q60: 巩固 | R60: 巩固 | S60: 是 | T60: 自主运营 | U60: 国企 | V60: 察隅县扶贫开发投资有限公司 | W60: 否 | AB60: 察隅县住房和城乡建设局 | AD60: 是 | AE60: 确权资料+超过1千万的财评台账（21年） | AF60: 否 | AG60: 无需写
A61: 540425201920018 | B61: 林芝市 | C61: 察隅县 | D61: 2019 | E61: 察隅县古拉乡石榴种植项目 | F61: 古拉乡人民政府 | G61: 古拉乡 | H61: 石榴种植30亩，购置苗木2000株，有机肥、农家肥、新建围栏1000m、病虫害防治30亩、人工修枝及管护30亩，60mmPE管400m，25mmPE管1600m，新建蓄水池1座（2m*2m*2m），土地平整30亩 | I61: =J61+K61 -> 50 | J61: 50 | K61: 0 | L61: =M61+N61 -> 50 | M61: 50 | N61: 0 | O61: 经营类 | P61: 石榴 | Q61: 调整 | R61: 调整 | S61: 否 | T61: 自主运营 | U61: 农村集体经济组织 | V61: 林芝市察隅县古拉乡则巴村股份经济合作社 | W61: 否 | Z61: 62000 | AB61: 察隅县农业农村局 | AD61: 是 | AE61: 确权资料 | AF61: 是 | AG61: 无需写
A62: 540425201908006 | B62: 林芝市 | C62: 察隅县 | D62: 2019 | E62: 竹瓦根镇空档村“4+1”藏鸡养殖项目 | F62: 竹瓦根镇人民政府 | G62: 竹瓦根镇空档村 | H62: 1、新建鸡舍255.60㎡；2、新建门卫室及消毒室57.76㎡；3、新增给水管道120m；4、新增排水管道100m（双壁波纹管Φ200）；5、新增供电线路100m；6、新增铁艺大门1座（宽4米，高3.6米）；7、新建消毒池1座；8、新建防护网600m；9、购买喂食槽4个；10、购买藏鸡苗400只；11、购买成年藏鸡100只 | I62: =J62+K62 -> 62.11 | J62: 60 | K62: 2.11 | L62: =M62+N62 -> 62.11 | M62: 60 | N62: 2.11 | O62: 经营类 | P62: 鸡 | Q62: 盘活 | R62: 调整 | S62: 是 | T62: 委托运营 | U62: 农户 | V62: 布索朗 | W62: 否 | Z62: 60000 | AA62: 2 | AB62: 察隅县农业农村局​ | AD62: 是 | AE62: 确权资料+50-1000万财评统计表 | AF62: 否 | AG62: 无需写 | AH62: 是
A63: 540425201907012 | B63: 林芝市 | C63: 察隅县 | D63: 2019 | E63: 下察隅镇沙琼村藏香猪养殖项目 | F63: 下察隅镇人民政府 | G63: 下察隅镇沙琼村 | H63: 新建猪舍200㎡、饲料库60㎡及饲料加工房40㎡、蓄水池1座、硬化路面及购买种猪、饲料、柴油发电机等 | I63: =J63+K63 -> 53.68 | J63: 50 | K63: 3.68 | L63: =M63+N63 -> 53.68 | M63: 50 | N63: 3.68 | O63: 经营类 | P63: 猪 | Q63: 盘活 | R63: 升级 | S63: 是 | T63: 委托运营 | U63: 农牧民专业合作社 | V63: 察隅县下察隅镇沙琼村小次仁农民专业合作社 | W63: 否 | Z63: 96600 | AB63: 察隅县农业农村局​ | AD63: 是 | AE63: 确权资料 | AF63: 是 | AG63: 无需写
A64: 540425201907013 | B64: 林芝市 | C64: 察隅县 | D64: 2019 | E64: 下察隅镇自更村仁青罗布生态养殖专业合作社藏香猪养殖项目 | F64: 下察隅镇人民政府 | G64: 下察隅镇自更村 | H64: 新建饲料仓库59.04平方米，配套网围栏等附属设施 | I64: =J64+K64 -> 30 | J64: 30 | K64: 0 | L64: =M64+N64 -> 30 | M64: 30 | N64: 0 | O64: 经营类 | P64: 猪 | Q64: 盘活 | R64: 调整 | S64: 否 | AD64: 是 | AE64: 确权资料 | AF64: 否 | AG64: 无需写 | AH64: 是
A65: 540425201907014 | B65: 林芝市 | C65: 察隅县 | D65: 2019 | E65: 下察隅镇拉丁村藏香猪养殖项目 | F65: 下察隅镇人民政府 | G65: 下察隅镇拉丁村 | H65: 新建猪圈149.24平方米，新建蓄水池3.14立方米，化粪池一座3立方米等附属设施 | I65: =J65+K65 -> 20 | J65: 20 | K65: 0 | L65: =M65+N65 -> 20 | M65: 20 | N65: 0 | O65: 经营类 | P65: 猪 | Q65: 盘活 | R65: 盘活 | S65: 是 | T65: 委托运营 | U65: 农户 | V65: 谢次仁 | W65: 否 | AD65: 是 | AE65: 确权资料 | AF65: 是 | AG65: 无需写 | AH65: 是
A66: 540425201907015 | B66: 林芝市 | C66: 察隅县 | D66: 2019 | E66: 下察隅镇塔玛村藏猪养殖项目 | F66: 下察隅镇人民政府 | G66: 下察隅镇塔玛村 | H66: 扩建猪圈51.34平米，并配套库房、饲料加工厂、围栏等附属设施。 | I66: =J66+K66 -> 20 | J66: 20 | K66: 0 | L66: =M66+N66 -> 20 | M66: 20 | N66: 0 | O66: 经营类 | P66: 猪 | Q66: 盘活 | R66: 升级 | S66: 是 | T66: 自主运营 | U66: 农牧民专业合作社 | V66: 塔玛村藏香猪养殖专业合作社 | AD66: 是 | AE66: 确权资料 | AF66: 否 | AG66: 无需写
A67: 540425201908007 | B67: 林芝市 | C67: 察隅县 | D67: 2019 | E67: 察隅县竹瓦根镇扎拉村“4+1”藏鸡养殖项目 | F67: 竹瓦根镇人民政府 | G67: 竹瓦根镇扎拉村 | H67: 鸡舍、仓库、化粪池、铁大门、附属设施部分、设备购置部分 | I67: =J67+K67 -> 41.03 | J67: 30 | K67: 11.03 | L67: =M67+N67 -> 41.03 | M67: 30 | N67: 11.03 | O67: 经营类 | P67: 鸡 | Q67: 盘活 | R67: 盘活 | S67: 否 | T67: 委托运营 | U67: 农户 | V67: 成晓 | AD67: 是 | AE67: 确权资料 | AF67: 否 | AG67: 无需写 | AH67: 是
A68: 540425201907016 | B68: 林芝市 | C68: 察隅县 | D68: 2019 | E68: 察隅县察瓦龙乡扎那村藏香猪养殖项目 | F68: 察瓦龙乡人民政府 | G68: 察瓦龙乡扎那村 | H68: 新建养猪厂面积314.32㎡（采用砖混结构），购买母猪30头，公猪3头，购买饲料加工机1台（型号：9FQ40－28，动力：11－15KW），购买柴油发电机1台（型号：Ｌ32－ROO，动力：23KW），新建猪舍C20砼硬化路面180.64㎡，饲养用水水管直径75mmPE管300m,饲养用水水管直径25mmPE管260m，新建大门一座 | I68: =J68+K68 -> 50.6 | J68: 50 | K68: 0.6 | L68: =M68+N68 -> 50.6 | M68: 50 | N68: 0.6 | O68: 经营类 | P68: 猪 | Q68: 盘活 | R68: 调整 | S68: 否 | W68: 否 | AB68: 察隅县农业农村局 | AC68: 资产闲置了 | AD68: 是 | AE68: 确权资料 | AF68: 否 | AG68: 无需写 | AH68: 是
A69: 540425201907017 | B69: 林芝市 | C69: 察隅县 | D69: 2019 | E69: 察隅县竹瓦根镇生猪养殖项目 | F69: 竹瓦根镇人民政府 | G69: 竹瓦根镇 | H69: 新建猪舍153.78平方米，新建值班室44.65平方米，硬化工程115.02平方米，新建网围栏114.50米，新建挡土墙工程1.06立方米，挖填方工程1项，新建大门一座，室外给排水工程1项，室外电气工程1项；种猪、小猪、柴油发电机、饲料加工机等设备购置 | I69: =J69+K69 -> 50 | J69: 50 | K69: 0 | L69: =M69+N69 -> 50 | M69: 50 | N69: 0 | O69: 经营类 | P69: 猪 | Q69: 盘活 | R69: 盘活 | S69: 否 | AD69: 是 | AE69: 确权资料+立项批复 | AF69: 否 | AG69: 无需写 | AH69: 是
A70: 540425201919019 | B70: 林芝市 | C70: 察隅县 | D70: 2019 | E70: 察隅县察瓦龙乡前中瓦村核桃榨油坊建设项目 | F70: 察瓦龙乡人民政府 | G70: 察瓦龙乡前中瓦村 | H70: 新建特色产品加工坊173.50m²，硬化工程220m²，土石方工程1500m3，新建围墙90m,新建大门1座，购置核桃加工设备1套 | I70: =J70+K70 -> 50.06 | J70: 50 | K70: 0.06 | L70: =M70+N70 -> 50.06 | M70: 50 | N70: 0.06 | O70: 经营类 | P70: 设施农业 | Q70: 升级 | R70: 盘活 | S70: 是 | T70: 委托运营 | U70: 个体工商户 | V70: 多吉 | W70: 否 | AB70: 察隅县农业农村局 | AD70: 是 | AE70: 确权资料 | AF70: 否 | AG70: 无需写 | AH70: 是
A71: 540425201919020 | B71: 林芝市 | C71: 察隅县 | D71: 2019 | E71: 察隅县察瓦龙乡处尼村特色农产品加工坊建设项目 | F71: 察瓦龙乡人民政府 | G71: 察瓦龙乡处尼村 | H71: 新建特色产品加工坊558.96m²，硬化工程423.12m²，购置仙人掌加工设备1套，核桃加工设备1套 | I71: =J71+K71 -> 76.11 | J71: 50 | K71: 26.11 | L71: =M71+N71 -> 76.11 | M71: 50 | N71: 26.11 | O71: 经营类 | P71: 设施农业 | Q71: 升级 | R71: 调整 | S71: 否 | AC71: 已搬迁 | AD71: 是 | AE71: 确权资料 | AF71: 否 | AG71: 无需写 | AH71: 是
A72: 540425201919021 | B72: 林芝市 | C72: 察隅县 | D72: 2019 | E72: 察隅县2019年庭院经济扶贫种植项目 | F72: 察隅县林业和草原局 | G72: 前中瓦村、拉卡村、松塔村、扎那村、扎恩村、昌西村、曲珠村、龙普村、沙布村、目巴村、格布村、俄玉村 | H72: 购置经济林木，前中瓦村：石榴1440株，苹果600株；拉卡村：石榴585株；松塔村：石榴500株；扎那村：石榴2908株；扎恩村：石榴2045株，苹果630株，橘子380株，水蜜桃25株；昌西村：石榴160株；曲珠村：石榴1030株；龙普村：石榴1240株，苹果995株，橘子115株，水蜜桃230株；沙布村：苹果148株，橘子145株；目巴村：石榴2100株；格布村：石榴675株；俄玉村：苹果380株，水蜜桃380株 | I72: =J72+K72 -> 150 | J72: 150 | K72: 0 | L72: =M72+N72 -> 150 | M72: 150 | N72: 0 | O72: 公益类 | P72: 其他 | Q72: 调整 | AD72: 否 | AE72: 立项批复，审定金额待定 | AF72: 是 | AG72: 是
A73: 540425201912011 | B73: 林芝市 | C73: 察隅县 | D73: 2019 | E73: 察隅县上察隅镇体育村通迪茶叶种植项目 | F73: 察隅县产业发展工作领导小组办公室 | G73: 上察隅镇体育村 | H73: 上察隅镇体育迪通种植茶叶136亩，新建蓄水池，购买茶苗，安装网围栏等附属设施 | I73: =J73+K73 -> 285.98 | J73: 285.98 | K73: 0 | L73: =M73+N73 -> 279.81427 | M73: 279.81427 | N73: 0 | O73: 经营类 | P73: 茶 | Q73: 升级 | R73: 调整 | S73: 否 | AD73: 否 | AE73: 立项批复+19-25年台账（20年） | AF73: 否 | AG73: 是
A74: 540425201919022 | B74: 林芝市 | C74: 察隅县 | D74: 2019 | E74: 察隅县古拉乡则巴村扩建核桃加工项目 | F74: 古拉乡人民政府 | G74: 古拉乡则巴村 | H74: 加工场地晒坝硬化260㎡，围墙48m，线路改造180m；设备购置：液压榨油机1台，剥壳机 2台，分拣机1台，烘干机1台，过滤器2台，核桃粉碎机（核桃粉）1台，包装机2台，包装袋及包装瓶1项，变压器及安装备件等1台，销售点装修费及柜台等1项，后期运转经费1项 | I74: =J74+K74 -> 50 | J74: 50 | K74: 0 | L74: =M74+N74 -> 50 | M74: 50 | N74: 0 | O74: 经营类 | P74: 设施农业 | Q74: 升级 | R74: 调整 | S74: 否 | AB74: ​察隅县农业农村局 | AC74: 已搬迁 | AD74: 是 | AE74: 确权资料 | AF74: 是 | AG74: 无需写 | AH74: 是
A75: 540425201919023 | B75: 林芝市 | C75: 察隅县 | D75: 2019 | E75: 察隅县本土生态农产品加工项目 | F75: 察隅县农业农村局 | G75: 上察隅镇迟巴村 | H75: 在上察隅迟巴村建立鸡爪股粉生产线、花生生产线等附属设施 | I75: =J75+K75 -> 250 | J75: 250 | K75: 0 | L75: =M75+N75 -> 239.92703 | M75: 239.92703 | N75: 0 | O75: 经营类 | P75: 设施农业 | Q75: 升级 | R75: 盘活 | S75: 否 | AC75: 产权未确定 | AD75: 是 | AE75: 确权资料+50-1000万财评统计表 | AF75: 否 | AG75: 无需写
A76: 540425201919024 | B76: 林芝市 | C76: 察隅县 | D76: 2019 | E76: 察隅县古拉乡特色经济林果种植建设项目 | F76: 察隅县林业和草原局 | G76: 古拉乡目本村 | H76: 人工种植突尼斯软粒石榴(含种苗购置及种植）45703株，成活养护960项，网围栏9587m，给水工程1项：灌溉水管共10819m、蓄水池4个共180m³、取水器260套、控制阀28个 | I76: =J76+K76 -> 943.67 | J76: 943.67 | K76: 0 | L76: =M76+N76 -> 881.45262 | M76: 881.45262 | N76: 0 | O76: 经营类 | P76: 石榴 | Q76: 盘活 | R76: 调整 | S76: 否 | AC76: 察空村已整体搬迁 | AD76: 是 | AE76: 确权资料 | AF76: 否 | AG76: 无需写 | AH76: 是
A77: 540425201912012 | B77: 林芝市 | C77: 察隅县 | D77: 2019 | E77: 察隅县上察隅镇本堆村茶叶种植项目 | F77: 察隅县产业发展工作领导小组办公室 | G77: 上察隅镇本堆村 | H77: 土地平整133亩，新建蓄水池，购买茶苗，安装网围栏等附属设施 | I77: =J77+K77 -> 265.93 | J77: 265.93 | K77: 0 | L77: =M77+N77 -> 251.86363 | M77: 251.86363 | N77: 0 | O77: 经营类 | P77: 茶 | Q77: 升级 | R77: 升级 | S77: 是 | T77: 委托运营 | U77: 私企 | V77: 察隅伟诚茶业有限责任公司 | W77: 否 | AD77: 是 | AE77: 确权资料+50-1000万财评统计表 | AF77: 否 | AG77: 无需写
A78: 540425201903001 | B78: 林芝市 | C78: 察隅县 | D78: 2019 | E78: 察隅县下察隅镇拉丁村生物有机肥厂建设项目 | F78: 下察隅镇人民政府 | G78: 下察隅拉丁村 | H78: 生化有机肥厂：建筑装饰工程1206.96平方米，安装工程1206.96平方米；门卫宿舍楼：建筑工程45.1平方米，安装工程45.1平方米；附属工程：通透式围墙316米，新建大门1座，室外电气工程1项，室外给排水工程1项，设备购置等 | I78: =J78+K78 -> 306 | J78: 306 | K78: 0 | L78: =M78+N78 -> 295.33395 | M78: 295.33395 | N78: 0 | O78: 经营类 | P78: 饲料 | Q78: 升级 | R78: 升级 | S78: 否 | AD78: 是 | AE78: 确权资料 | AF78: 否 | AG78: 无需写
A79: 540425201912013 | B79: 林芝市 | C79: 察隅县 | D79: 2019 | E79: 察隅县上察隅镇本堆村函部茶叶种植项目 | F79: 察隅县扶贫开发办公室 | G79: 上察隅镇本堆村 | H79: 土地平整103目，新建蓄水池，购买茶苗，安装网围栏等附属设施 | I79: =J79+K79 -> 205.93 | J79: 205.93 | K79: 0 | L79: =M79+N79 -> 185.69422 | M79: 185.69422 | N79: 0 | O79: 经营类 | P79: 茶 | Q79: 升级 | R79: 升级 | S79: 否 | AD79: 是 | AE79: 确权资料+50-1000万财评统计表 | AF79: 否 | AG79: 无需写
A80: 540425201919025 | B80: 林芝市 | C80: 察隅县 | D80: 2019 | E80: 察隅县就业创业孵化基地维修改造工程 | F80: 县人力资源和社会保障局 | G80: 察隅县 | H80: 新建轻质隔墙141.4㎡，乳胶漆内墙853.8㎡，乳胶漆顶棚407.3㎡，瓷砖内墙5.4㎡，新建台阶12.16㎡，安装工程454.5㎡，展览架5架，脚手架1项,拆除工程1项，门窗工程1项 | I80: =J80+K80 -> 50 | J80: 50 | K80: 0 | L80: =M80+N80 -> 45.3 | M80: 45.3 | N80: 0 | O80: 公益类 | P80: 其他 | Q80: 调整 | AD80: 是 | AE80: 确权资料+立项批复 | AF80: 否 | AG80: 无需写
A81: 540425201916009 | B81: 林芝市 | C81: 察隅县 | D81: 2019 | E81: 察隅县易地扶贫集中安置点温室配套建设项目 | F81: 县脱贫攻坚指挥部产业组 | G81: 下察隅镇格巴村、卡地村等村 | H81: 240平米温室大棚工程（共15栋），216平米温室大棚工程（共3栋），土石方工程、总平给排水工程 | I81: =J81+K81 -> 143.46 | J81: 143.46 | K81: 0 | L81: =M81+N81 -> 121.21263 | M81: 121.21263 | N81: 0 | O81: 公益类 | P81: 设施农业 | Q81: 升级 | S81: 是 | T81: 委托运营 | U81: 私企 | V81: 西藏利隆农业有限公司 | W81: 否 | AC81: 目本村由西藏利隆农业有限公司运营、 | AD81: 是 | AE81: 确权资料 | AF81: 否 | AG81: 无需写
A82: 540425201916010 | B82: 林芝市 | C82: 察隅县 | D82: 2019 | E82: 察隅县上察隅镇竹巴村温室大棚建设项目 | F82: 上察隅镇人民政府 | G82: 上察隅镇竹巴村 | H82: 新建蔬菜温室大棚6栋，每栋240㎡ | I82: =J82+K82 -> 35.2 | J82: 35.2 | K82: 0 | L82: =M82+N82 -> 35.2 | M82: 35.2 | N82: 0 | O82: 经营类 | P82: 设施农业 | Q82: 升级 | R82: 升级 | S82: 是 | T82: 委托运营 | U82: 农户 | V82: 吴芝云 | W82: 否 | AD82: 是 | AE82: 确权资料 | AF82: 否 | AG82: 无需写
A83: 540425201916011 | B83: 林芝市 | C83: 察隅县 | D83: 2019 | E83: 察隅县竹瓦根镇知美村、曲瓦村新建温室大棚项目 | F83: 竹瓦根镇人民政府 | G83: 竹瓦根镇知美村、曲瓦村 | H83: 在知美村新建10座100平方米的钢架双膜结构温室大棚，在曲瓦村新建6座99平方米的钢架双膜结构温室大棚 | I83: =J83+K83 -> 58.4 | J83: 58.4 | K83: 0 | L83: =M83+N83 -> 58.4 | M83: 58.4 | N83: 0 | O83: 到户类 | P83: 设施农业 | Q83: 升级 | S83: 是 | AD83: 是 | AE83: 确权资料+项目资料 | AF83: 否 | AG83: 无需写
A84: 540425201916012 | B84: 林芝市 | C84: 察隅县 | D84: 2019 | E84: 察隅县竹瓦根镇学尼村现代设施农业建设项目 | F84: 察隅县农牧局 | G84: 竹瓦根镇学尼村 | H84: 联栋温室大棚：建筑装饰工程3499.32㎡，安装工程3499.32㎡，附属工程：通透式围墙455m，新建大门1座，新建硬化247.73㎡，种植土1项 | I84: =J84+K84 -> 750 | J84: 750 | K84: 0 | L84: =M84+N84 -> 742.0825 | M84: 742.0825 | N84: 0 | O84: 经营类 | P84: 设施农业 | Q84: 升级 | R84: 巩固 | S84: 是 | T84: 委托运营 | U84: 私企 | V84: 察隅县牧丰绿色农业有限公司 | W84: 否 | Z84: 23898.29 | AA84: 14 | AB84: 察隅县农业农村局​ | AD84: 是 | AE84: 概批+50-1000万财评台账 | AF84: 否 | AG84: 无需写
A85: 540425201917009 | B85: 林芝市 | C85: 察隅县 | D85: 2019 | E85: 察瓦龙乡扎恩村旅游民宿客栈建设项目 | F85: 察瓦龙乡人民政府 | G85: 察瓦龙乡扎恩村 | H85: 客栈：建筑装饰工程196.71㎡，安装工程196.71㎡；附属工程：总平电气1项，总平给排水1项，大门工程1项，透视围墙1项及设备购置。 | I85: =J85+K85 -> 85 | J85: 85 | K85: 0 | L85: =M85+N85 -> 80.818207 | M85: 80.818207 | N85: 0 | O85: 经营类 | P85: 乡村旅游 | Q85: 升级 | R85: 盘活 | S85: 是 | T85: 委托运营 | U85: 个体工商户 | V85: 孙玉聪 | W85: 否 | AB85: 察隅县农业农村局 | AD85: 否 | AE85: 立项+50-1000万台账 | AF85: 否 | AG85: 是 | AH85: 是
A86: 540425201917010 | B86: 林芝市 | C86: 察隅县 | D86: 2019 | E86: 察隅县察瓦龙乡梦扎村客栈建设项目 | F86: 察瓦龙乡人民政府 | G86: 察瓦龙乡梦扎村 | H86: 建筑装饰工程686.76㎡，安装工程686.76㎡；附属工程：总体给排水工程1项，总体电器工程1项等内容 | I86: =J86+K86 -> 253.08 | J86: 10 | K86: 243.08 | L86: =M86+N86 -> 253.08 | M86: 10 | N86: 243.08 | O86: 经营类 | P86: 乡村旅游 | Q86: 升级 | R86: 巩固 | S86: 否 | AC86: 已搬迁 | AD86: 否 | AE86: 立项批复，审定金额无，以批复金额确权 | AF86: 否 | AG86: 是
A87: 540425201920020 | B87: 林芝市 | C87: 察隅县 | D87: 2019 | E87: 察隅县察瓦龙乡洪东村石榴种植项目 | F87: 察瓦龙乡人民政府 | G87: 察瓦龙乡洪东村 | H87: 挖种植穴2750株，购买种苗2750株，基肥7吨，病虫害防治50亩，围栏、大门等3000米，保湿地膜2750米，蓄水池50立方米，取水口2立方米，PE75引水管2500米，PE50支管300米，32塑料软管900米。 | I87: =J87+K87 -> 60 | J87: 60 | K87: 0 | L87: =M87+N87 -> 55.241853 | M87: 55.241853 | N87: 0 | O87: 经营类 | P87: 石榴 | Q87: 调整 | R87: 盘活 | S87: 是 | T87: 委托运营 | U87: 个体工商户 | V87: 江村 | W87: 否 | AB87: ​察隅县农业农村局 | AD87: 否 | AE87: 立项+50-1000万台账 | AF87: 是 | AG87: 是 | AH87: 是
A88: 540425201917011 | B88: 林芝市 | C88: 察隅县 | D88: 2019 | E88: 察隅县目若村农家旅游驿站建设项目 | F88: 竹瓦根镇人民政府 | G88: 竹瓦根镇目若村 | H88: 车行道工程3133.8㎡，入户道路工程909㎡，路基土方工程1项，排水沟工程550m，垃圾收集池工程1座，路缘石工程1102m，排污工程1项，照明工程1项，给水工程1项 | I88: =J88+K88 -> 864.36 | J88: 864.36 | K88: 0 | L88: =M88+N88 -> 805.88 | M88: 805.88 | N88: 0 | O88: 公益类 | P88: 乡村旅游 | Q88: 升级 | S88: 否 | AD88: 否 | AE88: 立项+50-1000万台账+财评 | AF88: 否 | AG88: 是
A89: 540425201912014 | B89: 林芝市 | C89: 察隅县 | D89: 2019 | E89: 察隅县产业扶贫竹巴村茶叶种植项目 | F89: 察隅县扶贫开发投资有限公司 | G89: 上察隅竹巴村 | H89: 土地平整：土石方工程1项；灌溉工程：管道工程1项，取水口1座，100m3蓄水池1座；茶叶种植：第一次树苗种植424950株，第二次补苗70825株；附属工程：铁丝网围栏2834.83m，大门3座，道路破除及恢复8㎡，设备购置：购买及运输除草机2部，购买安装防虫灯12个，购买安装标识牌2个 | I89: =J89+K89 -> 360 | J89: 240 | K89: 120 | L89: =M89+N89 -> 360 | M89: 240 | N89: 120 | O89: 经营类 | P89: 茶 | Q89: 升级 | R89: 盘活 | S89: 是 | T89: 委托运营 | U89: 私企 | V89: 察隅伟诚茶业有限责任公司 | W89: 否 | AD89: 是 | AE89: 确权资料+50-1000万财评统计表 | AF89: 否 | AG89: 无需写
A90: 540425201919026 | B90: 林芝市 | C90: 察隅县 | D90: 2019 | E90: 察隅县上察隅镇荣玉村花椒种植项目 | F90: 上察隅镇人民政府 | G90: 上察隅镇荣玉村 | H90: 土地平整；灌溉工程：管道工程1项，取水口1座，10m3蓄水池1座；花椒种植：花椒种植6066株，购买、施有机肥18.2t；附属工程：铁丝网围栏786m，大门1座 | I90: =J90+K90 -> 70 | J90: 59 | K90: 11 | L90: =M90+N90 -> 70 | M90: 59 | N90: 11 | O90: 经营类 | P90: 其他 | Q90: 调整 | R90: 调整 | S90: 是 | T90: 委托运营 | U90: 农户 | V90: 江安扎西 | AC90: 项目以由花椒改种果园、产值、产量以及收益不详，无法开展评估 | AD90: 否 | AE90: 立项批复+50-1000万台账（未注明审定金额） | AF90: 否 | AG90: 是 | AH90: 是
A91: 540425202019027 | B91: 林芝市 | C91: 察隅县 | D91: 2020 | E91: 察隅县育肥饲料（青贮玉米）加工厂项目 | F91: 察隅县农业农村局 | G91: 下察隅镇巴安通村 | H91: 饲料加工厂，建筑装饰工程725.24平方米，安装工程725.4平方米，附属工程及设备购置 | I91: =J91+K91 -> 150 | J91: 150 | K91: 0 | L91: =M91+N91 -> 141.61059 | M91: 141.61059 | N91: 0 | O91: 经营类 | P91: 饲料 | Q91: 升级 | R91: 升级 | S91: 是 | AD91: 是 | AE91: 确权资料+50-1000万财评统计表 | AF91: 否 | AG91: 无需写
A92: 540425202012015 | B92: 林芝市 | C92: 察隅县 | D92: 2020 | E92: 察隅县上察隅镇荣玉村第二期茶叶种植项目 | F92: 察隅县农业农村局 | G92: 上察隅镇荣玉村 | H92: 土地平整：土方清理150076.39m³，石方清理13985m³，场地平整699023.24m2，灌溉工程，管道工程1项，沉砂池1座，取水口1座，100m3蓄水池1座；茶叶种植：第一次茶苗种植2432636株，第二次茶苗补植419420株，防草布547154.36m2，反光膜151987.32m2，有机肥524.28t；附属设施：铁丝网围栏7684.07m，大门2座，标识牌1个 | I92: =J92+K92 -> 2403.91 | J92: 2403.91 | K92: 0 | L92: =M92+N92 -> 2286.39 | M92: 2286.39 | N92: 0 | O92: 经营类 | P92: 茶 | Q92: 升级 | R92: 升级 | S92: 是 | T92: 委托运营 | U92: 私企 | V92: 西藏宏峰建筑工程有限公司 | W92: 否 | AD92: 是 | AE92: 确权资料+超过1千万的财评台账（23年） | AF92: 否 | AG92: 无需写
A93: 540425202019028 | B93: 林芝市 | C93: 察隅县 | D93: 2020 | E93: 察隅县雪颠57啤酒厂改扩建项目 | F93: 西藏自治区察隅县国有资产经营有限公司 | G93: 竹瓦根镇嘎巴村 | H93: 采购水处理系统一套、粉碎系统一套、啤酒糖化设备生产线一套、发酵系统一套等 | I93: =J93+K93 -> 380 | J93: 380 | K93: 0 | L93: =M93+N93 -> 379 | M93: 379 | N93: 0 | O93: 经营类 | P93: 商贸流通 | Q93: 巩固 | R93: 升级 | S93: 是 | T93: 自主运营 | U93: 国企 | V93: 察隅县雪巅啤酒有限公司 | W93: 否 | Z93: 0 | AA93: 11 | AB93: 察隅县国资委 | AD93: 是 | AE93: 确权资料+50-1000万财评统计表 | AF93: 否 | AG93: 无需写
A94: 540425202020021 | B94: 林芝市 | C94: 察隅县 | D94: 2020 | E94: 察隅县察瓦龙乡珠拉村石榴种植项目 | F94: 察隅县农业农村局 | G94: 察瓦龙乡珠拉村 | H94: 种植工程，石榴种苗1454株，种植费32.3亩，有机肥1454株，病虫害防治32.3亩，人工修枝及管护32.3亩，保水剂32.3亩，蓄水池工程2座，灌溉支水管588.7m（PE,DN60），灌溉毛管541.13m（PE,DN13），控制阀门16个，网围栏906.21m。 | I94: =J94+K94 -> 43 | J94: 43 | K94: 0 | L94: =M94+N94 -> 43 | M94: 43 | N94: 0 | O94: 经营类 | P94: 石榴 | Q94: 调整 | R94: 盘活 | S94: 是 | AD94: 是 | AE94: 确权资料 | AF94: 是 | AG94: 无需写 | AH94: 是
A95: 540425202020022 | B95: 林芝市 | C95: 察隅县 | D95: 2020 | E95: 察隅县察瓦龙乡阿丙村石榴种植项目 | F95: 察隅县农业农村局 | G95: 察瓦龙乡阿丙村 | H95: 种植工程，石榴种苗6469株，种植费125亩，有机肥5625株，病虫害防治125亩，人工修枝及管护125亩，保水剂125亩，主水管299.18m（PE-DN110），灌溉支水管815.04m（PE-DN60），灌溉毛管16320.17m（PE-DN13），滴头5625个，控制阀门4个，网围栏1122.13m | I95: =J95+K95 -> 163 | J95: 163 | K95: 0 | L95: =M95+N95 -> 163 | M95: 163 | N95: 0 | O95: 经营类 | P95: 石榴 | Q95: 调整 | R95: 盘活 | S95: 否 | W95: 否 | AB95: 察隅县农业农村局 | AC95: 确权表主体是察瓦龙乡人民政府 | AD95: 是 | AE95: 确权资料+50-1000万财评统计表 | AF95: 否 | AG95: 无需写 | AH95: 是
A96: 540425202020023 | B96: 林芝市 | C96: 察隅县 | D96: 2020 | E96: 察隅县察瓦龙乡龙布村石榴种植项目 | F96: 察隅县农业农村局 | G96: 察瓦龙乡龙布村 | H96: 种植工程，石榴种苗12420株，种植费240亩，有机肥10800株，病虫害防治240亩，人工修枝及管护240亩，保水剂240亩，蓄水池工程2座，主水管1957.75m（PE,DN110），灌溉支水管1719.76m（PE,DN60），灌溉毛管4300.07m（PE,DN13），控制阀门60个，网围栏4271.4m。 | I96: =J96+K96 -> 312 | J96: 312 | K96: 0 | L96: =M96+N96 -> 312 | M96: 312 | N96: 0 | O96: 经营类 | P96: 石榴 | Q96: 调整 | R96: 盘活 | S96: 否 | W96: 否 | AB96: 察隅县农业农村局 | AC96: 确权表主体是察瓦龙乡人民政府 | AD96: 是 | AE96: 审定金额来源于确权资料和统计表 | AF96: 是 | AG96: 无需写 | AH96: 是
A97: 540425202020024 | B97: 林芝市 | C97: 察隅县 | D97: 2020 | E97: 古拉乡安巴村石榴种植项目 | F97: 古拉乡人民政府 | G97: 古拉乡安巴村 | H97: 种植工程：管道工程1项，闸阀井5套，蓄水池3座，网围栏1998m，石榴种植1项；临时工程：临时工程1项。 | I97: =J97+K97 -> 137 | J97: 137 | K97: 0 | L97: =M97+N97 -> 133.6574 | M97: 133.6574 | N97: 0 | O97: 经营类 | P97: 石榴 | Q97: 调整 | R97: 调整 | S97: 否 | AD97: 是 | AE97: 确权资料 | AF97: 是 | AG97: 无需写 | AH97: 是
A98: 540425202012016 | B98: 林芝市 | C98: 察隅县 | D98: 2020 | E98: 察隅县下察隅镇松古村茶叶种植项目 | F98: 县农业农村局 | G98: 下察隅镇松古村 | H98: 土地平整：土方清理13844.69m³，石方清理11610m³，场地平整357492.358m2，灌溉工程，管道工程1项，沉砂池3座，取水口3座，50m3蓄水池1座，25m3蓄水池2座；茶叶种植：第一次茶苗种植1833264株，第二次茶苗补植316080株，防草布412342.25m2，反光膜90833.48m2，有机肥395.11t；附属设施：铁丝网围栏8517.58m，大门3座，标识牌3个 | I98: =J98+K98 -> 1431 | J98: 1431 | K98: 0 | L98: =M98+N98 -> 1431 | M98: 1431 | N98: 0 | O98: 经营类 | P98: 茶 | Q98: 升级 | R98: 升级 | S98: 是 | AD98: 是 | AE98: 确权资料 | AF98: 否 | AG98: 无需写
A99: 540425202021002 | B99: 林芝市 | C99: 察隅县 | D99: 2020 | E99: 察隅县察瓦龙乡龙布村羊肚菌种植项目 | F99: 察瓦龙乡人民政府 | G99: 察瓦龙乡龙布村 | H99: 种植羊肚菌40亩，并配套灌溉、围栏等附属设施 | I99: =J99+K99 -> 50 | J99: 50 | K99: 0 | L99: =M99+N99 -> 50 | M99: 50 | N99: 0 | O99: 经营类 | P99: 菌类 | Q99: 升级 | R99: 调整 | S99: 否 | AD99: 是 | AE99: 确权资料 | AF99: 否 | AG99: 无需写 | AH99: 是
A100: 540425202019029 | B100: 林芝市 | C100: 察隅县 | D100: 2020 | E100: 察隅县察瓦龙乡龙布村灵芝种植项目 | F100: 察瓦龙乡人民政府 | G100: 察瓦龙乡龙布村 | H100: 种植灵芝菌8亩，并配套灌溉、围栏等附属设施 | I100: =J100+K100 -> 50 | J100: 50 | K100: 0 | L100: =M100+N100 -> 50 | M100: 50 | N100: 0 | O100: 经营类 | P100: 菌类 | Q100: 升级 | R100: 调整 | S100: 否 | AD100: 是 | AE100: 确权资料 | AF100: 否 | AG100: 无需写 | AH100: 是
...

Sheet 附件5-1
A1: 西藏自治区察隅县帮扶产业项目资产总台账 （截至2026年6月20日数据）
A2: 项目 编号 | B2: 项目县区 | C2: 项目年度 | D2: 项目名称 | E2: 项目实际投入金额 （万元） | F2: 资产 个数 | G2: 资产原值总金额（万元） | H2: 资产净值总金额 （万元） | I2: 资产属性 | J2: 资产“五权”确权主体 | P2: 备注
J3: 所有权 | L3: 经营权主体名称 | M3: 收益权主体名称 | N3: 监督权主体名称 | O3: 处置权主体名称
J4: 主体类别 | K4: 名称
A5: 填表说明：与表3项目编号一致 | D5: 一个项目仅填写一行 | E5: 与表2项目实际投资金额合计数一致 | F5: 应为项目实际形成资产个数合计数 | G5: 应为项目实际形成资产总数 （保留小数点后面2位） | H5: 统计时间为截止2024年12月31日 | I5: 在“国有资产、集体资产、到户资产”中选择 | J5: 在“农村集体经济组织、农户、国企、乡（镇）人民政府”中选择
A6: 540425201916012 | B6: 察隅县 | C6: 2019 | D6: 察隅县竹瓦根镇学尼村现代设施农业建设项目 | E6: 742.0825 | F6: =SUMIF('附件5-2'!$A$4:$A$336,A6,'附件5-2'!$I$4:$I$336) -> 4 | G6: 742 | H6: 519.4 | I6: 集体资产 | J6: 农村集体经济组织 | K6: 林芝市察隅县竹瓦根镇学尼村股份经济合作社 | L6: 察隅县牧丰绿色农业有限公司 | M6: 林芝市察隅县竹瓦根镇学尼村股份经济合作社 | N6: 西藏自治区林芝市察隅县竹瓦根镇学尼村村民委员会 | O6: 林芝市察隅县竹瓦根镇学尼村股份经济合作社
A7: 540425202116013 | B7: 察隅县 | C7: 2021 | D7: 察隅县竹瓦根镇城郊蔬菜种植项目 | E7: 371.55905 | F7: =SUMIF('附件5-2'!$A$4:$A$336,A7,'附件5-2'!$I$4:$I$336) -> 3 | G7: 371.55905 | H7: 315.82519 | I7: 集体资产 | J7: 农村集体经济组织 | K7: 林芝市察隅县竹瓦根镇学尼村股份经济合作社 | L7: 察隅县牧丰绿色农业有限公司 | M7: 林芝市察隅县竹瓦根镇学尼村股份经济合作社 | N7: 西藏自治区林芝市察隅县竹瓦根镇学尼村村民委员会 | O7: 林芝市察隅县竹瓦根镇学尼村股份经济合作社
A8: 540425201908006 | B8: 察隅县 | C8: 2019 | D8: 竹瓦根镇空档村“4+1”藏鸡养殖项目 | E8: 60 | F8: =SUMIF('附件5-2'!$A$4:$A$336,A8,'附件5-2'!$I$4:$I$336) -> 3 | G8: 59.05 | H8: 42.811249 | I8: 集体资产 | J8: 农村集体经济组织 | K8: 林芝市察隅县竹瓦根镇空档村股份经济合作社 | L8: 布索朗 | M8: 林芝市察隅县竹瓦根镇空档村股份经济合作社 | N8: 西藏自治区林芝市察隅县竹瓦根镇空档村村民委员会 | O8: 林芝市察隅县竹瓦根镇空档村股份经济合作社
A9: 540425202019028 | B9: 察隅县 | C9: 2020 | D9: 察隅县雪颠57啤酒厂改扩建项目 | E9: 379 | F9: =SUMIF('附件5-2'!$A$4:$A$336,A9,'附件5-2'!$I$4:$I$336) -> 9 | G9: 379 | H9: 189.5 | I9: 国有资产 | J9: 国企 | K9: 察隅县雪巅啤酒有限公司 | L9: 察隅县雪巅啤酒有限公司 | M9: 察隅县雪巅啤酒有限公司 | N9: 西藏自治区察隅县国有资产经营有限公司 | O9: 察隅县雪巅啤酒有限公司
A10: 540425201807008 | B10: 察隅县 | C10: 2018 | D10: 察隅县竹瓦根镇扎拉村阿多专业养殖合作社项目 | E10: 50 | F10: =SUMIF('附件5-2'!$A$4:$A$336,A10,'附件5-2'!$I$4:$I$336) -> 1 | G10: 50 | H10: 38.333333 | I10: 集体资产 | J10: 农村集体经济组织 | K10: 林芝市察隅县竹瓦根镇扎拉村股份经济合作社 | L10: 刘勇 | M10: 林芝市察隅县竹瓦根镇扎拉村股份经济合作社 | N10: 西藏自治区林芝市察隅县竹瓦根镇扎拉村村民委员会 | O10: 林芝市察隅县竹瓦根镇扎拉村股份经济合作社
A11: 540425201807009 | B11: 察隅县 | C11: 2018 | D11: 察隅县竹瓦根镇桑久村藏香猪养殖项目 | E11: 50 | F11: =SUMIF('附件5-2'!$A$4:$A$336,A11,'附件5-2'!$I$4:$I$336) -> 3 | G11: 52.88 | H11: 31.976 | I11: 集体资产 | J11: 农村集体经济组织 | K11: 林芝市察隅县竹瓦根镇桑久村股份经济合作社 | L11: 扎西次仁 | M11: 林芝市察隅县竹瓦根镇桑久村股份经济合作社 | N11: 西藏自治区林芝市察隅县竹瓦根镇桑久村村民委员会 | O11: 林芝市察隅县竹瓦根镇桑久村股份经济合作社
A12: 540425201918003 | B12: 察隅县 | C12: 2019 | D12: 察隅县竹瓦根镇沙通坝建材市场建设项目 | E12: 2326.1826 | F12: =SUMIF('附件5-2'!$A$4:$A$336,A12,'附件5-2'!$I$4:$I$336) -> 7 | G12: 2326.1826 | H12: 1949.85 | I12: 国有资产 | J12: 国企 | K12: 察隅县扶贫开发投资有限公司 | L12: 察隅县扶贫开发投资有限公司 | M12: 察隅县扶贫开发投资有限公司 | N12: 察隅县国有资产监督管理委员会 | O12: 察隅县扶贫开发投资有限公司
A13: 540425201908007 | B13: 察隅县 | C13: 2019 | D13: 察隅县竹瓦根镇扎拉村“4+1”藏鸡养殖项目 | E13: 30 | F13: =SUMIF('附件5-2'!$A$4:$A$336,A13,'附件5-2'!$I$4:$I$336) -> 296 | G13: 30 | H13: 20.049333 | I13: 集体资产 | J13: 农村集体经济组织 | K13: 林芝市察隅县竹瓦根镇扎拉村股份经济合作社 | L13: 成晓 | M13: 林芝市察隅县竹瓦根镇扎拉村股份经济合作社 | N13: 西藏自治区林芝市察隅县竹瓦根镇扎拉村村民委员会 | O13: 林芝市察隅县竹瓦根镇扎拉村股份经济合作社
A14: 540425202117014 | B14: 察隅县 | C14: 2021 | D14: 察隅县竹瓦根镇学尼村旅游配套设施建设项目 | E14: 242.17359 | F14: =SUMIF('附件5-2'!$A$4:$A$336,A14,'附件5-2'!$I$4:$I$336) -> 1 | G14: 242.17359 | H14: 215.93812 | I14: 集体资产 | J14: 农村集体经济组织 | K14: 林芝市察隅县竹瓦根镇学尼村股份经济合作社 | L14: 彭琼玲 | M14: 林芝市察隅县竹瓦根镇学尼村股份经济合作社 | N14: 西藏自治区林芝市察隅县竹瓦根镇学尼村村民委员会 | O14: 林芝市察隅县竹瓦根镇学尼村股份经济合作社
A15: 540425202104006 | B15: 察隅县 | C15: 2021 | D15: 察隅县竹瓦根镇高寒牧区高产养殖项目二期 | E15: 383.32645 | F15: =SUMIF('附件5-2'!$A$4:$A$336,A15,'附件5-2'!$I$4:$I$336) -> 118 | G15: 383.32645 | H15: 218.15905 | I15: 集体资产 | J15: 农村集体经济组织 | K15: 林芝市察隅县竹瓦根镇嘎达村股份经济合作社 | L15: 西藏察鑫农业科技有限公司 | M15: 林芝市察隅县竹瓦根镇嘎达村股份经济合作社 | N15: 西藏自治区林芝市察隅县竹瓦根镇嘎达村村民委员会 | O15: 林芝市察隅县竹瓦根镇嘎达村股份经济合作社
A16: 540425202004005 | B16: 察隅县 | C16: 2020 | D16: 察隅县竹瓦根镇高寒牧区高产养殖项目 | E16: 247.92948 | F16: =SUMIF('附件5-2'!$A$4:$A$336,A16,'附件5-2'!$I$4:$I$336) -> 94 | G16: 247.92948 | H16: 110.00961 | I16: 集体资产 | J16: 农村集体经济组织 | K16: 察隅县竹瓦根镇日东片区农畜产品专业合作社 | L16: 西藏察鑫农业科技有限公司 | M16: 察隅县竹瓦根镇日东片区农畜产品专业合作社 | N16: 察隅县竹瓦根镇日东片区农畜产品专业合作社 | O16: 察隅县竹瓦根镇日东片区农畜产品专业合作社
A17: 540425201619038 | B17: 察隅县 | C17: 2016 | D17: 察隅县古玉乡然乌学村茶馆 | E17: 30 | F17: =SUMIF('附件5-2'!$A$4:$A$336,A17,'附件5-2'!$I$4:$I$336) -> 1 | G17: 30 | H17: 17.875 | I17: 集体资产 | J17: 农村集体经济组织 | K17: 林芝市察隅县古玉乡然乌学村股份经济合作社 | M17: 林芝市察隅县古玉乡然乌学村股份经济合作社 | N17: 西藏自治区林芝市察隅县古玉乡然乌学村村民委员会 | O17: 林芝市察隅县古玉乡然乌学村股份经济合作社
A18: 540425201719011 | B18: 察隅县 | C18: 2017 | D18: 察隅县古玉乡博学村传统工艺品加工坊项目 | E18: 36 | F18: =SUMIF('附件5-2'!$A$4:$A$336,A18,'附件5-2'!$I$4:$I$336) -> 2 | G18: 36 | H18: 21.958333 | I18: 集体资产 | J18: 农村集体经济组织 | K18: 林芝市察隅县古玉乡博学村股份经济合作社 | M18: 林芝市察隅县古玉乡博学村股份经济合作社 | N18: 西藏自治区林芝市察隅县古玉乡博学村村民委员会 | O18: 林芝市察隅县古玉乡博学村股份经济合作社
A19: 540425201805001 | B19: 察隅县 | C19: 2018 | D19: 察隅县古玉乡博学村犏奶牛养殖场扩建项目 | E19: 50 | F19: =SUMIF('附件5-2'!$A$4:$A$336,A19,'附件5-2'!$I$4:$I$336) -> 1 | G19: 50 | H19: 36.458333 | I19: 集体资产 | J19: 农村集体经济组织 | K19: 林芝市察隅县古玉乡博学村股份经济合作社 | L19: 察隅县古玉乡博学村杰荣养殖专业合作社 | M19: 林芝市察隅县古玉乡博学村股份经济合作社 | N19: 西藏自治区林芝市察隅县古玉乡博学村村民委员会 | O19: 林芝市察隅县古玉乡博学村股份经济合作社
A20: 540425201819018 | B20: 察隅县 | C20: 2018 | D20: 察隅县古玉乡然乌学村然乌学组松茸加工坊 | E20: 40 | F20: =SUMIF('附件5-2'!$A$4:$A$336,A20,'附件5-2'!$I$4:$I$336) -> 3 | G20: 40 | H20: 24.05 | I20: 集体资产 | J20: 农村集体经济组织 | K20: 林芝市察隅县古玉乡然乌学村股份经济合作社 | M20: 林芝市察隅县古玉乡然乌学村股份经济合作社 | N20: 西藏自治区林芝市察隅县古玉乡然乌学村村民委员会 | O20: 林芝市察隅县古玉乡然乌学村股份经济合作社
A21: 540425202204008 | B21: 察隅县 | C21: 2022 | D21: 察隅县古玉乡巴依、玉和村犏牛养殖项目 | E21: 945.20898 | F21: =SUMIF('附件5-2'!$A$4:$A$336,A21,'附件5-2'!$I$4:$I$336) -> 180 | G21: =E21 -> 945.20898 | H21: 801.96832 | I21: 集体资产 | J21: 农村集体经济组织 | K21: 林芝市察隅县古玉乡巴依村股份经济合作社、林芝市察隅县古玉乡玉和村股份经济合作社 | L21: 西藏察鑫农业科技有限公司 | M21: 林芝市察隅县古玉乡巴依村股份经济合作社、林芝市察隅县古玉乡玉和村股份经济合作社 | N21: 西藏自治区林芝市察隅县古玉乡巴依村村民委员会、西藏自治区林芝市察隅县古玉乡巴玉和村村民委员会 | O21: 林芝市察隅县古玉乡巴依村股份经济合作社、林芝市察隅县古玉乡玉和村股份经济合作社
A22: 540425201718002 | B22: 察隅县 | C22: 2017 | D22: 察隅县汽修市场建设项目 | E22: 1904.5077 | F22: =SUMIF('附件5-2'!$A$4:$A$336,A22,'附件5-2'!$I$4:$I$336) -> 3 | G22: 1904.5077 | H22: 1301.4136 | I22: 国有资产 | J22: 国企 | K22: 察隅县扶贫开发投资有限公司 | L22: 察隅县扶贫开发投资有限公司 | M22: 察隅县扶贫开发投资有限公司 | N22: 察隅县国有资产监督管理委员会 | O22: 察隅县扶贫开发投资有限公司
A23: 540425201807007 | B23: 察隅县 | C23: 2018 | D23: 察隅县古玉乡古井村藏香猪养殖项目 | E23: 76.36 | F23: =SUMIF('附件5-2'!$A$4:$A$336,A23,'附件5-2'!$I$4:$I$336) -> 232 | G23: 50 | H23: 19.519793 | I23: 集体资产 | J23: 农村集体经济组织 | K23: 林芝市察隅县古玉乡古井村股份经济合作社 | L23: 察隅县古玉乡古井村青冈林藏香猪养殖专业合作社 | M23: 林芝市察隅县古玉乡古井村股份经济合作社 | N23: 西藏自治区林芝市察隅县古玉乡古井村村民委员会 | O23: 林芝市察隅县古玉乡古井村股份经济合作社
A24: 540425201808005 | B24: 察隅县 | C24: 2018 | D24: 察隅县古玉乡古井村藏鸡养殖项目 | E24: 50 | F24: =SUMIF('附件5-2'!$A$4:$A$336,A24,'附件5-2'!$I$4:$I$336) -> 1137 | G24: 50 | H24: 21.583333 | I24: 集体资产 | J24: 农村集体经济组织 | K24: 林芝市察隅县古玉乡古井村股份经济合作社 | L24: 察隅县兄弟藏鸡养殖场 | M24: 林芝市察隅县古玉乡古井村股份经济合作社 | N24: 西藏自治区林芝市察隅县古玉乡古井村村民委员会 | O24: 林芝市察隅县古玉乡古井村股份经济合作社
A25: 540425201819017 | B25: 察隅县 | C25: 2018 | D25: 察隅县古玉乡古井村松茸加工房 | E25: 30 | F25: =SUMIF('附件5-2'!$A$4:$A$336,A25,'附件5-2'!$I$4:$I$336) -> 1 | G25: 30 | H25: 19.5 | I25: 集体资产 | J25: 农村集体经济组织 | K25: 林芝市察隅县古玉乡古井村股份经济合作社 | L25: 乔君伟 | M25: 林芝市察隅县古玉乡古井村股份经济合作社 | N25: 西藏自治区林芝市察隅县古玉乡古井村村民委员会 | O25: 林芝市察隅县古玉乡古井村股份经济合作社
A26: 540425201517003 | B26: 察隅县 | C26: 2015 | D26: 察隅县古玉乡罗马村农家乐 | E26: 200 | F26: =SUMIF('附件5-2'!$A$4:$A$336,A26,'附件5-2'!$I$4:$I$336) -> 1 | G26: 200 | H26: 109.16667 | I26: 集体资产 | J26: 农村集体经济组织 | K26: 林芝市察隅县古玉乡罗马村股份经济合作社 | L26: 张鹏 | M26: 林芝市察隅县古玉乡罗马村股份经济合作社 | N26: 西藏自治区林芝市察隅县古玉乡罗马村村民委员会 | O26: 林芝市察隅县古玉乡罗马村股份经济合作社
A27: 540425202117015 | B27: 察隅县 | C27: 2021 | D27: 察隅县古玉乡罗马村宾馆 | E27: 400 | F27: =SUMIF('附件5-2'!$A$4:$A$336,A27,'附件5-2'!$I$4:$I$336) -> 1 | G27: 400 | H27: 338.33333 | I27: 集体资产 | J27: 农村集体经济组织 | K27: 林芝市察隅县古玉乡罗马村股份经济合作社 | L27: 王新华 | M27: 林芝市察隅县古玉乡罗马村股份经济合作社 | N27: 西藏自治区林芝市察隅县古玉乡罗马村村民委员会 | O27: 林芝市察隅县古玉乡罗马村股份经济合作社
A28: 540425201304001 | B28: 察隅县 | C28: 2013 | D28: 察隅县古玉乡罗马村犏牛养殖场 | E28: 151 | F28: =SUMIF('附件5-2'!$A$4:$A$336,A28,'附件5-2'!$I$4:$I$336) -> 3 | G28: 151 | H28: 67.320833 | I28: 集体资产 | J28: 农村集体经济组织 | K28: 林芝市察隅县古玉乡罗马村股份经济合作社 | M28: 林芝市察隅县古玉乡罗马村股份经济合作社 | N28: 西藏自治区林芝市察隅县古玉乡罗马村村民委员会 | O28: 林芝市察隅县古玉乡罗马村股份经济合作社
A29: 540425201719012 | B29: 察隅县 | C29: 2017 | D29: 察隅县古玉乡罗马村松茸加工坊 | E29: 20 | F29: =SUMIF('附件5-2'!$A$4:$A$336,A29,'附件5-2'!$I$4:$I$336) -> 1 | G29: 20 | H29: 12.916667 | I29: 集体资产 | J29: 农村集体经济组织 | K29: 林芝市察隅县古玉乡罗马村股份经济合作社 | L29: 白玛曲培 | M29: 林芝市察隅县古玉乡罗马村股份经济合作社 | N29: 西藏自治区林芝市察隅县古玉乡罗马村村民委员会 | O29: 林芝市察隅县古玉乡罗马村股份经济合作社
A30: 540425201807010 | B30: 察隅县 | C30: 2018 | D30: 下察隅镇京都村藏香猪养殖项目 | E30: 50 | F30: =SUMIF('附件5-2'!$A$4:$A$336,A30,'附件5-2'!$I$4:$I$336) -> 67 | G30: 50 | H30: 20.182334 | I30: 集体资产 | J30: 农村集体经济组织 | K30: 林芝市察隅县下察隅镇京都村股份经济合作社 | L30: 下察隅镇京都村阿胖养殖专业合作社 | M30: 林芝市察隅县下察隅镇京都村股份经济合作社 | N30: 西藏自治区林芝市察隅县下察隅镇京都村村民委员会 | O30: 林芝市察隅县下察隅镇京都村股份经济合作社
A31: 540425202019030 | B31: 察隅县 | C31: 2020 | D31: 察隅县下察隅镇京都村柑橘项目 | E31: 59.36 | F31: =SUMIF('附件5-2'!$A$4:$A$336,A31,'附件5-2'!$I$4:$I$336) -> 2 | G31: 60 | H31: 30 | I31: 集体资产 | J31: 农村集体经济组织 | K31: 林芝市察隅县下察隅镇京都村股份经济合作社 | L31: 察隅县兴农猕猴桃有限公司 | M31: 林芝市察隅县下察隅镇京都村股份经济合作社 | N31: 西藏自治区林芝市察隅县下察隅镇京都村村民委员会 | O31: 林芝市察隅县下察隅镇京都村股份经济合作社
A32: 540425201907012 | B32: 察隅县 | C32: 2019 | D32: 下察隅镇沙琼村藏香猪养殖项目 | E32: 50 | F32: =SUMIF('附件5-2'!$A$4:$A$336,A32,'附件5-2'!$I$4:$I$336) -> 69 | G32: 50 | H32: 18.342334 | I32: 集体资产 | J32: 农村集体经济组织 | K32: 林芝市察隅县下察隅镇沙琼村股份经济合作社 | L32: 察隅县下察隅镇沙琼村小次仁农民专业合作社 | M32: 林芝市察隅县下察隅镇沙琼村股份经济合作社 | N32: 西藏自治区林芝市察隅县下察隅镇沙琼村村民委员会 | O32: 林芝市察隅县下察隅镇沙琼村股份经济合作社
A33: 540425202315008 | B33: 察隅县 | C33: 2023 | D33: 察隅县下察隅镇沙琼村、洞冲村入股猕猴桃基地项目 | E33: 140 | F33: =SUMIF('附件5-2'!$A$4:$A$336,A33,'附件5-2'!$I$4:$I$336) -> 1 | G33: 140 | H33: 0 | I33: 集体资产 | J33: 农村集体经济组织 | K33: 林芝市察隅县下察隅镇沙琼村股份经济合作社、林芝市察隅县下察隅镇洞冲村股份经济合作社 | L33: 林芝华源佳隅农业科技开发有限公司 | M33: 林芝市察隅县下察隅镇沙琼村股份经济合作社、林芝市察隅县下察隅镇洞冲村股份经济合作社 | N33: 西藏自治区林芝市察隅县下察隅镇沙琼村村民委员会、西藏自治区林芝市察隅县下察隅镇洞冲村村民委员会 | O33: 林芝市察隅县下察隅镇沙琼村股份经济合作社、林芝市察隅县下察隅镇洞冲村股份经济合作社
A34: 540425202204009 | B34: 察隅县 | C34: 2022 | D34: 察隅县古玉乡犏牛养殖场配套设施项目 | E34: 94.24684 | F34: =SUMIF('附件5-2'!$A$4:$A$336,A34,'附件5-2'!$I$4:$I$336) -> 1 | G34: 94.24684 | H34: 86.785632 | I34: 集体资产 | J34: 农村集体经济组织 | K34: 林芝市察隅县古玉乡罗马村股份经济合作社 | M34: 林芝市察隅县古玉乡罗马村股份经济合作社 | N34: 西藏自治区林芝市察隅县古玉乡罗马村村民委员会 | O34: 林芝市察隅县古玉乡罗马村股份经济合作社
A35: 540425201715001 | B35: 察隅县 | C35: 2017 | D35: 察隅县下察隅镇夏尼村猕猴桃产业园区建设项目 | E35: 132.706 | F35: =SUMIF('附件5-2'!$A$4:$A$336,A35,'附件5-2'!$I$4:$I$336) -> 6003 | G35: 126.006 | H35: 71.056233 | I35: 集体资产 | J35: 农村集体经济组织 | K35: 林芝市察隅县下察隅镇夏尼村股份经济合作社 | L35: 察隅县兴农猕猴桃有限公司 | M35: 林芝市察隅县下察隅镇夏尼村股份经济合作社 | N35: 西藏自治区林芝市察隅县下察隅镇夏尼村村民委员会 | O35: 林芝市察隅县下察隅镇夏尼村股份经济合作社
A36: 540425202115006 | B36: 察隅县 | C36: 2021 | D36: 察隅县下察隅镇夏尼村猕猴桃种植项目 | E36: 229.48 | F36: =SUMIF('附件5-2'!$A$4:$A$336,A36,'附件5-2'!$I$4:$I$336) -> 100 | G36: 229.48 | H36: 160.636 | I36: 集体资产 | J36: 农村集体经济组织 | K36: 林芝市察隅县下察隅镇夏尼村股份经济合作社 | L36: 察隅县兴农猕猴桃有限公司 | M36: 林芝市察隅县下察隅镇夏尼村股份经济合作社 | N36: 西藏自治区林芝市察隅县下察隅镇夏尼村村民委员会 | O36: 林芝市察隅县下察隅镇夏尼村股份经济合作社
A37: 540425202115004 | B37: 察隅县 | C37: 2021 | D37: 察隅县下察隅镇夏尼村猕猴桃园提升项目 | E37: 65.475 | F37: =SUMIF('附件5-2'!$A$4:$A$336,A37,'附件5-2'!$I$4:$I$336) -> 1 | G37: 11.52 | H37: 7.872 | I37: 集体资产 | J37: 农村集体经济组织 | K37: 林芝市察隅县下察隅镇夏尼村股份经济合作社 | M37: 林芝市察隅县下察隅镇夏尼村股份经济合作社 | N37: 西藏自治区林芝市察隅县下察隅镇夏尼村村民委员会 | O37: 林芝市察隅县下察隅镇夏尼村股份经济合作社
A38: 540425202117013 | B38: 察隅县 | C38: 2021 | D38: 察隅县下察隅镇夏尼村旅游配套设施建设项目 | E38: 45 | F38: =SUMIF('附件5-2'!$A$4:$A$336,A38,'附件5-2'!$I$4:$I$336) -> 10 | G38: 45 | H38: 30.749999 | I38: 集体资产 | J38: 农村集体经济组织 | K38: 林芝市察隅县下察隅镇夏尼村股份经济合作社 | M38: 林芝市察隅县下察隅镇夏尼村股份经济合作社 | N38: 西藏自治区林芝市察隅县下察隅镇夏尼村村民委员会 | O38: 林芝市察隅县下察隅镇夏尼村股份经济合作社
A39: 540425202212029 | B39: 察隅县 | C39: 2022 | D39: 察隅县下察隅镇卡地村茶园提升改造建设项目 | E39: 402.64434 | F39: =SUMIF('附件5-2'!$A$4:$A$336,A39,'附件5-2'!$I$4:$I$336) -> 9 | G39: 201.25 | H39: 168.73937 | I39: 集体资产 | J39: 农村集体经济组织 | K39: 林芝市察隅县下察隅镇卡地村股份经济合作社 | M39: 林芝市察隅县下察隅镇卡地村股份经济合作社 | N39: 西藏自治区林芝市察隅县下察隅镇卡地村村民委员会 | O39: 林芝市察隅县下察隅镇卡地村股份经济合作社
A40: 540425202012020 | B40: 察隅县 | C40: 2020 | D40: 察隅县下察隅镇卡地村第二期茶叶种植项目 | E40: 176.3802 | F40: =SUMIF('附件5-2'!$A$4:$A$336,A40,'附件5-2'!$I$4:$I$336) -> 266.46 | G40: 40.59 | H40: 23.001 | I40: 集体资产 | J40: 农村集体经济组织 | K40: 林芝市察隅县下察隅镇卡地村股份经济合作社 | L40: 西藏自治区林芝市察隅县下察隅镇卡地村股份经济合作社 | M40: 林芝市察隅县下察隅镇卡地村股份经济合作社 | N40: 西藏自治区林芝市察隅县下察隅镇卡地村村民委员会 | O40: 林芝市察隅县下察隅镇卡地村股份经济合作社
A41: 540425201715002 | B41: 察隅县 | C41: 2017 | D41: 察隅县下察隅镇布巴村等三个行政村猕猴桃种植建设项目 | E41: 1484.39 | F41: =SUMIF('附件5-2'!$A$4:$A$336,A41,'附件5-2'!$I$4:$I$336) -> 966 | G41: 0 | H41: 0 | I41: 集体资产 | J41: 农村集体经济组织 | K41: 林芝市察隅县下察隅镇布巴村股份经济合作社、林芝市察隅县下察隅镇宗古村股份经济合作社、林芝市察隅县下察隅镇京都村股份经济合作社 | L41: 察隅县宗古农业发展有限责任公司、察隅县兴农猕猴桃有限公司、西藏林芝察隅巴布吉土地种植专业合作社 | M41: 林芝市察隅县下察隅镇布巴村股份经济合作社、林芝市察隅县下察隅镇宗古村股份经济合作社、林芝市察隅县下察隅镇京都村股份经济合作社 | N41: 西藏自治区林芝市察隅县下察隅镇布巴村村民委员会、西藏自治区林芝市察隅县下察隅镇京都村村民委员会、西藏自治区林芝市察隅县下察隅镇宗古村村民委员会 | O41: 林芝市察隅县下察隅镇布巴村股份经济合作社、林芝市察隅县下察隅镇宗古村股份经济合作社、林芝市察隅县下察隅镇京都村股份经济合作社
A42: 540425202321003 | B42: 察隅县 | C42: 2023 | D42: 察隅县下察隅镇卡地村林下菌类种植项目 | E42: 759.38473 | F42: =SUMIF('附件5-2'!$A$4:$A$336,A42,'附件5-2'!$I$4:$I$336) -> 2 | G42: 693.89661 | H42: 624.88305 | I42: 集体资产 | J42: 农村集体经济组织 | K42: 林芝市察隅县下察隅镇卡地村股份经济合作社 | L42: 西藏自治区林芝市察隅县下察隅镇卡地村股份经济合作社 | M42: 林芝市察隅县下察隅镇卡地村股份经济合作社 | N42: 西藏自治区林芝市察隅县下察隅镇卡地村村民委员会 | O42: 林芝市察隅县下察隅镇卡地村股份经济合作社
A43: 540425201907013 | B43: 察隅县 | C43: 2019 | D43: 下察隅镇自更村仁青罗布生态养殖专业合作社藏香猪养殖项目 | E43: 30 | F43: =SUMIF('附件5-2'!$A$4:$A$336,A43,'附件5-2'!$I$4:$I$336) -> 1 | G43: 30 | H43: 22.5 | I43: 集体资产 | J43: 农村集体经济组织 | K43: 林芝市察隅县下察隅镇自更村股份经济合作社 | L43: - | M43: 林芝市察隅县下察隅镇自更村股份经济合作社 | N43: 西藏自治区林芝市察隅县下察隅镇自更村村民委员会 | O43: 林芝市察隅县下察隅镇自更村股份经济合作社
A44: 540425202219035 | B44: 察隅县 | C44: 2022 | D44: 察隅县上、下察隅镇木耳种植项目 | E44: 178.85887 | F44: =SUMIF('附件5-2'!$A$4:$A$336,A44,'附件5-2'!$I$4:$I$336) -> 4 | G44: 111.44 | H44: 94.51 | I44: 集体资产 | J44: 农村集体经济组织 | K44: 林芝市察隅县下察隅镇共同村股份经济合作社 | L44: 淳安千岛湖正杰农业发展有限责任公司 | M44: 林芝市察隅县下察隅镇共同村股份经济合作社 | N44: 西藏自治区林芝市察隅县下察隅镇共同村村民委员会 | O44: 林芝市察隅县下察隅镇共同村股份经济合作社
A45: 540425201812006 | B45: 察隅县 | C45: 2018 | D45: 察隅县茶叶产业项目（第二批） | E45: 2000 | F45: =SUMIF('附件5-2'!$A$4:$A$336,A45,'附件5-2'!$I$4:$I$336) -> 0 | G45: 0 | H45: 0 | I45: 到户资产 | J45: - | K45: - | L45: - | M45: - | N45: - | O45: -
A46: 540425201907015 | B46: 察隅县 | C46: 2019 | D46: 下察隅镇塔玛村藏猪养殖项目 | E46: 20 | F46: =SUMIF('附件5-2'!$A$4:$A$336,A46,'附件5-2'!$I$4:$I$336) -> 1 | G46: 20 | H46: 14.916667 | I46: 集体资产 | J46: 农村集体经济组织 | K46: 林芝市察隅县下察隅镇塔玛村股份经济合作社 | L46: - | M46: 林芝市察隅县下察隅镇塔玛村股份经济合作社 | N46: 西藏自治区林芝市察隅县下察隅镇塔玛村村民委员会 | O46: 林芝市察隅县下察隅镇塔玛村股份经济合作社
A47: 540425202115005 | B47: 察隅县 | C47: 2021 | D47: 察隅县下察隅镇布巴村猕猴桃园提升项目 | E47: 71.78243 | F47: =SUMIF('附件5-2'!$A$4:$A$336,A47,'附件5-2'!$I$4:$I$336) -> 2 | G47: 71.81 | H47: 49.668584 | I47: 集体资产 | J47: 农村集体经济组织 | K47: 林芝市察隅县下察隅镇布巴村股份经济合作社 | L47: - | M47: 林芝市察隅县下察隅镇布巴村股份经济合作社 | N47: 西藏自治区林芝市察隅县下察隅镇布巴村村民委员会 | O47: 林芝市察隅县下察隅镇布巴村股份经济合作社
A48: 540425202215007 | B48: 察隅县 | C48: 2022 | D48: 察隅县2022年拉丁村搬迁配套猕猴桃种植项目 | E48: 454 | F48: =SUMIF('附件5-2'!$A$4:$A$336,A48,'附件5-2'!$I$4:$I$336) -> 803 | G48: 69.08 | H48: 55.839666 | I48: 集体资产 | J48: 农村集体经济组织 | K48: 林芝市察隅县下察隅镇拉丁村股份经济合作社 | L48: - | M48: 林芝市察隅县下察隅镇拉丁村股份经济合作社 | N48: 西藏自治区林芝市察隅县下察隅镇拉丁村村民委员会 | O48: 林芝市察隅县下察隅镇拉丁村股份经济合作社
A49: 540425202216017 | B49: 察隅县 | C49: 2022 | D49: 察隅县下察隅镇沙玛村枇杷种植水肥一体化项目 | E49: 214.34023 | F49: =SUMIF('附件5-2'!$A$4:$A$336,A49,'附件5-2'!$I$4:$I$336) -> 14 | G49: 118.18 | H49: 92.6005 | I49: 集体资产 | J49: 农村集体经济组织 | K49: 林芝市察隅县下察隅镇沙玛村股份经济合作社 | L49: - | M49: 林芝市察隅县下察隅镇沙玛村股份经济合作社 | N49: 西藏自治区林芝市察隅县下察隅镇沙玛村村民委员会 | O49: 林芝市察隅县下察隅镇沙玛村股份经济合作社
A50: 540425201907014 | B50: 察隅县 | C50: 2019 | D50: 下察隅镇拉丁村藏香猪养殖项目 | E50: 20 | F50: =SUMIF('附件5-2'!$A$4:$A$336,A50,'附件5-2'!$I$4:$I$336) -> 1 | G50: 20 | H50: 14.916667 | I50: 集体资产 | J50: 农村集体经济组织 | K50: 林芝市察隅县下察隅镇拉丁村股份经济合作社 | L50: - | M50: 林芝市察隅县下察隅镇拉丁村股份经济合作社 | N50: 西藏自治区林芝市察隅县下察隅镇拉丁村村民委员会 | O50: 林芝市察隅县下察隅镇拉丁村股份经济合作社
A51: 540425201903001 | B51: 察隅县 | C51: 2019 | D51: 察隅县下察隅镇拉丁村生物有机肥厂建设项目 | E51: 295.33395 | F51: =SUMIF('附件5-2'!$A$4:$A$336,A51,'附件5-2'!$I$4:$I$336) -> 1 | G51: 295.33395 | H51: 223.96158 | I51: 集体资产 | J51: 农村集体经济组织 | K51: 林芝市察隅县下察隅镇拉丁村股份经济合作社 | L51: - | M51: 林芝市察隅县下察隅镇拉丁村股份经济合作社 | N51: 西藏自治区林芝市察隅县下察隅镇拉丁村村民委员会 | O51: 林芝市察隅县下察隅镇拉丁村股份经济合作社
... A55: 540425201912012 | B55: 察隅县 | C55: 2019 | D55: 察隅县上察隅镇本堆村茶叶种植项目 | E55: 251.86363 | F55: =SUMIF('附件5-2'!$A$4:$A$336,A55,'附件5-2'!$I$4:$I$336) -> 141.73 | G55: 93.222 | H55: 47.38785 | I55: 集体资产 | J55: 农村集体经济组织 | K55: 林芝市察隅县上察隅镇本堆村股份经济合作社 | L55: - | M55: 林芝市察隅县上察隅镇本堆村股份经济合作社 | N55: 西藏自治区林芝市察隅县上察隅镇本堆村村民委员会 | O55: 林芝市察隅县上察隅镇本堆村股份经济合作社
A56: 540425201912013 | B56: 察隅县 | C56: 2019 | D56: 察隅县上察隅镇本堆村函部茶叶种植项目 | E56: 185.69422 | F56: =SUMIF('附件5-2'!$A$4:$A$336,A56,'附件5-2'!$I$4:$I$336) -> 110.85 | G56: 42.2055 | H56: 21.10275 | I56: 集体资产 | J56: 农村集体经济组织 | K56: 林芝市察隅县上察隅镇本堆村股份经济合作社 | L56: - | M56: 林芝市察隅县上察隅镇本堆村股份经济合作社 | N56: 西藏自治区林芝市察隅县上察隅镇本堆村村民委员会 | O56: 林芝市察隅县上察隅镇本堆村股份经济合作社 | P56: 项目验收未通过
A57: 540425201919023 | B57: 察隅县 | C57: 2019 | D57: 察隅县本土生态农产品加工项目 | E57: 239.92703 | F57: =SUMIF('附件5-2'!$A$4:$A$336,A57,'附件5-2'!$I$4:$I$336) -> 22 | G57: 237.7 | H57: 125.71958 | I57: 集体资产 | J57: 农村集体经济组织 | K57: - | L57: - | M57: - | N57: - | O57: - | P57: 产权未确定
A58: 540425201719010 | B58: 察隅县 | C58: 2017 | D58: 察隅县上察隅镇西巴村珞巴民族服饰加工项目 | E58: 24.62 | F58: =SUMIF('附件5-2'!$A$4:$A$336,A58,'附件5-2'!$I$4:$I$336) -> 1 | G58: 24.62 | H58: 0 | I58: 集体资产 | J58: 农村集体经济组织 | K58: 林芝市察隅县上察隅镇西巴村股份经济合作社 | L58: - | M58: 林芝市察隅县上察隅镇西巴村股份经济合作社 | N58: 西藏自治区林芝市察隅县上察隅镇西巴村村民委员会 | O58: 林芝市察隅县上察隅镇西巴村股份经济合作社
A59: 540425201819013 | B59: 察隅县 | C59: 2018 | D59: 察隅县上察隅镇西巴村铁皮石斛种植扩建项目 | E59: 500000 | F59: =SUMIF('附件5-2'!$A$4:$A$336,A59,'附件5-2'!$I$4:$I$336) -> 10 | G59: 45 | H59: 17.625 | I59: 集体资产 | J59: 农村集体经济组织 | K59: 林芝市察隅县上察隅镇西巴村股份经济合作社 | L59: - | M59: 林芝市察隅县上察隅镇西巴村股份经济合作社 | N59: 西藏自治区林芝市察隅县上察隅镇西巴村村民委员会 | O59: 林芝市察隅县上察隅镇西巴村股份经济合作社
A60: 540425202112021 | B60: 察隅县 | C60: 2021 | D60: 察隅县上察隅镇荣玉村茶叶粗加工坊建设项目 | E60: 263.24016 | F60: =SUMIF('附件5-2'!$A$4:$A$336,A60,'附件5-2'!$I$4:$I$336) -> 1 | G60: 261.75 | H60: 223.57812 | I60: 集体资产 | J60: 农村集体经济组织 | K60: 林芝市察隅县上察隅镇荣玉村股份经济合作社 | L60: - | M60: 林芝市察隅县上察隅镇荣玉村股份经济合作社 | N60: 西藏自治区林芝市察隅县上察隅镇荣玉村村民委员会 | O60: 林芝市察隅县上察隅镇荣玉村股份经济合作社
A61: 540425201919026 | B61: 察隅县 | C61: 2019 | D61: 察隅县上察隅镇荣玉村花椒种植项目 | E61: 59 | F61: =SUMIF('附件5-2'!$A$4:$A$336,A61,'附件5-2'!$I$4:$I$336) -> 6068 | G61: 40.45 | H61: 6.0375 | I61: 集体资产 | J61: 农村集体经济组织 | K61: 林芝市察隅县上察隅镇荣玉村股份经济合作社 | L61: - | M61: 林芝市察隅县上察隅镇荣玉村股份经济合作社 | N61: 西藏自治区林芝市察隅县上察隅镇荣玉村村民委员会 | O61: 林芝市察隅县上察隅镇荣玉村股份经济合作社
A62: 540425201812008 | B62: 察隅县 | C62: 2018 | D62: 察隅县荣玉村2018年有机茶叶种植项目 | E62: 435.6 | F62: =SUMIF('附件5-2'!$A$4:$A$336,A62,'附件5-2'!$I$4:$I$336) -> 332.94 | G62: 249.4524 | H62: 85.42272 | I62: 集体资产 | J62: 农村集体经济组织 | K62: 林芝市察隅县上察隅镇荣玉村股份经济合作社 | L62: - | M62: 林芝市察隅县上察隅镇荣玉村股份经济合作社 | N62: 西藏自治区林芝市察隅县上察隅镇荣玉村村民委员会 | O62: 林芝市察隅县上察隅镇荣玉村股份经济合作社 | P62: 原有1236527株，182亩，因退耕还林仅剩下约40亩
A63: 540425201812003 | B63: 察隅县 | C63: 2018 | D63: 察隅县产业扶贫毕达村茶叶种植项目 | E63: 283.06028 | F63: =SUMIF('附件5-2'!$A$4:$A$336,A63,'附件5-2'!$I$4:$I$336) -> 307.82 | G63: 449.28 | H63: 180.09133 | I63: 国有资产 | J63: 国企 | K63: 察隅县扶贫开发投资有限公司 | L63: - | M63: 察隅县扶贫开发投资有限公司 | N63: 察隅县扶贫开发投资有限公司 | O63: 察隅县扶贫开发投资有限公司
A64: 540425202212025 | B64: 察隅县 | C64: 2022 | D64: 察隅县2022年本堆村搬迁配套茶叶种植项目 | E64: 558.73 | F64: =SUMIF('附件5-2'!$A$4:$A$336,A64,'附件5-2'!$I$4:$I$336) -> 319 | G64: 118.335 | H64: 99.598626 | I64: 集体资产 | J64: 农村集体经济组织 | K64: 林芝市察隅县上察隅镇本堆村股份经济合作社 | L64: - | M64: 林芝市察隅县上察隅镇本堆村股份经济合作社 | N64: 西藏自治区林芝市察隅县上察隅镇本堆村村民委员会 | O64: 林芝市察隅县上察隅镇本堆村股份经济合作社 | P64: 项目于2025年完成财评，未开始采摘，经营权尚未确定。
A65: 540425202012015 | B65: 察隅县 | C65: 2020 | D65: 察隅县上察隅镇荣玉村第二期茶叶种植项目 | E65: 2403.91 | F65: =SUMIF('附件5-2'!$A$4:$A$336,A65,'附件5-2'!$I$4:$I$336) -> 940.78 | G65: 2403.91 | H65: 1682.74 | I65: 集体资产 | J65: 农村集体经济组织 | K65: 林芝市察隅县上察隅镇荣玉村股份经济合作社 | L65: - | M65: 林芝市察隅县上察隅镇荣玉村股份经济合作社 | N65: 西藏自治区林芝市察隅县上察隅镇荣玉村村民委员会 | O65: 林芝市察隅县上察隅镇荣玉村股份经济合作社 | P65: 项目未移交，计划移交给村集体
A66: 540425202012018 | B66: 察隅县 | C66: 2020 | D66: 察隅县上察隅镇格拥村茶叶种植项目 | E66: 295.12047 | F66: =SUMIF('附件5-2'!$A$4:$A$336,A66,'附件5-2'!$I$4:$I$336) -> 0 | G66: 0 | H66: 0 | I66: 到户资产 | J66: - | K66: - | L66: - | M66: - | N66: - | O66: -
A67: 540425201916010 | B67: 察隅县 | C67: 2019 | D67: 察隅县上察隅镇竹巴村温室大棚建设项目 | E67: 35.2 | F67: =SUMIF('附件5-2'!$A$4:$A$336,A67,'附件5-2'!$I$4:$I$336) -> 6 | G67: 34.68 | H67: 17.34 | I67: 集体资产 | J67: 农村集体经济组织 | K67: 林芝市察隅县上察隅镇竹巴村股份经济合作社 | L67: - | M67: 林芝市察隅县上察隅镇竹巴村股份经济合作社 | N67: 西藏自治区林芝市察隅县上察隅镇竹巴村村民委员会 | O67: 林芝市察隅县上察隅镇竹巴村股份经济合作社
A68: 540425201912011 | B68: 察隅县 | C68: 2019 | D68: 察隅县上察隅镇体育村通迪茶叶种植项目 | E68: 279.81427 | F68: =SUMIF('附件5-2'!$A$4:$A$336,A68,'附件5-2'!$I$4:$I$336) -> 3 | G68: 137.95 | H68: 71.274167 | I68: 集体资产 | J68: 农村集体经济组织 | K68: 林芝市察隅县上察隅镇体育村股份经济合作社 | L68: - | M68: 林芝市察隅县上察隅镇体育村股份经济合作社 | N68: 西藏自治区林芝市察隅县上察隅镇体育村村民委员会 | O68: 林芝市察隅县上察隅镇体育村股份经济合作社
A69: 540425201712009 | B69: 察隅县 | C69: 2018 | D69: 察隅县体育村2018年有机茶叶种植项目 | E69: 600.7 | F69: =SUMIF('附件5-2'!$A$4:$A$336,A69,'附件5-2'!$I$4:$I$336) -> 83 | G69: 600.7 | H69: 180.21 | I69: 集体资产 | J69: 农村集体经济组织 | K69: 林芝市察隅县上察隅镇体育村股份经济合作社 | L69: - | M69: 林芝市察隅县上察隅镇体育村股份经济合作社 | N69: 西藏自治区林芝市察隅县上察隅镇体育村村民委员会 | O69: 林芝市察隅县上察隅镇体育村股份经济合作社
A70: 540425201619009 | B70: 察隅县 | C70: 2016 | D70: 察隅县上察隅镇迟巴村产业扶贫 | E70: 160.38 | F70: =SUMIF('附件5-2'!$A$4:$A$336,A70,'附件5-2'!$I$4:$I$336) -> 0 | G70: 0 | H70: 0 | I70: 到户资产 | J70: - | K70: - | L70: - | M70: - | N70: - | O70: -
A71: 540425201912014 | B71: 察隅县 | C71: 2019 | D71: 察隅县产业扶贫竹巴村茶叶种植项目 | E71: 240 | F71: =SUMIF('附件5-2'!$A$4:$A$336,A71,'附件5-2'!$I$4:$I$336) -> 355.63 | G71: 181.89 | H71: 95.32125 | I71: 集体资产 | J71: 农村集体经济组织 | K71: 林芝市察隅县上察隅镇竹巴村股份经济合作社 | L71: - | M71: 林芝市察隅县上察隅镇竹巴村股份经济合作社 | N71: 西藏自治区林芝市察隅县上察隅镇竹巴村村民委员会 | O71: 林芝市察隅县上察隅镇竹巴村股份经济合作社
A72: 540425202321004 | B72: 察隅县 | C72: 2023 | D72: 察隅县上察隅镇布宗村林下菌类种植项目 | E72: 703.05588 | F72: =SUMIF('附件5-2'!$A$4:$A$336,A72,'附件5-2'!$I$4:$I$336) -> 387832 | G72: 411.51 | H72: 353.21275 | I72: 集体资产 | J72: 农村集体经济组织 | K72: 林芝市察隅县上察隅镇布宗村股份经济合作社 | L72: - | M72: 林芝市察隅县上察隅镇布宗村股份经济合作社 | N72: 西藏自治区林芝市察隅县上察隅镇布宗村村民委员会 | O72: 林芝市察隅县上察隅镇布宗村股份经济合作社 | P72: 消耗性生物资产
A73: 540425202212024 | B73: 察隅县 | C73: 2022 | D73: 察隅县巩固村搬迁配套茶叶种植项目 | E73: 892.97985 | F73: =SUMIF('附件5-2'!$A$4:$A$336,A73,'附件5-2'!$I$4:$I$336) -> 487 | G73: 845.20314 | H73: 760.68282 | I73: 集体资产 | J73: 农村集体经济组织 | K73: 林芝市察隅县上察隅镇桑典村股份经济合作社 | L73: - | M73: 林芝市察隅县上察隅镇桑典村股份经济合作社 | N73: 西藏自治区林芝市察隅县上察隅镇桑典村村民委员会 | O73: 林芝市察隅县上察隅镇桑典村股份经济合作社
A74: 540425202012029 | B74: 察隅县 | C74: 2020 | D74: 察隅县上察隅镇米古村第二期茶叶种植项目 | E74: 104.33007 | F74: =SUMIF('附件5-2'!$A$4:$A$336,A74,'附件5-2'!$I$4:$I$336) -> 0 | G74: 0 | H74: 0 | I74: 集体资产 | J74: 农村集体经济组织 | K74: 林芝市察隅县上察隅镇米古村股份经济合作社 | L74: - | M74: 林芝市察隅县上察隅镇米古村股份经济合作社 | N74: 西藏自治区林芝市察隅县上察隅镇米古村村民委员会 | O74: 林芝市察隅县上察隅镇米古村股份经济合作社
A75: 540425202119031 | B75: 察隅县 | C75: 2021 | D75: 察隅县下察隅镇布巴村、沙玛村产业提升项目 | E75: 157.4 | F75: =SUMIF('附件5-2'!$A$4:$A$336,A75,'附件5-2'!$I$4:$I$336) -> 0 | G75: 0 | H75: 0 | I75: 集体资产 | J75: 农村集体经济组织 | K75: 林芝市察隅县下察隅镇布巴村股份经济合作社、林芝市察隅县下察隅镇沙玛村股份经济合作社 | L75: - | M75: 林芝市察隅县下察隅镇布巴村股份经济合作社、林芝市察隅县下察隅镇沙玛村股份经济合作社 | N75: 西藏自治区林芝市察隅县下察隅镇布巴村村民委员会、西藏自治区林芝市察隅县下察隅镇沙玛村村民委员会 | O75: 林芝市察隅县下察隅镇布巴村股份经济合作社、林芝市察隅县下察隅镇沙玛村股份经济合作社
A76: 540425202012017 | B76: 察隅县 | C76: 2020 | D76: 察隅县上察隅镇松林村茶叶种植项目 | E76: 562.02147 | F76: =SUMIF('附件5-2'!$A$4:$A$336,A76,'附件5-2'!$I$4:$I$336) -> 358.04 | G76: 324.39 | H76: 229.2255 | I76: 集体资产 | J76: 农村集体经济组织 | K76: 林芝市察隅县上察隅镇松林村股份经济合作社 | L76: - | M76: 林芝市察隅县上察隅镇松林村股份经济合作社 | N76: 西藏自治区林芝市察隅县上察隅镇松林村村民委员会 | O76: 林芝市察隅县上察隅镇松林村股份经济合作社
A77: 540425201320001 | B77: 察隅县 | C77: 2013 | D77: 察瓦龙乡昌西村石榴品种改良项目 | E77: 24 | G77: 24 | H77: 0 | I77: 集体资产 | J77: 农村集体经济组织 | K77: 林芝市察隅县察瓦龙乡昌西村股份经济合作社 | L77: - | M77: 林芝市察隅县察瓦龙乡昌西村股份经济合作社 | N77: 西藏自治区林芝市察隅县察瓦龙乡昌西村村民委员会 | O77: 林芝市察隅县察瓦龙乡昌西村股份经济合作社
A78: 540425201517002 | B78: 察隅县 | C78: 2015 | D78: 罗马桃花村旅游资源升级改造项目 | E78: 500 | F78: =SUMIF('附件5-2'!$A$4:$A$336,A78,'附件5-2'!$I$4:$I$336) -> 0 | G78: 0 | H78: 0 | I78: 集体资产 | J78: 农村集体经济组织 | K78: 林芝市察隅县古玉乡罗马村股份经济合作社 | L78: - | M78: 林芝市察隅县古玉乡罗马村股份经济合作社 | N78: 西藏自治区林芝市察隅县古玉乡罗马村村民委员会 | O78: 林芝市察隅县古玉乡罗马村股份经济合作社
A79: 540425201619002 | B79: 察隅县 | C79: 2016 | D79: 古拉乡核桃粮油加工坊 | E79: 60 | F79: =SUMIF('附件5-2'!$A$4:$A$336,A79,'附件5-2'!$I$4:$I$336) -> 0 | G79: 0 | H79: 0 | I79: 集体资产 | J79: 农村集体经济组织 | K79: - | L79: - | M79: - | N79: - | O79: -
A80: 540425201607001 | B80: 察隅县 | C80: 2016 | D80: 察隅县养猪项目 | E80: 601 | F80: =SUMIF('附件5-2'!$A$4:$A$336,A80,'附件5-2'!$I$4:$I$336) -> 0 | G80: 0 | H80: 0 | I80: 到户资产 | J80: - | K80: - | L80: - | M80: - | N80: - | O80: -
A81: 540425201608001 | B81: 察隅县 | C81: 2016 | D81: 察隅县养鸡项目 | E81: 207 | F81: =SUMIF('附件5-2'!$A$4:$A$336,A81,'附件5-2'!$I$4:$I$336) -> 0 | G81: 0 | H81: 0 | I81: 集体资产 | J81: 农村集体经济组织 | K81: - | L81: - | M81: - | N81: - | O81: -
A82: 540425201616002 | B82: 察隅县 | C82: 2016 | D82: 察隅县温室建设项目 | E82: 470 | F82: =SUMIF('附件5-2'!$A$4:$A$336,A82,'附件5-2'!$I$4:$I$336) -> 0 | G82: 0 | H82: 0 | I82: 集体资产 | J82: 农村集体经济组织 | K82: - | L82: - | M82: - | N82: - | O82: -
A83: 540425201604002 | B83: 察隅县 | C83: 2016 | D83: 察隅县牦牛养殖项目 | E83: 577 | F83: =SUMIF('附件5-2'!$A$4:$A$336,A83,'附件5-2'!$I$4:$I$336) -> 0 | G83: 0 | H83: 0 | I83: 到户资产 | J83: - | K83: - | L83: - | M83: - | N83: - | O83: -
A84: 540425201606001 | B84: 察隅县 | C84: 2016 | D84: 察隅县养羊项目 | E84: 30 | F84: =SUMIF('附件5-2'!$A$4:$A$336,A84,'附件5-2'!$I$4:$I$336) -> 0 | G84: 0 | H84: 0 | I84: 到户资产 | J84: - | K84: - | L84: - | M84: - | N84: - | O84: -
A85: 540425201619003 | B85: 察隅县 | C85: 2016 | D85: 察隅县特色种植项目 | E85: 27 | F85: =SUMIF('附件5-2'!$A$4:$A$336,A85,'附件5-2'!$I$4:$I$336) -> 0 | G85: 0 | H85: 0 | I85: 到户资产 | J85: - | K85: - | L85: - | M85: - | N85: - | O85: -
A86: 540425201619004 | B86: 察隅县 | C86: 2016 | D86: 古拉乡则巴村养殖基地项目 | E86: 73.8 | F86: =SUMIF('附件5-2'!$A$4:$A$336,A86,'附件5-2'!$I$4:$I$336) -> 0 | G86: 0 | H86: 0 | I86: 集体资产 | J86: 农村集体经济组织 | K86: 林芝市察隅县古拉乡则巴村股份经济合作社 | L86: - | M86: 林芝市察隅县古拉乡则巴村股份经济合作社 | N86: 西藏自治区林芝市察隅县古拉乡则巴村村民委员会 | O86: 林芝市察隅县古拉乡则巴村股份经济合作社
A87: 540425201607002 | B87: 察隅县 | C87: 2016 | D87: 古拉乡安巴村养猪基地项目 | E87: 10 | F87: =SUMIF('附件5-2'!$A$4:$A$336,A87,'附件5-2'!$I$4:$I$336) -> 0 | G87: 0 | H87: 0 | I87: 集体资产 | J87: 农村集体经济组织 | K87: 林芝市察隅县古拉乡安巴村股份经济合作社 | L87: - | M87: 林芝市察隅县古拉乡安巴村股份经济合作社 | N87: 西藏自治区林芝市察隅县古拉乡安巴村村民委员会 | O87: 林芝市察隅县古拉乡安巴村股份经济合作社
A88: 540425201619005 | B88: 察隅县 | C88: 2016 | D88: 古拉乡则巴村菩提树种 植及加工项目 | E88: 85 | F88: =SUMIF('附件5-2'!$A$4:$A$336,A88,'附件5-2'!$I$4:$I$336) -> 0 | G88: 0 | H88: 0 | I88: 集体资产 | J88: 农村集体经济组织 | K88: 林芝市察隅县古拉乡则巴村股份经济合作社 | L88: - | M88: 林芝市察隅县古拉乡则巴村股份经济合作社 | N88: 西藏自治区林芝市察隅县古拉乡则巴村村民委员会 | O88: 林芝市察隅县古拉乡则巴村股份经济合作社
A89: 540425201607003 | B89: 察隅县 | C89: 2016 | D89: 俄玉村藏香猪养殖 | E89: 65 | F89: =SUMIF('附件5-2'!$A$4:$A$336,A89,'附件5-2'!$I$4:$I$336) -> 0 | G89: 0 | H89: 0 | I89: 到户资产 | J89: - | K89: - | L89: - | M89: - | N89: - | O89: -
... A91: 540425201619007 | B91: 察隅县 | C91: 2016 | D91: 上察隅镇木碗加工项目 | E91: 20 | F91: =SUMIF('附件5-2'!$A$4:$A$336,A91,'附件5-2'!$I$4:$I$336) -> 0 | G91: 0 | H91: 0 | I91: 集体资产 | J91: 农村集体经济组织 | K91: 林芝市察隅县上察隅镇阿扎村股份经济合作社 | L91: - | M91: 林芝市察隅县上察隅镇阿扎村股份经济合作社 | N91: 西藏自治区林芝市察隅县上察隅镇阿扎村村民委员会 | O91: 林芝市察隅县上察隅镇阿扎村股份经济合作社
A92: 540425201608002 | B92: 察隅县 | C92: 2016 | D92: 察瓦龙乡藏鸡养殖项目 | E92: 9.435 | F92: 84 | G92: 9.435 | H92: 0 | I92: 到户资产 | J92: 农村集体经济组织 | K92: - | L92: - | M92: - | N92: - | O92: -
A93: 540425201607004 | B93: 察隅县 | C93: 2016 | D93: 察瓦龙乡藏猪养殖项目 | E93: 38.907 | F93: =SUMIF('附件5-2'!$A$4:$A$336,A93,'附件5-2'!$I$4:$I$336) -> 0 | G93: 0 | H93: 0 | I93: 到户资产 | J93: - | K93: - | L93: - | M93: - | N93: - | O93: -
A94: 540425201616005 | B94: 察隅县 | C94: 2016 | D94: 察瓦龙乡贫困户温室大棚建设项目 | E94: 57.19 | F94: =SUMIF('附件5-2'!$A$4:$A$336,A94,'附件5-2'!$I$4:$I$336) -> 0 | G94: 0 | H94: 0 | I94: 集体资产 | J94: 农村集体经济组织 | K94: - | L94: - | M94: - | N94: - | O94: -
A95: 540425201608003 | B95: 察隅县 | C95: 2016 | D95: 察瓦龙乡贫困养鸡项目 | E95: 12.71 | F95: =SUMIF('附件5-2'!$A$4:$A$336,A95,'附件5-2'!$I$4:$I$336) -> 0 | G95: 0 | H95: 0 | I95: 到户资产 | J95: - | K95: - | L95: - | M95: - | N95: - | O95: -
A96: 540425201607005 | B96: 察隅县 | C96: 2016 | D96: 察瓦龙乡贫困户养猪项目 | E96: 42.06 | F96: =SUMIF('附件5-2'!$A$4:$A$336,A96,'附件5-2'!$I$4:$I$336) -> 0 | G96: 0 | H96: 0 | I96: 到户资产 | J96: - | K96: - | L96: - | M96: - | N96: - | O96: -
A97: 540425201607006 | B97: 察隅县 | C97: 2016 | D97: 察隅县贫困户藏猪养殖项目 | E97: 474.2525 | F97: =SUMIF('附件5-2'!$A$4:$A$336,A97,'附件5-2'!$I$4:$I$336) -> 0 | G97: 0 | H97: 0 | I97: 到户资产 | J97: - | K97: - | L97: - | M97: - | N97: - | O97: -
A98: 540425201608004 | B98: 察隅县 | C98: 2016 | D98: 察隅县贫困户养殖鸡项目 | E98: 208.605 | F98: =SUMIF('附件5-2'!$A$4:$A$336,A98,'附件5-2'!$I$4:$I$336) -> 0 | G98: 0 | H98: 0 | I98: 到户资产 | J98: - | K98: - | L98: - | M98: - | N98: - | O98: -
A99: 540425201604003 | B99: 察隅县 | C99: 2016 | D99: 察隅县优质犏奶牛繁育基地建设项目 | E99: 199.95 | F99: =SUMIF('附件5-2'!$A$4:$A$336,A99,'附件5-2'!$I$4:$I$336) -> 0 | G99: 0 | H99: 0 | I99: 集体资产 | J99: 农村集体经济组织 | K99: - | L99: - | M99: - | N99: - | O99: -
A100: 540425201718001 | B100: 察隅县 | C100: 2017 | D100: 察隅县察瓦龙乡汽修市场建设项目 | E100: 1308.153 | F100: =SUMIF('附件5-2'!$A$4:$A$336,A100,'附件5-2'!$I$4:$I$336) -> 7 | G100: 1308.153 | H100: 942.54644 | I100: 国有资产 | J100: 乡（镇）人民政府 | K100: 察隅县察瓦龙乡人民政府 | L100: - | M100: 察隅县察瓦龙乡人民政府 | N100: #N/A | O100: 察隅县察瓦龙乡人民政府
A101: 540425201811001 | B101: 察隅县 | C101: 2018 | D101: 察隅县察瓦龙乡龙布村重楼种植项目 | E101: 50 | F101: =SUMIF('附件5-2'!$A$4:$A$336,A101,'附件5-2'!$I$4:$I$336) -> 0 | G101: 28 | H101: 0 | I101: 集体资产 | J101: 农村集体经济组织 | K101: 林芝市察隅县察瓦龙乡龙布村股份经济合作社 | L101: - | M101: 林芝市察隅县察瓦龙乡龙布村股份经济合作社 | N101: 西藏自治区林芝市察隅县察瓦龙乡龙布村村民委员会 | O101: 林芝市察隅县察瓦龙乡龙布村股份经济合作社
A102: 540425201811002 | B102: 察隅县 | C102: 2018 | D102: 察隅县察瓦龙乡扎恩村重楼种植项目 | E102: 64.4 | F102: =SUMIF('附件5-2'!$A$4:$A$336,A102,'附件5-2'!$I$4:$I$336) -> 0 | G102: 0 | H102: 0 | I102: 集体资产 | J102: 农村集体经济组织 | K102: 林芝市察隅县察瓦龙乡扎恩村股份经济合作社 | L102: - | M102: 林芝市察隅县察瓦龙乡扎恩村股份经济合作社 | N102: 西藏自治区林芝市察隅县察瓦龙乡扎恩村村民委员会 | O102: 林芝市察隅县察瓦龙乡扎恩村股份经济合作社
A103: 540425201816008 | B103: 察隅县 | C103: 2018 | D103: 察隅县察瓦龙乡苗圃基地建设项目 | E103: 50 | F103: =SUMIF('附件5-2'!$A$4:$A$336,A103,'附件5-2'!$I$4:$I$336) -> 0 | G103: 0 | H103: 0 | I103: 集体资产 | J103: 乡（镇）人民政府 | K103: 察隅县察瓦龙乡人民政府 | L103: - | M103: 察隅县察瓦龙乡人民政府 | N103: #N/A | O103: 察隅县察瓦龙乡人民政府
A104: 540425201807011 | B104: 察隅县 | C104: 2018 | D104: 察隅县古拉乡俄玉村藏香猪养殖项目 | E104: 50 | F104: =SUMIF('附件5-2'!$A$4:$A$336,A104,'附件5-2'!$I$4:$I$336) -> 108 | G104: 47.52 | H104: 36.225666 | I104: 集体资产 | J104: 农村集体经济组织 | K104: 林芝市察隅县古拉乡俄玉村股份经济合作社 | L104: - | M104: 林芝市察隅县古拉乡俄玉村股份经济合作社 | N104: 西藏自治区林芝市察隅县古拉乡俄玉村村民委员会 | O104: 林芝市察隅县古拉乡俄玉村股份经济合作社 | P104: 俄玉村集体经济组织尚未成立
...

Sheet 附件5-2
A1: 西藏自治区察隅县帮扶产业项目资产明细表 （截至2026年6月20日数据）
A2: 项目编号 | B2: 项目县区 | C2: 资产编号 | D2: 资产名称 | E2: 构（购）建时间 （必填年月） | F2: 坐落或置放 位置 | G2: 资产 型号 | H2: 预计使用年限（自构建时间起预计能够使用的年限数） | I2: 资产 个数 | J2: 资产 原值（元） | K2: 资产累计 折旧 （摊销）（元） | L2: 资产 净值（元） | M2: 资产形态 | N2: 具体形态 | O2: 资产 属性 | P2: 资产状态 | Q2: 资产使用情况 | R2: 资产 类别 | S2: 资产 类别 | T2: 经营性资产运营情况 | U2: 资产所有权主体名称 | V2: 备注
A3: 填表说明：与表3项目编号一致 | C3: 根据指南编码规则对资产进行编号 | D3: 按形成的具体资产名称填写，不同资产应分行填写 | E3: 例：2018.01 | H3: 例：10（即为该资产预计可使用时间为10年） | J3: 保留2位小数 | K3: 统计时间为截止2024年12月31日 （权益类资产、消耗性生物资产、公益性生物资产不填） 保留2位小数 | L3: 统计时间为截止2024年12月31日 保留2位小数 | M3: 在“固定资产、生物资产（含消耗性生物资产、生产性生物资产、公益性生物资产）、权益类资产、其他资产”中选择 | N3: 在“房屋建筑物、构筑物、机器设备、车辆、办公用具家具、牲畜（禽）、林木、股权资产、债权资产、低值易耗品、无形资产”中选择 | O3: 在“国有资产、集体资产”中选择 | P3: 在“正常、损坏、损毁”中选择 | Q3: 根据实际情况填写“在用/不在用” | R3: 在“自用、出租、存栏、在培、已消耗、已出售、已死亡、闲置、损毁、拆除、待维修、盘亏等”中选择 | S3: 在“经营性资产、公益性资产”中选择 | T3: 在“正常、低效、闲置”中选择
A4: 540425201916012 | B4: 察隅县 | C4: 54042520191601210001 | D4: 联栋温室大棚 | E4: 43466 | F4: 学尼村 | G4: 个 | H4: 20 | I4: 1 | J4: 1855000 | K4: 556500 | L4: 1298500 | M4: 固定资产 | N4: 构筑物 | O4: 集体资产 | P4: 正常 | Q4: 在用 | R4: 出租 | S4: 经营性资产 | T4: 正常 | U4: 林芝市察隅县竹瓦根镇学尼村股份经济合作社
A5: 540425201916012 | B5: 察隅县 | C5: 54042520191601210002 | D5: 联栋温室大棚 | E5: 43466 | F5: 学尼村 | G5: 个 | H5: 20 | I5: 1 | J5: 1855000 | K5: 556500 | L5: 1298500 | M5: 固定资产 | N5: 构筑物 | O5: 集体资产 | P5: 正常 | Q5: 在用 | R5: 出租 | S5: 经营性资产 | T5: 正常 | U5: 林芝市察隅县竹瓦根镇学尼村股份经济合作社
A6: 540425201916012 | B6: 察隅县 | C6: 54042520191601210003 | D6: 联栋温室大棚 | E6: 43466 | F6: 学尼村 | G6: 个 | H6: 20 | I6: 1 | J6: 1855000 | K6: 556500 | L6: 1298500 | M6: 固定资产 | N6: 构筑物 | O6: 集体资产 | P6: 正常 | Q6: 在用 | R6: 出租 | S6: 经营性资产 | T6: 正常 | U6: 林芝市察隅县竹瓦根镇学尼村股份经济合作社
A7: 540425201916012 | B7: 察隅县 | C7: 54042520191601210004 | D7: 联栋温室大棚 | E7: 43466 | F7: 学尼村 | G7: 个 | H7: 20 | I7: 1 | J7: 1855000 | K7: 556500 | L7: 1298500 | M7: 固定资产 | N7: 构筑物 | O7: 集体资产 | P7: 正常 | Q7: 在用 | R7: 出租 | S7: 经营性资产 | T7: 正常 | U7: 林芝市察隅县竹瓦根镇学尼村股份经济合作社
A8: 540425202116013 | B8: 察隅县 | C8: 54042520211601310001 | D8: 温室大棚 | E8: 44562 | F8: 学尼村 | G8: 个 | H8: 20 | I8: 1 | J8: 1238530.2 | K8: 185779.53 | L8: 1052750.6 | M8: 固定资产 | N8: 构筑物 | O8: 集体资产 | P8: 正常 | Q8: 在用 | R8: 闲置 | S8: 经营性资产 | T8: 正常 | U8: 林芝市察隅县竹瓦根镇学尼村股份经济合作社
A9: 540425202116013 | B9: 察隅县 | C9: 54042520211601310002 | D9: 温室大棚 | E9: 44562 | F9: 学尼村 | G9: 个 | H9: 20 | I9: 1 | J9: 1238530.2 | K9: 185779.53 | L9: 1052750.6 | M9: 固定资产 | N9: 构筑物 | O9: 集体资产 | P9: 正常 | Q9: 在用 | R9: 闲置 | S9: 经营性资产 | T9: 正常 | U9: 林芝市察隅县竹瓦根镇学尼村股份经济合作社
A10: 540425202116013 | B10: 察隅县 | C10: 54042520211601310003 | D10: 温室大棚 | E10: 44562 | F10: 学尼村 | G10: 个 | H10: 20 | I10: 1 | J10: 1238530.2 | K10: 185779.53 | L10: 1052750.6 | M10: 固定资产 | N10: 构筑物 | O10: 集体资产 | P10: 正常 | Q10: 在用 | R10: 闲置 | S10: 经营性资产 | T10: 正常 | U10: 林芝市察隅县竹瓦根镇学尼村股份经济合作社
A11: 540425201908006 | B11: 察隅县 | C11: 54042520190800610001 | D11: 鸡舍 | E11: 43647 | F11: 空档村 | G11: 栋 | H11: 20 | I11: 1 | J11: 228983.33 | K11: 62970.42 | L11: 166012.91 | M11: 固定资产 | N11: 房屋建筑物 | O11: 集体资产 | P11: 正常 | Q11: 在用 | R11: 闲置 | S11: 经营性资产 | T11: 正常 | U11: 林芝市察隅县竹瓦根镇空档村股份经济合作社
A12: 540425201908006 | B12: 察隅县 | C12: 54042520190800610002 | D12: 鸡舍 | E12: 43647 | F12: 空档村 | G12: 栋 | H12: 20 | I12: 1 | J12: 228983.33 | K12: 62970.42 | L12: 166012.91 | M12: 固定资产 | N12: 房屋建筑物 | O12: 集体资产 | P12: 正常 | Q12: 在用 | R12: 闲置 | S12: 经营性资产 | T12: 正常 | U12: 林芝市察隅县竹瓦根镇空档村股份经济合作社
A13: 540425201908006 | B13: 察隅县 | C13: 54042520190800610003 | D13: 消毒池 | E13: 43647 | F13: 空档村 | G13: 座 | H13: 20 | I13: 1 | J13: 132533.34 | K13: 36446.67 | L13: 96086.67 | M13: 固定资产 | N13: 房屋建筑物 | O13: 集体资产 | P13: 正常 | Q13: 在用 | R13: 闲置 | S13: 经营性资产 | T13: 正常 | U13: 林芝市察隅县竹瓦根镇空档村股份经济合作社
A14: 540425202019028 | B14: 察隅县 | C14: 54042520201902810001 | D14: 10吨水处理系统 | E14: 43831 | F14: 嘎巴村 | G14: 套 | H14: 10 | I14: 1 | J14: 349000 | K14: 174500 | L14: 174500 | M14: 固定资产 | N14: 机器设备 | O14: 国有资产 | P14: 正常 | Q14: 在用 | R14: 闲置 | S14: 经营性资产 | T14: 正常 | U14: 察隅县雪巅啤酒有限公司
A15: 540425202019028 | B15: 察隅县 | C15: 54042520201902810002 | D15: 粉碎系统 | E15: 43831 | F15: 嘎巴村 | G15: 套 | H15: 10 | I15: 1 | J15: 88000 | K15: 44000 | L15: 44000 | M15: 固定资产 | N15: 机器设备 | O15: 国有资产 | P15: 正常 | Q15: 在用 | R15: 闲置 | S15: 经营性资产 | T15: 正常 | U15: 察隅县雪巅啤酒有限公司
... A115: 540425201918003 | B115: 察隅县 | C115: 54042520191800310007 | D115: 大门 | E115: 44105 | F115: 竹瓦根镇 | G115: 栋 | H115: 20 | I115: 1 | J115: 216400 | K115: 45985 | L115: 170415 | M115: 固定资产 | N115: 房屋建筑物 | O115: 国有资产 | P115: 正常 | Q115: 在用 | R115: 出租 | S115: 经营性资产 | T115: 正常 | U115: 察隅县扶贫开发投资有限公司
A116: 540425202204009 | B116: 察隅县 | C116: 54042520220400910001 | D116: 通电工程 | E116: 45078 | F116: 罗马村 | G116: 套 | H116: 20 | I116: 1 | J116: 942468.4 | K116: 74612.08 | L116: 867856.32 | M116: 固定资产 | N116: 构筑物 | O116: 集体资产 | P116: 正常 | Q116: 在用 | R116: 出租 | S116: 公益性资产 | U116: 林芝市察隅县古玉乡罗马村股份经济合作社
A117: 540425201907012 | B117: 察隅县 | C117: 54042520190701210001 | D117: 猪舍 | E117: 43952 | F117: 沙琼村 | G117: 栋 | H117: 20 | I117: 1 | J117: 143333.33 | K117: 33444.44 | L117: 109888.89 | M117: 固定资产 | N117: 房屋建筑物 | O117: 集体资产 | P117: 正常 | Q117: 在用 | R117: 出租 | S117: 经营性资产 | T117: 正常 | U117: 林芝市察隅县下察隅镇沙琼村股份经济合作社
A118: 540425201907012 | B118: 察隅县 | C118: 54042520190701210002 | D118: 饲料库房 | E118: 43952 | F118: 沙琼村 | G118: 栋 | H118: 20 | I118: 1 | J118: 55000 | K118: 12833.33 | L118: 42166.67 | M118: 固定资产 | N118: 房屋建筑物 | O118: 集体资产 | P118: 正常 | Q118: 在用 | R118: 出租 | S118: 经营性资产 | T118: 正常 | U118: 林芝市察隅县下察隅镇沙琼村股份经济合作社
A119: 540425201907012 | B119: 察隅县 | C119: 54042520190701210003 | D119: 饲料加工房 | E119: 43952 | F119: 沙琼村 | G119: 栋 | H119: 20 | I119: 1 | J119: 36666.67 | K119: 8555.56 | L119: 28111.11 | M119: 固定资产 | N119: 房屋建筑物 | O119: 集体资产 | P119: 正常 | Q119: 在用 | R119: 出租 | S119: 经营性资产 | T119: 正常 | U119: 林芝市察隅县下察隅镇沙琼村股份经济合作社
A120: 540425201907012 | B120: 察隅县 | C120: 54042520190701210004 | D120: 蓄水池 | E120: 43952 | F120: 沙琼村 | G120: 座 | H120: 20 | I120: 1 | J120: 2700 | K120: 630 | L120: 2070 | M120: 固定资产 | N120: 房屋建筑物 | O120: 集体资产 | P120: 正常 | Q120: 在用 | R120: 出租 | S120: 经营性资产 | T120: 正常 | U120: 林芝市察隅县下察隅镇沙琼村股份经济合作社
A121: 540425201907012 | B121: 察隅县 | C121: 54042520190701210005 | D121: 饲料加工机 | E121: 43952 | F121: 沙琼村 | G121: 台 | H121: 5 | I121: 1 | J121: 10000 | K121: 9333.33 | L121: 666.67 | M121: 固定资产 | N121: 机器设备 | O121: 集体资产 | P121: 正常 | Q121: 在用 | R121: 出租 | S121: 经营性资产 | T121: 正常 | U121: 林芝市察隅县下察隅镇沙琼村股份经济合作社
A122: 540425201907012 | B122: 察隅县 | C122: 54042520190701210006 | D122: 柴油发电机 | E122: 43952 | F122: 沙琼村 | G122: 台 | H122: 5 | I122: 1 | J122: 7800 | K122: 7280 | L122: 520 | M122: 固定资产 | N122: 机器设备 | O122: 集体资产 | P122: 损毁 | Q122: 不在用 | R122: 损毁 | S122: 经营性资产 | T122: 闲置 | U122: 林芝市察隅县下察隅镇沙琼村股份经济合作社
A123: 540425201907012 | B123: 察隅县 | C123: 54042520190701220007 | D123: 猪 | E123: 43952 | F123: 沙琼村 | G123: 只 | H123: 3 | I123: 63 | J123: 244500 | K123: 244500 | L123: 0 | M123: 生物资产 | N123: 牲畜（禽） | O123: 集体资产 | P123: 损毁 | Q123: 不在用 | R123: 已死亡 | S123: 经营性资产 | T123: 闲置 | U123: 林芝市察隅县下察隅镇沙琼村股份经济合作社
A124: 540425201715001 | B124: 察隅县 | C124: 54042520171500110001 | D124: 管理培训中心 | E124: 43252 | F124: 夏尼村 | G124: 栋 | H124: 20 | I124: 1 | J124: 850759.99 | K124: 280041.83 | L124: 570718.16 | M124: 固定资产 | N124: 房屋建筑物 | O124: 集体资产 | P124: 正常 | Q124: 在用 | R124: 出租 | S124: 经营性资产 | T124: 正常 | U124: 林芝市察隅县下察隅镇夏尼村股份经济合作社
A125: 540425201715001 | B125: 察隅县 | C125: 54042520171500110002 | D125: 猕猴桃架桩 | E125: 43252 | F125: 夏尼村 | G125: 套 | H125: 10 | I125: 1 | J125: 235300 | K125: 154905.83 | L125: 80394.17 | M125: 固定资产 | N125: 构筑物 | O125: 集体资产 | P125: 正常 | Q125: 在用 | R125: 出租 | S125: 经营性资产 | T125: 正常 | U125: 林芝市察隅县下察隅镇夏尼村股份经济合作社
A126: 540425201715001 | B126: 察隅县 | C126: 54042520171500110003 | D126: 铁丝网 | E126: 43252 | F126: 夏尼村 | G126: 套 | H126: 10 | I126: 1 | J126: 120000 | K126: 79000 | L126: 41000 | M126: 固定资产 | N126: 构筑物 | O126: 集体资产 | P126: 正常 | Q126: 在用 | R126: 出租 | S126: 经营性资产 | T126: 正常 | U126: 林芝市察隅县下察隅镇夏尼村股份经济合作社
A127: 540425201715001 | B127: 察隅县 | C127: 54042520171500120004 | D127: 猕猴桃苗木 | E127: 43252 | F127: 夏尼村 | G127: 株 | H127: 10 | I127: 6000 | J127: 54000 | K127: 35550 | L127: 18450 | M127: 生物资产 | N127: 林木 | O127: 集体资产 | P127: 正常 | Q127: 在用 | R127: 出租 | S127: 经营性资产 | T127: 正常 | U127: 林芝市察隅县下察隅镇夏尼村股份经济合作社
A128: 540425202115006 | B128: 察隅县 | C128: 54042520211500620001 | D128: 猕猴桃 | E128: 44562 | F128: 夏尼村 | G128: 亩 | H128: 10 | I128: 100 | J128: 2294800 | K128: 688440 | L128: 1606360 | M128: 生物资产 | N128: 林木 | O128: 集体资产 | P128: 正常 | Q128: 在用 | R128: 出租 | S128: 经营性资产 | T128: 正常 | U128: 林芝市察隅县下察隅镇夏尼村股份经济合作社 | V128: 项目原种植数量无数据，期间又有补种等，无法核实项目原始株树
A129: 540425202115004 | B129: 察隅县 | C129: 54042520211500410001 | D129: 青石板步道 | E129: 44501 | F129: 夏尼村 | G129: 600米 | H129: 10 | I129: 1 | J129: 115200 | K129: 36480 | L129: 78720 | M129: 固定资产 | N129: 构筑物 | O129: 集体资产 | P129: 正常 | Q129: 在用 | R129: 出租 | S129: 公益性资产 | U129: 林芝市察隅县下察隅镇夏尼村股份经济合作社
A130: 540425202117013 | B130: 察隅县 | C130: 54042520211701310001 | D130: 铭牌 | E130: 44501 | F130: 夏尼村 | G130: 座 | H130: 10 | I130: 1 | J130: 52000 | K130: 16466.67 | L130: 35533.33 | M130: 固定资产 | N130: 构筑物 | O130: 集体资产 | P130: 正常 | Q130: 在用 | R130: 出租 | S130: 公益性资产 | U130: 林芝市察隅县下察隅镇夏尼村股份经济合作社
A131: 540425202117013 | B131: 察隅县 | C131: 54042520211701310002 | D131: 停车场 | E131: 44501 | F131: 夏尼村 | G131: 525平方米 | H131: 10 | I131: 1 | J131: 184700 | K131: 58488.33 | L131: 126211.67 | M131: 固定资产 | N131: 构筑物 | O131: 集体资产 | P131: 正常 | Q131: 在用 | R131: 自用 | S131: 公益性资产 | U131: 林芝市察隅县下察隅镇夏尼村股份经济合作社
A132: 540425202117013 | B132: 察隅县 | C132: 54042520211701310003 | D132: 镂空围墙 | E132: 44501 | F132: 夏尼村 | G132: 51米 | H132: 10 | I132: 1 | J132: 23300 | K132: 7378.33 | L132: 15921.67 | M132: 固定资产 | N132: 构筑物 | O132: 集体资产 | P132: 正常 | Q132: 在用 | R132: 自用 | S132: 公益性资产 | U132: 林芝市察隅县下察隅镇夏尼村股份经济合作社
A133: 540425202117013 | B133: 察隅县 | C133: 54042520211701310004 | D133: 小挡墙 | E133: 44501 | F133: 夏尼村 | G133: 35.96米 | H133: 10 | I133: 1 | J133: 12300 | K133: 3895 | L133: 8405 | M133: 固定资产 | N133: 构筑物 | O133: 集体资产 | P133: 正常 | Q133: 在用 | R133: 自用 | S133: 公益性资产 | U133: 林芝市察隅县下察隅镇夏尼村股份经济合作社
A134: 540425202117013 | B134: 察隅县 | C134: 54042520211701310005 | D134: 僜人雕塑 | E134: 44501 | F134: 夏尼村 | G134: 座 | H134: 10 | I134: 1 | J134: 62700 | K134: 19855 | L134: 42845 | M134: 固定资产 | N134: 构筑物 | O134: 集体资产 | P134: 正常 | Q134: 在用 | R134: 自用 | S134: 公益性资产 | U134: 林芝市察隅县下察隅镇夏尼村股份经济合作社
A135: 540425202117013 | B135: 察隅县 | C135: 54042520211701310006 | D135: 僜人雕塑 | E135: 44501 | F135: 夏尼村 | G135: 座 | H135: 10 | I135: 1 | J135: 62700 | K135: 19855 | L135: 42845 | M135: 固定资产 | N135: 构筑物 | O135: 集体资产 | P135: 正常 | Q135: 在用 | R135: 自用 | S135: 公益性资产 | U135: 林芝市察隅县下察隅镇夏尼村股份经济合作社
A136: 540425202117013 | B136: 察隅县 | C136: 54042520211701310007 | D136: 景观石 | E136: 44501 | F136: 夏尼村 | G136: 个 | H136: 10 | I136: 1 | J136: 13075 | K136: 4140.42 | L136: 8934.58 | M136: 固定资产 | N136: 构筑物 | O136: 集体资产 | P136: 损毁 | Q136: 不在用 | R136: 损毁 | S136: 公益性资产 | U136: 林芝市察隅县下察隅镇夏尼村股份经济合作社
A137: 540425202117013 | B137: 察隅县 | C137: 54042520211701310008 | D137: 景观石 | E137: 44501 | F137: 夏尼村 | G137: 个 | H137: 10 | I137: 1 | J137: 13075 | K137: 4140.42 | L137: 8934.58 | M137: 固定资产 | N137: 构筑物 | O137: 集体资产 | P137: 损毁 | Q137: 不在用 | R137: 损毁 | S137: 公益性资产 | U137: 林芝市察隅县下察隅镇夏尼村股份经济合作社
A138: 540425202117013 | B138: 察隅县 | C138: 54042520211701310009 | D138: 景观石 | E138: 44501 | F138: 夏尼村 | G138: 个 | H138: 10 | I138: 1 | J138: 13075 | K138: 4140.42 | L138: 8934.58 | M138: 固定资产 | N138: 构筑物 | O138: 集体资产 | P138: 损毁 | Q138: 不在用 | R138: 损毁 | S138: 公益性资产 | U138: 林芝市察隅县下察隅镇夏尼村股份经济合作社
A139: 540425202117013 | B139: 察隅县 | C139: 54042520211701310010 | D139: 景观石 | E139: 44501 | F139: 夏尼村 | G139: 个 | H139: 10 | I139: 1 | J139: 13075 | K139: 4140.42 | L139: 8934.58 | M139: 固定资产 | N139: 构筑物 | O139: 集体资产 | P139: 损毁 | Q139: 不在用 | R139: 损毁 | S139: 公益性资产 | U139: 林芝市察隅县下察隅镇夏尼村股份经济合作社
A140: 540425202019030 | B140: 察隅县 | C140: 54042520201903010001 | D140: 网围栏 | E140: 43831 | F140: 京都村 | G140: 4346米 | H140: 10 | I140: 1 | J140: 336600 | K140: 168300 | L140: 168300 | M140: 固定资产 | N140: 构筑物 | O140: 集体资产 | P140: 正常 | Q140: 在用 | R140: 自用 | S140: 经营性资产 | T140: 正常 | U140: 林芝市察隅县下察隅镇京都村股份经济合作社
A141: 540425202019030 | B141: 察隅县 | C141: 54042520201903010002 | D141: 混泥土道路 | E141: 43831 | F141: 京都村 | G141: 939.16平方米 | H141: 10 | I141: 1 | J141: 263400 | K141: 131700 | L141: 131700 | M141: 固定资产 | N141: 构筑物 | O141: 集体资产 | P141: 正常 | Q141: 在用 | R141: 自用 | S141: 经营性资产 | T141: 正常 | U141: 林芝市察隅县下察隅镇京都村股份经济合作社
A142: 540425202315008 | B142: 察隅县 | C142: 54042520231500830001 | D142: 下察隅镇沙琼村、洞冲村入股猕猴桃基地 | E142: 45231 | F142: 沙琼村 | G142: 140万元 | I142: 1 | J142: 1400000 | K142: - | L142: 0 | M142: 权益类资产 | N142: 股权资产 | O142: 集体资产 | P142: 正常 | Q142: 在用 | R142: 自用 | S142: 经营性资产 | T142: 正常 | U142: 林芝市察隅县下察隅镇沙琼村股份经济合作社、林芝市察隅县下察隅镇洞冲村股份经济合作社
A143: 540425202212029 | B143: 察隅县 | C143: 5404252022120290001 | D143: 一体化用房 | E143: 45017 | F143: 卡地村 | G143: 栋 | H143: 20 | I143: 1 | J143: 167800 | K143: 14682.5 | L143: 153117.5 | M143: 固定资产 | N143: 房屋建筑物 | O143: 集体资产 | P143: 正常 | Q143: 在用 | R143: 出租 | S143: 公益性资产 | U143: 林芝市察隅县下察隅镇卡地村股份经济合作社
A144: 540425202212029 | B144: 察隅县 | C144: 5404252022120290002 | D144: 主大门 | E144: 45017 | F144: 卡地村 | G144: 个 | H144: 10 | I144: 1 | J144: 39500 | K144: 6912.5 | L144: 32587.5 | M144: 固定资产 | N144: 构筑物 | O144: 集体资产 | P144: 正常 | Q144: 在用 | R144: 出租 | S144: 公益性资产 | U144: 林芝市察隅县下察隅镇卡地村股份经济合作社
A145: 540425202212029 | B145: 察隅县 | C145: 5404252022120290003 | D145: 次大门 | E145: 45017 | F145: 卡地村 | G145: 个 | H145: 10 | I145: 1 | J145: 20300 | K145: 3552.5 | L145: 16747.5 | M145: 固定资产 | N145: 构筑物 | O145: 集体资产 | P145: 正常 | Q145: 在用 | R145: 出租 | S145: 公益性资产 | U145: 林芝市察隅县下察隅镇卡地村股份经济合作社
A146: 540425202212029 | B146: 察隅县 | C146: 5404252022120290004 | D146: 景观木屋 | E146: 45017 | F146: 卡地村 | G146: 栋 | H146: 20 | I146: 1 | J146: 141700 | K146: 12398.75 | L146: 129301.25 | M146: 固定资产 | N146: 构筑物 | O146: 集体资产 | P146: 正常 | Q146: 在用 | R146: 出租 | S146: 公益性资产 | U146: 林芝市察隅县下察隅镇卡地村股份经济合作社
A147: 540425202212029 | B147: 察隅县 | C147: 5404252022120290005 | D147: 木栈道 | E147: 45017 | F147: 卡地村 | G147: 672米 | H147: 10 | I147: 1 | J147: 1195900 | K147: 209282.5 | L147: 986617.5 | M147: 固定资产 | N147: 构筑物 | O147: 集体资产 | P147: 正常 | Q147: 在用 | R147: 出租 | S147: 公益性资产 | U147: 林芝市察隅县下察隅镇卡地村股份经济合作社
A148: 540425202212029 | B148: 察隅县 | C148: 5404252022120290006 | D148: 金属围网 | E148: 45017 | F148: 卡地村 | G148: 643米 | H148: 10 | I148: 1 | J148: 148200 | K148: 25935 | L148: 122265 | M148: 固定资产 | N148: 构筑物 | O148: 集体资产 | P148: 正常 | Q148: 在用 | R148: 出租 | S148: 公益性资产 | U148: 林芝市察隅县下察隅镇卡地村股份经济合作社
A149: 540425202212029 | B149: 察隅县 | C149: 5404252022120290007 | D149: 碎石道路 | E149: 45017 | F149: 卡地村 | G149: 2525米 | H149: 10 | I149: 1 | J149: 137100 | K149: 23992.5 | L149: 113107.5 | M149: 固定资产 | N149: 构筑物 | O149: 集体资产 | P149: 正常 | Q149: 在用 | R149: 出租 | S149: 公益性资产 | U149: 林芝市察隅县下察隅镇卡地村股份经济合作社
A150: 540425202212029 | B150: 察隅县 | C150: 5404252022120290008 | D150: 石材铺装路 | E150: 45017 | F150: 卡地村 | G150: 273米 | H150: 10 | I150: 1 | J150: 62100 | K150: 10867.5 | L150: 51232.5 | M150: 固定资产 | N150: 构筑物 | O150: 集体资产 | P150: 正常 | Q150: 在用 | R150: 出租 | S150: 公益性资产 | U150: 林芝市察隅县下察隅镇卡地村股份经济合作社
A151: 540425202212029 | B151: 察隅县 | C151: 5404252022120290009 | D151: 葡萄廊架 | E151: 45017 | F151: 卡地村 | G151: 30米 | H151: 10 | I151: 1 | J151: 99900 | K151: 17482.5 | L151: 82417.5 | M151: 固定资产 | N151: 构筑物 | O151: 集体资产 | P151: 正常 | Q151: 在用 | R151: 出租 | S151: 公益性资产 | U151: 林芝市察隅县下察隅镇卡地村股份经济合作社
A152: 540425202012020 | B152: 察隅县 | C152: 5404252020120200001 | D152: 茶苗 | E152: 44075 | F152: 卡地村 | G152: 亩 | H152: 10 | I152: 266.46 | J152: 405900 | K152: 175890 | L152: 230010 | M152: 生物资产 | N152: 林木 | O152: 集体资产 | P152: 损坏 | Q152: 在用 | R152: 出租 | S152: 经营性资产 | T152: 正常 | U152: 林芝市察隅县下察隅镇卡地村股份经济合作社
A153: 540425201812003 | B153: 察隅县 | C153: 5404252018120030001 | D153: 茶苗 | E153: 43497 | F153: 毕达村 | G153: 亩 | H153: 10 | I153: 290.82 | J153: 3660500 | K153: 2165795.8 | L153: 1494704.2 | M153: 生物资产 | N153: 林木 | O153: 国有资产 | P153: 损坏 | Q153: 不在用 | R153: 已死亡 | S153: 经营性资产 | T153: 闲置 | U153: 察隅县扶贫开发投资有限公司
A154: 540425201812003 | B154: 察隅县 | C154: 5404252018120030002 | D154: 蓄水池 | E154: 43497 | F154: 毕达村 | G154: 座 | H154: 10 | I154: 1 | J154: 81900 | K154: 48457.5 | L154: 33442.5 | M154: 固定资产 | N154: 构筑物 | O154: 国有资产 | P154: 正常 | Q154: 不在用 | R154: 闲置 | S154: 经营性资产 | T154: 闲置 | U154: 察隅县扶贫开发投资有限公司
A155: 540425201812003 | B155: 察隅县 | C155: 5404252018120030003 | D155: 沉砂池 | E155: 43497 | F155: 毕达村 | G155: 座 | H155: 10 | I155: 1 | J155: 5300 | K155: 3135.83 | L155: 2164.17 | M155: 固定资产 | N155: 构筑物 | O155: 国有资产 | P155: 正常 | Q155: 不在用 | R155: 闲置 | S155: 经营性资产 | T155: 闲置 | U155: 察隅县扶贫开发投资有限公司
A156: 540425201812003 | B156: 察隅县 | C156: 5404252018120030004 | D156: 钢丝网围栏 | E156: 43497 | F156: 毕达村 | G156: 3500米 | H156: 10 | I156: 1 | J156: 662700 | K156: 392097.5 | L156: 270602.5 | M156: 固定资产 | N156: 构筑物 | O156: 国有资产 | P156: 正常 | Q156: 不在用 | R156: 闲置 | S156: 经营性资产 | T156: 闲置 | U156: 察隅县扶贫开发投资有限公司
A157: 540425201812003 | B157: 察隅县 | C157: 5404252018120030005 | D157: 除草机 | E157: 43497 | F157: 毕达村 | G157: 部 | H157: 5 | I157: 4 | J157: 6000 | K157: 6000 | L157: 0 | M157: 固定资产 | N157: 机器设备 | O157: 国有资产 | P157: 正常 | Q157: 不在用 | R157: 闲置 | S157: 经营性资产 | T157: 闲置 | U157: 察隅县扶贫开发投资有限公司
A158: 540425201812003 | B158: 察隅县 | C158: 5404252018120030006 | D158: 修剪机 | E158: 43497 | F158: 毕达村 | G158: 台 | H158: 5 | I158: 4 | J158: 10000 | K158: 10000 | L158: 0 | M158: 固定资产 | N158: 机器设备 | O158: 国有资产 | P158: 正常 | Q158: 不在用 | R158: 闲置 | S158: 经营性资产 | T158: 闲置 | U158: 察隅县扶贫开发投资有限公司
A159: 540425201812003 | B159: 察隅县 | C159: 5404252018120030007 | D159: 中耕机 | E159: 43497 | F159: 毕达村 | G159: 台 | H159: 5 | I159: 4 | J159: 60000 | K159: 60000 | L159: 0 | M159: 固定资产 | N159: 机器设备 | O159: 国有资产 | P159: 正常 | Q159: 不在用 | R159: 闲置 | S159: 经营性资产 | T159: 闲置 | U159: 察隅县扶贫开发投资有限公司
A160: 540425201812003 | B160: 察隅县 | C160: 5404252018120030008 | D160: 施肥机 | E160: 43497 | F160: 毕达村 | G160: 台 | H160: 5 | I160: 2 | J160: 6400 | K160: 6400 | L160: 0 | M160: 固定资产 | N160: 机器设备 | O160: 国有资产 | P160: 正常 | Q160: 不在用 | R160: 闲置 | S160: 经营性资产 | T160: 闲置 | U160: 察隅县扶贫开发投资有限公司
A161: 540425202212024 | B161: 察隅县 | C161: 5404252022120240001 | D161: 茶苗 | E161: 45292 | F161: 桑典村 | G161: 亩 | H161: 10 | I161: 487 | J161: 8452031.4 | K161: 845203.14 | L161: 7606828.2 | M161: 生物资产 | N161: 林木 | O161: 集体资产 | P161: 损坏 | Q161: 在用 | R161: 出租 | S161: 经营性资产 | T161: 低效 | U161: 林芝市察隅县上察隅镇桑典村股份经济合作社
A162: 540425202012017 | B162: 察隅县 | C162: 5404252020120170001 | D162: 茶苗 | E162: 43862 | F162: 松林村 | G162: 亩 | H162: 10 | I162: 133.32 | J162: 1264600 | K162: 621761.67 | L162: 642838.33 | M162: 生物资产 | N162: 林木 | O162: 集体资产 | P162: 损坏 | Q162: 在用 | R162: 出租 | S162: 经营性资产 | T162: 低效 | U162: 林芝市察隅县上察隅镇松林村股份经济合作社
A163: 540425202012017 | B163: 察隅县 | C163: 5404252020120170001 | D163: 25m3蓄水池 | E163: 45047 | F163: 松林村 | G163: 座 | H163: 10 | I163: 1 | J163: 73200 | K163: 12200 | L163: 61000 | M163: 固定资产 | N163: 构筑物 | O163: 集体资产 | P163: 正常 | Q163: 在用 | R163: 出租 | S163: 经营性资产 | T163: 低效 | U163: 林芝市察隅县上察隅镇松林村股份经济合作社
... A172: 540425201912014 | B172: 察隅县 | C172: 5404252019120140005 | D172: 除草机 | E172: 43922 | F172: 竹巴村 | G172: 台 | H172: 5 | I172: 2 | J172: 3600 | K172: 3420 | L172: 180 | M172: 固定资产 | N172: 机器设备 | O172: 集体资产 | P172: 损坏 | Q172: 在用 | R172: 出租 | S172: 经营性资产 | T172: 低效 | U172: 林芝市察隅县上察隅镇竹巴村股份经济合作社
A173: 540425201712009 | B173: 察隅县 | C173: 5404252018120090001 | D173: 茶苗 | E173: 43101 | F173: 体育村 | G173: 亩 | H173: 10 | I173: 83 | J173: 6007000 | K173: 4204900 | L173: 1802100 | M173: 生物资产 | N173: 林木 | O173: 集体资产 | P173: 损坏 | Q173: 不再用 | R173: 已死亡 | S173: 经营性资产 | T173: 闲置 | U173: 林芝市察隅县上察隅镇体育村股份经济合作社 | V173: 到户资产
A174: 540425201912011 | B174: 察隅县 | C174: 5404252019120110001 | D174: 50m³蓄水池 | E174: 43891 | F174: 体育村 | G174: 座 | H174: 10 | I174: 1 | J174: 109200 | K174: 52780 | L174: 56420 | M174: 固定资产 | N174: 构筑物 | O174: 集体资产 | P174: 正常 | Q174: 不再用 | R174: 闲置 | S174: 经营性资产 | T174: 闲置 | U174: 林芝市察隅县上察隅镇体育村股份经济合作社
A175: 540425201912011 | B175: 察隅县 | C175: 5404252019120110002 | D175: 茶苗 | E175: 43891 | F175: 体育村 | G175: 亩 | H175: 10 | I175: 0 | J175: 1157200 | K175: 559313.33 | L175: 597886.67 | M175: 生物资产 | N175: 林木 | O175: 集体资产 | P175: 损毁 | Q175: 不再用 | R175: 已死亡 | S175: 经营性资产 | T175: 闲置 | U175: 林芝市察隅县上察隅镇体育村股份经济合作社
A176: 540425201912011 | B176: 察隅县 | C176: 5404252019120110003 | D176: 铁丝网围栏 | E176: 43891 | F176: 体育村 | G176: 1263米 | H176: 10 | I176: 1 | J176: 108700 | K176: 52538.33 | L176: 56161.67 | M176: 固定资产 | N176: 构筑物 | O176: 集体资产 | P176: 损坏 | Q176: 不再用 | R176: 损毁 | S176: 经营性资产 | T176: 闲置 | U176: 林芝市察隅县上察隅镇体育村股份经济合作社
A177: 540425201912011 | B177: 察隅县 | C177: 5404252019120110004 | D177: 大门 | E177: 43891 | F177: 体育村 | G177: 个 | H177: 10 | I177: 1 | J177: 4400 | K177: 2126.67 | L177: 2273.33 | M177: 固定资产 | N177: 构筑物 | O177: 集体资产 | P177: 损坏 | Q177: 不再用 | R177: 损毁 | S177: 经营性资产 | T177: 闲置 | U177: 林芝市察隅县上察隅镇体育村股份经济合作社
A178: 540425201712009 | B178: 察隅县 | C178: 5404252018120090001 | D178: 茶苗 | E178: 43466 | F178: 体育村 | G178: 亩 | H178: 10 | I178: 0 | J178: 6007000 | K178: 6007000 | L178: 0 | M178: 生物资产 | N178: 林木 | O178: 集体资产 | P178: 损毁 | Q178: 不再用 | R178: 已死亡 | S178: 经营性资产 | T178: 闲置 | U178: 林芝市察隅县上察隅镇体育村股份经济合作社
A179: 540425202321004 | B179: 察隅县 | C179: 5404252023210040001 | D179: 木耳菌包 | E179: 45139 | F179: 布宗村 | G179: 个 | H179: 10 | I179: 387831 | J179: 3851300 | K179: 545600.83 | L179: 3305699.2 | M179: 生物资产 | N179: 林木 | O179: 集体资产 | P179: 损坏 | Q179: 不再用 | R179: 已消耗 | S179: 经营性资产 | T179: 低效 | U179: 林芝市察隅县上察隅镇布宗村股份经济合作社
A180: 540425202321004 | B180: 察隅县 | C180: 5404252023210040002 | D180: 200m³蓄水池 | E180: 45139 | F180: 布宗村 | G180: 座 | H180: 10 | I180: 1 | J180: 263800 | K180: 37371.67 | L180: 226428.33 | M180: 固定资产 | N180: 构筑物 | O180: 集体资产 | P180: 损毁 | Q180: 不再用 | R180: 损毁 | S180: 经营性资产 | T180: 闲置 | U180: 林芝市察隅县上察隅镇布宗村股份经济合作社 | V180: 泥石流
A181: 540425201812008 | B181: 察隅县 | C181: 5404252018120080001 | D181: 茶苗 | E181: 43466 | F181: 荣玉村 | G181: 亩 | H181: 10 | I181: 158 | J181: 1058700 | K181: 635220 | L181: 423480 | M181: 生物资产 | N181: 林木 | O181: 集体资产 | P181: 损毁 | Q181: 不再用 | R181: 已死亡 | S181: 公益性资产 | T181: 闲置 | U181: 林芝市察隅县上察隅镇荣玉村股份经济合作社 | V181: 到户资产，保留的面积与数量个户不同，难以核顶具体株数
A182: 540425202012015 | B182: 察隅县 | C182: 5404252020120150001 | D182: 100m3蓄水池 | E182: 44228 | F182: 荣玉村 | G182: 座 | H182: 10 | I182: 1 | J182: 184500 | K182: 72262.5 | L182: 112237.5 | M182: 固定资产 | N182: 构筑物 | O182: 集体资产 | P182: 正常 | Q182: 在用 | R182: 出租 | S182: 经营性资产 | T182: 低效 | U182: 林芝市察隅县上察隅镇荣玉村股份经济合作社
A183: 540425202012015 | B183: 察隅县 | C183: 5404252020120150002 | D183: 茶苗 | E183: 44228 | F183: 荣玉村 | G183: 亩 | H183: 10 | I183: 936.78 | J183: 2598350 | K183: 1017687.1 | L183: 1580662.9 | M183: 生物资产 | N183: 林木 | O183: 集体资产 | P183: 损坏 | Q183: 在用 | R183: 出租 | S183: 经营性资产 | T183: 低效 | U183: 林芝市察隅县上察隅镇荣玉村股份经济合作社
A184: 540425202012015 | B184: 察隅县 | C184: 5404252020120150003 | D184: 铁丝网围栏 | E184: 44228 | F184: 荣玉村 | G184: 7684.07米 | H184: 10 | I184: 1 | J184: 667300 | K184: 261359.17 | L184: 405940.83 | M184: 固定资产 | N184: 构筑物 | O184: 集体资产 | P184: 损坏 | Q184: 在用 | R184: 出租 | S184: 经营性资产 | T184: 低效 | U184: 林芝市察隅县上察隅镇荣玉村股份经济合作社
A185: 540425202012015 | B185: 察隅县 | C185: 5404252020120150004 | D185: 大门 | E185: 44228 | F185: 荣玉村 | G185: 座 | H185: 10 | I185: 2 | J185: 14100 | K185: 5522.5 | L185: 8577.5 | M185: 固定资产 | N185: 构筑物 | O185: 集体资产 | P185: 损坏 | Q185: 在用 | R185: 出租 | S185: 经营性资产 | T185: 低效 | U185: 林芝市察隅县上察隅镇荣玉村股份经济合作社
A186: 540425202112021 | B186: 察隅县 | C186: 5404252021120210001 | D186: 茶叶粗加工厂坊 | E186: 44593 | F186: 荣玉村 | G186: 栋 | H186: 20 | I186: 1 | J186: 2617500 | K186: 381718.75 | L186: 2235781.2 | M186: 固定资产 | N186: 房屋建筑物 | O186: 集体资产 | P186: 正常 | Q186: 在用 | R186: 出租 | S186: 经营性资产 | T186: 低效 | U186: 林芝市察隅县上察隅镇荣玉村股份经济合作社 | V186: （含门卫室及配套）
A187: 540425201812008 | B187: 察隅县 | C187: 5404252018120080001 | D187: 茶苗 | E187: 43101 | F187: 荣玉村 | G187: 亩 | H187: 10 | I187: 174.94 | J187: 1435824 | K187: 1005076.8 | L187: 430747.2 | M187: 生物资产 | N187: 林木 | O187: 集体资产 | P187: 损坏 | Q187: 不再用 | R187: 已死亡 | S187: 经营性资产 | T187: 低效 | U187: 林芝市察隅县上察隅镇荣玉村股份经济合作社 | V187: 原有1236527株，182亩，因退耕还林仅剩下约40亩
A188: 540425202212025 | B188: 察隅县 | C188: 5404252022120250001 | D188: 50m³蓄水池 | E188: 45078 | F188: 本堆村 | G188: 座 | H188: 10 | I188: 1 | J188: 105400 | K188: 16688.33 | L188: 88711.67 | M188: 固定资产 | N188: 构筑物 | O188: 集体资产 | P188: 正常 | Q188: 在用 | R188: 出租 | S188: 经营性资产 | T188: 低效 | U188: 林芝市察隅县上察隅镇本堆村股份经济合作社
A189: 540425202212025 | B189: 察隅县 | C189: 5404252022120250002 | D189: 茶苗 | E189: 45078 | F189: 本堆村 | G189: 亩 | H189: 10 | I189: 315 | J189: 880750 | K189: 139452.08 | L189: 741297.92 | M189: 生物资产 | N189: 林木 | O189: 集体资产 | P189: 损坏 | Q189: 在用 | R189: 出租 | S189: 经营性资产 | T189: 低效 | U189: 林芝市察隅县上察隅镇本堆村股份经济合作社
A190: 540425202212025 | B190: 察隅县 | C190: 5404252022120250003 | D190: 铁丝网围栏 | E190: 45078 | F190: 本堆村 | G190: 2783.50米 | H190: 10 | I190: 1 | J190: 183700 | K190: 29085.83 | L190: 154614.17 | M190: 固定资产 | N190: 构筑物 | O190: 集体资产 | P190: 损坏 | Q190: 在用 | R190: 出租 | S190: 经营性资产 | T190: 低效 | U190: 林芝市察隅县上察隅镇本堆村股份经济合作社
A191: 540425202212025 | B191: 察隅县 | C191: 5404252022120250004 | D191: 大门 | E191: 45078 | F191: 本堆村 | G191: 座 | H191: 10 | I191: 2 | J191: 13500 | K191: 2137.5 | L191: 11362.5 | M191: 固定资产 | N191: 构筑物 | O191: 集体资产 | P191: 损坏 | Q191: 在用 | R191: 出租 | S191: 经营性资产 | T191: 低效 | U191: 林芝市察隅县上察隅镇本堆村股份经济合作社
A192: 540425201912012 | B192: 察隅县 | C192: 5404252019120120001 | D192: 10m3蓄水池 | E192: 43862 | F192: 本堆村 | G192: 座 | H192: 10 | I192: 2 | J192: 102600 | K192: 50445 | L192: 52155 | M192: 固定资产 | N192: 构筑物 | O192: 集体资产 | P192: 正常 | Q192: 在用 | R192: 出租 | S192: 经营性资产 | T192: 低效 | U192: 林芝市察隅县上察隅镇本堆村股份经济合作社
A193: 540425201912012 | B193: 察隅县 | C193: 5404252019120120002 | D193: 25m3蓄水池 | E193: 43862 | F193: 本堆村 | G193: 座 | H193: 10 | I193: 1 | J193: 79800 | K193: 39235 | L193: 40565 | M193: 固定资产 | N193: 构筑物 | O193: 集体资产 | P193: 正常 | Q193: 在用 | R193: 出租 | S193: 经营性资产 | T193: 低效 | U193: 林芝市察隅县上察隅镇本堆村股份经济合作社
A194: 540425201912012 | B194: 察隅县 | C194: 5404252019120120003 | D194: 铁丝围栏 | E194: 43862 | F194: 本堆村 | G194: 1455.71米 | H194: 10 | I194: 1 | J194: 126900 | K194: 62392.5 | L194: 64507.5 | M194: 固定资产 | N194: 构筑物 | O194: 集体资产 | P194: 损坏 | Q194: 在用 | R194: 出租 | S194: 经营性资产 | T194: 低效 | U194: 林芝市察隅县上察隅镇本堆村股份经济合作社
A195: 540425201912012 | B195: 察隅县 | C195: 5404252019120120004 | D195: 大门 | E195: 43862 | F195: 本堆村 | G195: 座 | H195: 10 | I195: 2 | J195: 9300 | K195: 4572.5 | L195: 4727.5 | M195: 固定资产 | N195: 构筑物 | O195: 集体资产 | P195: 损坏 | Q195: 在用 | R195: 出租 | S195: 经营性资产 | T195: 低效 | U195: 林芝市察隅县上察隅镇本堆村股份经济合作社
A196: 540425201912012 | B196: 察隅县 | C196: 5404252019120120005 | D196: 茶苗 | E196: 43862 | F196: 本堆村 | G196: 亩 | H196: 10 | I196: 135.73 | J196: 613620 | K196: 301696.5 | L196: 311923.5 | M196: 生物资产 | N196: 林木 | O196: 集体资产 | P196: 损坏 | Q196: 在用 | R196: 出租 | S196: 经营性资产 | T196: 低效 | U196: 林芝市察隅县上察隅镇本堆村股份经济合作社
A197: 540425201912013 | B197: 察隅县 | C197: 5404252019120130001 | D197: 25m3蓄水池 | E197: 43831 | F197: 本堆村 | G197: 座 | H197: 10 | I197: 1 | J197: 79800 | K197: 39900 | L197: 39900 | M197: 固定资产 | N197: 构筑物 | O197: 集体资产 | P197: 正常 | Q197: 不再用 | R197: 闲置 | S197: 经营性资产 | T197: 低效 | U197: 林芝市察隅县上察隅镇本堆村股份经济合作社
A198: 540425201912013 | B198: 察隅县 | C198: 5404252019120130002 | D198: 铁丝网围栏 | E198: 43831 | F198: 本堆村 | G198: 1455.71米 | H198: 10 | I198: 1 | J198: 126900 | K198: 63450 | L198: 63450 | M198: 固定资产 | N198: 构筑物 | O198: 集体资产 | P198: 损坏 | Q198: 在用 | R198: 出租 | S198: 经营性资产 | T198: 低效 | U198: 林芝市察隅县上察隅镇本堆村股份经济合作社
A199: 540425201912013 | B199: 察隅县 | C199: 5404252019120130003 | D199: 茶苗 | E199: 43831 | F199: 本堆村 | G199: 亩 | H199: 10 | I199: 108.85 | J199: 215355 | K199: 107677.5 | L199: 107677.5 | M199: 生物资产 | N199: 林木 | O199: 集体资产 | P199: 损坏 | Q199: 在用 | R199: 出租 | S199: 经营性资产 | T199: 低效 | U199: 林芝市察隅县上察隅镇本堆村股份经济合作社
... A218: 540425202216017 | B218: 察隅县 | C218: 54042520221601700012 | D218: 智能水肥一体机 | E218: 44562 | F218: 沙玛村 | G218: 台 | H218: 5 | I218: 2 | J218: 39200 | K218: 23520 | L218: 15680 | M218: 固定资产 | N218: 机器设备 | O218: 集体资产 | P218: 正常 | Q218: 在用 | R218: 出租 | S218: 经营性资产 | T218: 正常 | U218: 林芝市察隅县下察隅镇沙玛村股份经济合作社
A219: 540425201715002 | B219: 察隅县 | C219: 5404252017150020001 | D219: 猕猴桃 | E219: 42979 | F219: 京都村、宗古村、布巴村 | G219: 亩 | H219: 10 | I219: 956 | K219: 0 | L219: 0 | M219: 固定资产 | N219: 机器设备 | O219: 集体资产 | P219: 正常 | Q219: 在用 | R219: 出租 | S219: 经营性资产 | T219: 正常 | U219: 林芝市察隅县下察隅镇布巴村股份经济合作社、林芝市察隅县下察隅镇宗古村股份经济合作社、林芝市察隅县下察隅镇京都村股份经济合作社 | V219: 布巴村37000株、京都村24300株、宗古村23000株；无固定资产原值数据
A220: 540425201715002 | B220: 察隅县 | C220: 5404252017150020002 | D220: 值班室及大门 | E220: 42979 | F220: 京都村、宗古村、布巴村 | G220: 座 | H220: 20 | I220: 3 | K220: 0 | L220: 0 | M220: 固定资产 | N220: 机器设备 | O220: 集体资产 | P220: 正常 | Q220: 在用 | R220: 出租 | S220: 经营性资产 | T220: 正常 | U220: 林芝市察隅县下察隅镇布巴村股份经济合作社、林芝市察隅县下察隅镇宗古村股份经济合作社、林芝市察隅县下察隅镇京都村股份经济合作社 | V220: 布巴村37000株、京都村24300株、宗古村23000株；无固定资产原值数据
A221: 540425201715002 | B221: 察隅县 | C221: 5404252017150020003 | D221: 水池 | E221: 42979 | F221: 京都村、宗古村、布巴村 | G221: 座 | H221: 10 | I221: 7 | K221: 0 | L221: 0 | M221: 固定资产 | N221: 机器设备 | O221: 集体资产 | P221: 正常 | Q221: 在用 | R221: 出租 | S221: 经营性资产 | T221: 正常 | U221: 林芝市察隅县下察隅镇布巴村股份经济合作社、林芝市察隅县下察隅镇宗古村股份经济合作社、林芝市察隅县下察隅镇京都村股份经济合作社 | V221: 布巴村37000株、京都村24300株、宗古村23000株；无固定资产原值数据
A222: 540425201916010 | B222: 察隅县 | C222: 5404252019160100001 | D222: 240㎡温室大棚 | E222: 43831 | F222: 竹巴村 | G222: 座 | H222: 10 | I222: 6 | J222: 346800 | K222: 173400 | L222: 173400 | M222: 固定资产 | N222: 构筑物 | O222: 集体资产 | P222: 正常 | Q222: 在用 | R222: 出租 | S222: 经营性资产 | T222: 正常 | U222: 林芝市察隅县上察隅镇竹巴村股份经济合作社
A223: 540425201919026 | B223: 察隅县 | C223: 5404252019190260001 | D223: 蓄水池 | E223: 43922 | F223: 荣玉村 | G223: 座 | H223: 10 | I223: 1 | J223: 45800 | K223: 21755 | L223: 24045 | M223: 固定资产 | N223: 构筑物 | O223: 集体资产 | P223: 正常 | Q223: 在用 | R223: 出租 | S223: 经营性资产 | T223: 正常 | U223: 林芝市察隅县上察隅镇荣玉村股份经济合作社
A224: 540425201919026 | B224: 察隅县 | C224: 5404252019190260002 | D224: 花椒 | E224: 43922 | F224: 荣玉村 | G224: 珠 | H224: 10 | I224: 6066 | J224: 289500 | K224: 289500 | L224: 0 | M224: 生物资产 | N224: 林木 | O224: 集体资产 | P224: 损毁 | Q224: 在用 | R224: 出租 | S224: 经营性资产 | T224: 低效 | U224: 林芝市察隅县上察隅镇荣玉村股份经济合作社
A225: 540425201919026 | B225: 察隅县 | C225: 5404252019190260003 | D225: 铁丝网围栏 | E225: 43922 | F225: 荣玉村 | G225: 786米 | H225: 10 | I225: 1 | J225: 69200 | K225: 32870 | L225: 36330 | M225: 固定资产 | N225: 构筑物 | O225: 集体资产 | P225: 损坏 | Q225: 在用 | R225: 出租 | S225: 经营性资产 | T225: 低效 | U225: 林芝市察隅县上察隅镇荣玉村股份经济合作社
...

Sheet 附件6
A1: 西藏自治区察隅县低效、闲置项目资产台账 （截至2026年6月20日数据）
A2: 项目编号 | B2: 项目县区 | C2: 资产编号 | D2: 资产 名称 | E2: 构（购）建时间 （必填年月） | F2: 坐落或置放位置 | G2: 资产 型号 | H2: 预计使用年限（自构建时间起预计能够使用的年限数） | I2: 资产个数 | J2: 资产原值（元） | K2: 资产累计折旧（摊销）（元） | L2: 资产净值（元） | M2: 资产形态 | N2: 具体形态 | O2: 资产 属性 | P2: 资产 状态 | Q2: 资产使用情况 | R2: 资产 类别 | S2: 资产类别 | T2: 经营性资产运营情况 | U2: 资产所有权 （资产盘活责任主体） 主体名称 | V2: 资产盘活措施 | W2: 是否完成盘活 | X2: 资产完成盘活时间 | Y2: 备注
A3: 填表说明：与表2项目编号一致 | C3: 根据指南编码规则对资产进行编号 | D3: 按形成的具体资产名称填写，不同资产应分行填写 | E3: 例：2018.01 | H3: 例：10（即为该资产预计可使用时间为10年） | J3: 保留2位小数 | K3: 统计时间为截止2024年12月31日 （权益类资产、消耗性生物资产、公益性生物资产不填） 保留2位小数 | L3: 统计时间为截止2024年12月31日 保留2位小数 | M3: 在“固定资产、生物资产、权益类资产、其他资产”中选择 | N3: 在“房屋建筑物、构筑物、机器设备、车辆、办公用具家具、牲畜（禽）、林木、股权资产、债权资产、低值易耗品、无形资产”中选择 | O3: 在“国有资产、集体资产”中选择 | P3: 在“正常、损坏、损毁”中选择 | Q3: 根据实际情况填写“在用/不在用” | R3: 在“自用、出租、存栏、在培、已消耗、已出售、已死亡、闲置、损毁、拆除、待维修、盘亏等”中选择 | S3: 在“经营性资产、公益性资产”中选择 | T3: 在“低效、闲置”中选择 | W3: 填写“是/否” | X3: 例：2025.09.30
A4: 540425201908007 | B4: 察隅县 | C4: 54042520190800710001 | D4: 鸡舍 | E4: 43709 | F4: 扎拉村 | G4: 栋 | H4: 20 | I4: 1 | J4: 273400 | K4: 72906.67 | L4: 200493.33 | M4: 固定资产 | N4: 房屋建筑物 | O4: 集体资产 | P4: 正常 | Q4: 在用 | R4: 出租 | S4: 经营性资产 | T4: 闲置 | U4: 林芝市察隅县竹瓦根镇扎拉村股份经济合作社 | W4: 否
A5: 540425201908007 | B5: 察隅县 | C5: 54042520190800710002 | D5: 喂食槽 | E5: 43709 | F5: 扎拉村 | G5: 个 | H5: 5 | I5: 1 | J5: 400 | K5: 400 | L5: 0 | M5: 固定资产 | N5: 机器设备 | O5: 集体资产 | P5: 正常 | Q5: 在用 | R5: 出租 | S5: 经营性资产 | T5: 闲置 | U5: 林芝市察隅县竹瓦根镇扎拉村股份经济合作社 | W5: 否
A6: 540425201908007 | B6: 察隅县 | C6: 54042520190800710003 | D6: 喂食槽 | E6: 43709 | F6: 扎拉村 | G6: 个 | H6: 5 | I6: 1 | J6: 400 | K6: 400 | L6: 0 | M6: 固定资产 | N6: 机器设备 | O6: 集体资产 | P6: 正常 | Q6: 在用 | R6: 出租 | S6: 经营性资产 | T6: 闲置 | U6: 林芝市察隅县竹瓦根镇扎拉村股份经济合作社 | W6: 否
A7: 540425201908007 | B7: 察隅县 | C7: 54042520190800710004 | D7: 喂食槽 | E7: 43709 | F7: 扎拉村 | G7: 个 | H7: 5 | I7: 1 | J7: 400 | K7: 400 | L7: 0 | M7: 固定资产 | N7: 机器设备 | O7: 集体资产 | P7: 正常 | Q7: 在用 | R7: 出租 | S7: 经营性资产 | T7: 闲置 | U7: 林芝市察隅县竹瓦根镇扎拉村股份经济合作社 | W7: 否
A8: 540425201908007 | B8: 察隅县 | C8: 54042520190800720005 | D8: 藏鸡苗 | E8: 43709 | F8: 扎拉村 | G8: 只 | H8: 3 | I8: 200 | J8: 7000 | K8: 7000 | L8: 0 | M8: 生物资产 | N8: 牲畜（禽） | O8: 集体资产 | P8: 损毁 | Q8: 不在用 | R8: 已死亡 | S8: 经营性资产 | T8: 闲置 | U8: 林芝市察隅县竹瓦根镇扎拉村股份经济合作社 | W8: 否
A9: 540425201908007 | B9: 察隅县 | C9: 54042520190800720205 | D9: 成年藏鸡 | E9: 43709 | F9: 扎拉村 | G9: 只 | H9: 3 | I9: 92 | J9: 18400 | K9: 18400 | L9: 0 | M9: 生物资产 | N9: 牲畜（禽） | O9: 集体资产 | P9: 损毁 | Q9: 不在用 | R9: 已死亡 | S9: 经营性资产 | T9: 闲置 | U9: 林芝市察隅县竹瓦根镇扎拉村股份经济合作社 | W9: 否
A10: 540425201807010 | B10: 察隅县 | C10: 54042520180701010001 | D10: 猪舍 | E10: 43952 | F10: 京都村 | G10: 栋 | H10: 20 | I10: 1 | J10: 191100 | K10: 44590 | L10: 146510 | M10: 固定资产 | N10: 房屋建筑物 | O10: 集体资产 | P10: 正常 | Q10: 在用 | R10: 出租 | S10: 经营性资产 | T10: 低效 | U10: 林芝市察隅县下察隅镇京都村股份经济合作社 | W10: 否
A11: 540425201807010 | B11: 察隅县 | C11: 54042520180701010002 | D11: 饲料库房加工坊 | E11: 43952 | F11: 京都村 | G11: 栋 | H11: 20 | I11: 1 | J11: 70600 | K11: 16473.33 | L11: 54126.67 | M11: 固定资产 | N11: 房屋建筑物 | O11: 集体资产 | P11: 正常 | Q11: 在用 | R11: 出租 | S11: 经营性资产 | T11: 低效 | U11: 林芝市察隅县下察隅镇京都村股份经济合作社 | W11: 否
A12: 540425201807010 | B12: 察隅县 | C12: 54042520180701010003 | D12: 饲料加工机 | E12: 43952 | F12: 京都村 | G12: 台 | H12: 5 | I12: 1 | J12: 10000 | K12: 9333.33 | L12: 666.67 | M12: 固定资产 | N12: 机器设备 | O12: 集体资产 | P12: 损坏 | Q12: 不在用 | R12: 损毁 | S12: 经营性资产 | T12: 闲置 | U12: 林芝市察隅县下察隅镇京都村股份经济合作社 | W12: 否
A13: 540425201807010 | B13: 察隅县 | C13: 54042520180701010004 | D13: 柴油发电机 | E13: 43952 | F13: 京都村 | G13: 台 | H13: 5 | I13: 1 | J13: 7800 | K13: 7280 | L13: 520 | M13: 固定资产 | N13: 机器设备 | O13: 集体资产 | P13: 损坏 | Q13: 不在用 | R13: 闲置 | S13: 经营性资产 | T13: 闲置 | U13: 林芝市察隅县下察隅镇京都村股份经济合作社 | W13: 否
A14: 540425201807010 | B14: 察隅县 | C14: 54042520180701020005 | D14: 藏香猪 | E14: 43952 | F14: 京都村 | G14: 只 | H14: 3 | I14: 63 | J14: 220500 | K14: 220500 | L14: 0 | M14: 生物资产 | N14: 牲畜（禽） | O14: 集体资产 | P14: 损坏 | Q14: 不在用 | R14: 已死亡 | S14: 经营性资产 | T14: 闲置 | U14: 林芝市察隅县下察隅镇京都村股份经济合作社 | W14: 否
A15: 540425201819017 | B15: 察隅县 | C15: 54042520181901710001 | D15: 松茸加工坊 | E15: 43101 | F15: 古井村 | G15: 栋 | H15: 20 | I15: 1 | J15: 300000 | K15: 105000 | L15: 195000 | M15: 固定资产 | N15: 房屋建筑物 | O15: 集体资产 | P15: 正常 | Q15: 在用 | R15: 出租 | S15: 经营性资产 | T15: 低效 | U15: 林芝市察隅县古玉乡古井村股份经济合作社 | W15: 否
... A128: 540425201907013 | B128: 察隅县 | C128: 5404252019070130001 | D128: 饲料仓库 | E128: 43831 | F128: 自更村 | G128: 栋 | H128: 20 | I128: 1 | J128: 300000 | K128: 75000 | L128: 225000 | M128: 固定资产 | N128: 房屋建筑物 | O128: 集体资产 | P128: 正常 | Q128: 不再用 | R128: 闲置 | S128: 经营性资产 | T128: 闲置 | U128: 林芝市察隅县下察隅镇自更村股份经济合作社 | W128: 否
A129: 540425202019029 | B129: 察隅县 | C129: 5404252020190290001 | D129: 灵芝 | E129: 43800 | F129: 龙布村 | G129: 亩 | H129: 10 | I129: 8 | J129: 500000 | K129: - | L129: - | M129: 生物资产 | N129: 林木 | O129: 集体资产 | P129: 正常 | Q129: 不再用 | R129: 闲置 | S129: 经营性资产 | T129: 闲置 | U129: 林芝市察隅县察瓦龙乡龙布村股份经济合作社 | W129: 否
A130: 540425202019029 | B130: 察隅县 | C130: 5404252020190290001 | D130: 灵芝 | E130: 44166 | F130: 龙布村 | G130: 亩 | H130: 10 | I130: 8 | J130: 500000 | K130: - | L130: - | M130: 生物资产 | N130: 林木 | O130: 集体资产 | P130: 正常 | Q130: 不再用 | R130: 闲置 | S130: 经营性资产 | T130: 闲置 | U130: 林芝市察隅县察瓦龙乡龙布村股份经济合作社 | W130: 否
A131: 540425201811001 | B131: 察隅县 | C131: 5404252018110010001 | D131: 重楼 | E131: 43435 | F131: 龙布村 | G131: 株 | H131: 10 | I131: 280000 | J131: 280000 | K131: 280000 | L131: 0 | M131: 生物资产 | N131: 林木 | O131: 集体资产 | P131: 损毁 | Q131: 不再用 | R131: 已死亡 | S131: 经营性资产 | T131: 闲置 | U131: 林芝市察隅县察瓦龙乡龙布村股份经济合作社 | W131: 否
A132: 540425201807011 | B132: 察隅县 | C132: 54042520180701110001 | D132: 猪舍 | E132: 2019.11 | F132: 俄玉村 | G132: 105.7㎡ | H132: 20 | I132: 1 | J132: 71137.23 | K132: 18377.12 | L132: 52760.11 | M132: 固定资产 | N132: 房屋建筑物 | O132: 集体资产 | P132: 正常 | Q132: 不在用 | R132: 闲置 | S132: 经营性资产 | T132: 闲置 | U132: 林芝市察隅县古拉乡俄玉村股份经济合作社 | W132: 否
A133: 540425201807011 | B133: 察隅县 | C133: 54042520180701110002 | D133: 育种室和隔离室 | E133: 2019.11 | F133: 俄玉村 | G133: 164.16㎡ | H133: 20 | I133: 1 | J133: 126916.49 | K133: 32786.76 | L133: 94129.73 | M133: 固定资产 | N133: 房屋建筑物 | O133: 集体资产 | P133: 正常 | Q133: 不在用 | R133: 闲置 | S133: 经营性资产 | T133: 闲置 | U133: 林芝市察隅县古拉乡俄玉村股份经济合作社 | W133: 否
A134: 540425201807011 | B134: 察隅县 | C134: 54042520180701110003 | D134: 仓库及管理用房 | E134: 2019.11 | F134: 俄玉村 | G134: 64.84㎡ | H134: 20 | I134: 1 | J134: 111146.28 | K134: 28712.79 | L134: 82433.49 | M134: 固定资产 | N134: 房屋建筑物 | O134: 集体资产 | P134: 正常 | Q134: 不在用 | R134: 闲置 | S134: 经营性资产 | T134: 闲置 | U134: 林芝市察隅县古拉乡俄玉村股份经济合作社 | W134: 否
A135: 540425201807011 | B135: 察隅县 | C135: 54042520180701110004 | D135: 围墙 | E135: 2019.11 | F135: 俄玉村 | G135: 200m | H135: 10 | I135: 1 | J135: 64000 | K135: 33066.67 | L135: 30933.33 | M135: 固定资产 | N135: 构筑物 | O135: 集体资产 | P135: 正常 | Q135: 不在用 | R135: 闲置 | S135: 经营性资产 | T135: 闲置 | U135: 林芝市察隅县古拉乡俄玉村股份经济合作社 | W135: 否
A136: 540425201807011 | B136: 察隅县 | C136: 54042520180701120001 | D136: 藏香猪 | E136: 2019.11 | F136: 俄玉村 | G136: 头 | H136: 3 | I136: 104 | J136: 102000 | L136: 0 | M136: 生物资产 | N136: 牲畜（禽） | O136: 集体资产 | P136: 损毁 | Q136: 不在用 | R136: 已死亡 | S136: 经营性资产 | T136: 闲置 | U136: 林芝市察隅县古拉乡俄玉村股份经济合作社 | W136: 否
A137: 540425201917017 | B137: 察隅县 | C137: 54042520191701710001 | D137: 家庭旅馆 | E137: 2015.12 | F137: 觉布如村 | G137: 栋 | H137: 20 | I137: 1 | J137: 600000 | K137: 272500 | L137: 327500 | M137: 固定资产 | N137: 房屋建筑物 | O137: 集体资产 | P137: 正常 | Q137: 不在用 | R137: 闲置 | S137: 经营性资产 | T137: 闲置 | U137: 林芝市察隅县古拉乡觉布如村股份经济合作社 | W137: 否
A138: 540425202120032 | B138: 察隅县 | C138: 54042520212003320002 | D138: 石榴（存活） | E138: 2021.12 | F138: 则巴村 | G138: 株 | H138: 10 | I138: 1384 | J138: 285898.97 | K138: 88152.18 | L138: 197746.79 | M138: 生物资产 | N138: 林木 | O138: 集体资产 | P138: 正常 | Q138: 不在用 | R138: 闲置 | S138: 经营性资产 | T138: 低效 | U138: 林芝市察隅县古拉乡则巴村股份经济合作社 | W138: 否
A139: 540425202120032 | B139: 察隅县 | C139: 54042520212003310001 | D139: 灌溉工程 | E139: 2021.12 | F139: 则巴村 | G139: 项 | H139: 10 | I139: 1 | J139: 374135.07 | K139: 115358.31 | L139: 258776.76 | M139: 固定资产 | N139: 构筑物 | O139: 集体资产 | P139: 正常 | Q139: 不在用 | R139: 闲置 | S139: 经营性资产 | T139: 低效 | U139: 林芝市察隅县古拉乡则巴村股份经济合作社 | W139: 否
A140: 540425202120032 | B140: 察隅县 | C140: 54042520212003310002 | D140: 网围栏 | E140: 2021.12 | F140: 则巴村 | G140: 2199m | H140: 10 | I140: 1 | J140: 195639.97 | K140: 60322.32 | L140: 135317.65 | M140: 固定资产 | N140: 构筑物 | O140: 集体资产 | P140: 正常 | Q140: 不在用 | R140: 闲置 | S140: 经营性资产 | T140: 低效 | U140: 林芝市察隅县古拉乡则巴村股份经济合作社 | W140: 否
A141: 540425201919022 | B141: 察隅县 | C141: 54042520191902210001 | D141: 液压榨油机 | E141: 2019.7 | F141: 则巴村 | G141: 台 | H141: 10 | I141: 1 | J141: 28800 | K141: 15840 | L141: 12960 | M141: 固定资产 | N141: 机器设备 | O141: 集体资产 | P141: 损坏 | Q141: 不在用 | R141: 损毁 | S141: 经营性资产 | T141: 闲置 | U141: 林芝市察隅县古拉乡则巴村股份经济合作社 | W141: 否
A142: 540425201919022 | B142: 察隅县 | C142: 54042520191902210002 | D142: 剥壳机 | E142: 2019.7 | F142: 则巴村 | G142: 台 | H142: 10 | I142: 2 | J142: 15000 | K142: 8250 | L142: 6750 | M142: 固定资产 | N142: 机器设备 | O142: 集体资产 | P142: 正常 | Q142: 不在用 | R142: 闲置 | S142: 经营性资产 | T142: 闲置 | U142: 林芝市察隅县古拉乡则巴村股份经济合作社 | W142: 否
A143: 540425201919022 | B143: 察隅县 | C143: 54042520191902210003 | D143: 分拣机 | E143: 2019.7 | F143: 则巴村 | G143: 台 | H143: 10 | I143: 1 | J143: 14500 | K143: 7975 | L143: 6525 | M143: 固定资产 | N143: 机器设备 | O143: 集体资产 | P143: 正常 | Q143: 不在用 | R143: 闲置 | S143: 经营性资产 | T143: 闲置 | U143: 林芝市察隅县古拉乡则巴村股份经济合作社 | W143: 否
A144: 540425201919022 | B144: 察隅县 | C144: 54042520191902210004 | D144: 烘干机 | E144: 2019.7 | F144: 则巴村 | G144: 台 | H144: 10 | I144: 1 | J144: 13500 | K144: 7425 | L144: 6075 | M144: 固定资产 | N144: 机器设备 | O144: 集体资产 | P144: 正常 | Q144: 不在用 | R144: 闲置 | S144: 经营性资产 | T144: 闲置 | U144: 林芝市察隅县古拉乡则巴村股份经济合作社 | W144: 否
A145: 540425201919022 | B145: 察隅县 | C145: 54042520191902210005 | D145: 过滤器 | E145: 2019.7 | F145: 则巴村 | G145: 台 | H145: 10 | I145: 2 | J145: 24000 | K145: 13200 | L145: 10800 | M145: 固定资产 | N145: 机器设备 | O145: 集体资产 | P145: 正常 | Q145: 不在用 | R145: 闲置 | S145: 经营性资产 | T145: 闲置 | U145: 林芝市察隅县古拉乡则巴村股份经济合作社 | W145: 否
A146: 540425201919022 | B146: 察隅县 | C146: 54042520191902210006 | D146: 核桃粉碎机 | E146: 2019.7 | F146: 则巴村 | G146: 台 | H146: 10 | I146: 1 | J146: 12500 | K146: 6875 | L146: 5625 | M146: 固定资产 | N146: 机器设备 | O146: 集体资产 | P146: 正常 | Q146: 不在用 | R146: 闲置 | S146: 经营性资产 | T146: 闲置 | U146: 林芝市察隅县古拉乡则巴村股份经济合作社 | W146: 否
A147: 540425201919022 | B147: 察隅县 | C147: 54042520191902210007 | D147: 包装机 | E147: 2019.7 | F147: 则巴村 | G147: 台 | H147: 10 | I147: 2 | J147: 19000 | K147: 10450 | L147: 8550 | M147: 固定资产 | N147: 机器设备 | O147: 集体资产 | P147: 正常 | Q147: 不在用 | R147: 闲置 | S147: 经营性资产 | T147: 闲置 | U147: 林芝市察隅县古拉乡则巴村股份经济合作社 | W147: 否
A148: 540425201919022 | B148: 察隅县 | C148: 54042520191902210008 | D148: 变压器 | E148: 2019.7 | F148: 则巴村 | G148: 台 | H148: 10 | I148: 1 | J148: 21400 | K148: 11770 | L148: 9630 | M148: 固定资产 | N148: 机器设备 | O148: 集体资产 | P148: 正常 | Q148: 不在用 | R148: 闲置 | S148: 经营性资产 | T148: 闲置 | U148: 林芝市察隅县古拉乡则巴村股份经济合作社 | W148: 否
... A194: 540425201907016 | B194: 察隅县 | C194: 54042520190701610001 | D194: 猪舍 | E194: 2020.03 | F194: 扎那村 | G194: 栋 | H194: 20 | I194: 1 | J194: 366700 | K194: 177238.33 | L194: 189461.67 | M194: 固定资产 | N194: 房屋建筑物 | O194: 集体资产 | P194: 正常 | Q194: 不在用 | R194: 闲置 | S194: 经营性资产 | T194: 闲置 | U194: 林芝市察隅县察瓦龙乡扎那村股份经济合作社 | W194: 否
A195: 540425201907016 | B195: 察隅县 | C195: 54042520190701620001 | D195: 藏香猪 | E195: 2020.03 | F195: 扎那村 | G195: 头 | H195: 3 | I195: 33 | J195: 115500 | L195: 0 | M195: 生物资产 | N195: 牲畜（禽） | O195: 集体资产 | P195: 正常 | Q195: 不在用 | R195: 闲置 | S195: 经营性资产 | T195: 闲置 | U195: 林芝市察隅县察瓦龙乡扎那村股份经济合作社 | W195: 否
A196: 540425201907016 | B196: 察隅县 | C196: 54042520190701610002 | D196: 饲料加工机 | E196: 2020.03 | F196: 扎那村 | G196: 台 | H196: 10 | I196: 1 | J196: 10000 | K196: 4833.33 | L196: 5166.67 | M196: 固定资产 | N196: 机器设备 | O196: 集体资产 | P196: 正常 | Q196: 不在用 | R196: 闲置 | S196: 经营性资产 | T196: 闲置 | U196: 林芝市察隅县察瓦龙乡扎那村股份经济合作社 | W196: 否
A197: 540425201907016 | B197: 察隅县 | C197: 54042520190701610003 | D197: 柴油发电机 | E197: 2020.03 | F197: 扎那村 | G197: 台 | H197: 10 | I197: 1 | J197: 7800 | K197: 3770 | L197: 4030 | M197: 固定资产 | N197: 机器设备 | O197: 集体资产 | P197: 正常 | Q197: 不在用 | R197: 闲置 | S197: 经营性资产 | T197: 闲置 | U197: 林芝市察隅县察瓦龙乡扎那村股份经济合作社 | W197: 否
A198: 540425201820016 | B198: 察隅县 | C198: 54042520182001620001 | D198: 石榴（存活） | E198: 2019.03 | F198: 龙布村 | G198: 珠 | H198: 10 | I198: 3622 | J198: 362240 | K198: 211306.7 | L198: 150933.3 | M198: 生物资产 | N198: 林木 | O198: 集体资产 | P198: 正常 | Q198: 不在用 | R198: 闲置 | S198: 经营性资产 | T198: 闲置 | U198: 林芝市察隅县察瓦龙乡龙布村股份经济合作社 | W198: 否
A199: 540425201820016 | B199: 察隅县 | C199: 54042520182001620002 | D199: 石榴（未存活） | E199: 2019.03 | F199: 龙布村 | G199: 珠 | H199: 10 | I199: 5434 | J199: 543360 | K199: 543360 | L199: 0 | M199: 生物资产 | N199: 林木 | O199: 集体资产 | P199: 损毁 | Q199: 不在用 | R199: 已死亡 | S199: 经营性资产 | T199: 闲置 | U199: 林芝市察隅县察瓦龙乡龙布村股份经济合作社 | W199: 否

Sheet 附件9
A1: 西藏自治区察隅县帮扶产业项目待处置资产台账 （截至2026年6月20日数据）
A2: 项目编号 | B2: 项目县区 | C2: 资产 编号 | D2: 资产 名称 | E2: 构（购）建时间 （必填年月） | F2: 坐落或置放位置 | G2: 资产 型号 | H2: 预计使用年限（自构建时间起预计能够使用的年限数） | I2: 资产 个数 | J2: 资产原值（元） | K2: 资产累计折旧（摊销）（元） | L2: 资产净值（元） | M2: 资产形态 | N2: 具体形态 | O2: 资产属性 | P2: 资产状态 | Q2: 资产使用情况 | R2: 资产 类别 | S2: 资产类别 | T2: 经营性资产运营情况 | U2: 资产所有权主体（处置责任主体）名称 | V2: 资产处置方法 | W2: 资产处置流程是否执行到位 | X2: 资产完成处置时间 | Y2: 备注
A3: 填表说明：与表2项目编号一致 | C3: 根据指南编码规则对资产进行编号 | D3: 按形成的具体资产名称填写，不同资产应分行填写 | E3: 例：2018.01 | H3: 例：10（即为该资产预计可使用时间为10年） | J3: 保留2位小数 | K3: 统计时间为截止2024年12月31日 （权益类资产、消耗性生物资产、公益性生物资产不填） 保留2位小数 | L3: 统计时间为截止2024年12月31日 （保留2位小数） | M3: 在“固定资产、生物资产、权益类资产、其他资产”中选择 | N3: 在“房屋建筑物、构筑物、机器设备、车辆、办公用具家具、牲畜（禽）、林木、股权资产、债权资产、低值易耗品、无形资产”中选择 | O3: 在“国有资产、集体资产”中选择 | P3: 仅为“待处置” | Q3: 根据实际情况填写“在用/不在用” | R3: 在“自用、出租、存栏、在培、已消耗、已出售、已死亡、闲置、损毁、拆除、待维修、盘亏等”中选择 | S3: 在“经营性资产、公益性资产”中选择 | T3: 在“低效、闲置”中选择 | W3: 填写“是/否” | X3: 如：2025.09.30
A4: 540425201912012 | B4: 察隅县 | C4: 5404252019120120004 | D4: 大门 | E4: 43862 | F4: 本堆村 | G4: 座 | H4: 10 | I4: 2 | J4: 9300 | K4: 4572.5 | L4: 4727.5 | M4: 固定资产 | N4: 构筑物 | O4: 集体资产 | P4: 损坏 | Q4: 在用 | R4: 出租 | S4: 经营性资产 | T4: 低效 | U4: 林芝市察隅县上察隅镇本堆村股份经济合作社 | W4: 否
A5: 540425201912012 | B5: 察隅县 | C5: 5404252019120120005 | D5: 茶苗 | E5: 43862 | F5: 本堆村 | G5: 株 | H5: 10 | I5: 277914 | J5: 613620 | K5: 301696.5 | L5: 311923.5 | M5: 生物资产 | N5: 林木 | O5: 集体资产 | P5: 损坏 | Q5: 在用 | R5: 出租 | S5: 经营性资产 | T5: 低效 | U5: 林芝市察隅县上察隅镇本堆村股份经济合作社 | W5: 否
A6: 540425201912013 | B6: 察隅县 | C6: 5404252019120130001 | D6: 25m3蓄水池 | E6: 43831 | F6: 本堆村 | G6: 座 | H6: 10 | I6: 1 | J6: 79800 | K6: 39900 | L6: 39900 | M6: 固定资产 | N6: 构筑物 | O6: 集体资产 | P6: 正常 | Q6: 不再用 | R6: 闲置 | S6: 经营性资产 | T6: 低效 | U6: 林芝市察隅县上察隅镇本堆村股份经济合作社 | W6: 否
A7: 540425201912013 | B7: 察隅县 | C7: 5404252019120130002 | D7: 铁丝网围栏 | E7: 43831 | F7: 本堆村 | G7: 1455.71米 | H7: 10 | I7: 1 | J7: 126900 | K7: 63450 | L7: 63450 | M7: 固定资产 | N7: 构筑物 | O7: 集体资产 | P7: 损坏 | Q7: 在用 | R7: 出租 | S7: 经营性资产 | T7: 低效 | U7: 林芝市察隅县上察隅镇本堆村股份经济合作社 | W7: 否
A8: 540425201912013 | B8: 察隅县 | C8: 5404252019120130003 | D8: 茶苗 | E8: 43831 | F8: 本堆村 | G8: 株 | H8: 10 | I8: 358925 | J8: 215355 | K8: 107677.5 | L8: 107677.5 | M8: 生物资产 | N8: 林木 | O8: 集体资产 | P8: 损坏 | Q8: 在用 | R8: 出租 | S8: 经营性资产 | T8: 低效 | U8: 林芝市察隅县上察隅镇本堆村股份经济合作社 | W8: 否
A9: 540425201919026 | B9: 察隅县 | C9: 5404252019190260002 | D9: 花椒 | E9: 43922 | F9: 荣玉村 | G9: 珠 | H9: 10 | I9: 6066 | J9: 289500 | K9: 289500 | L9: 0 | M9: 生物资产 | N9: 林木 | O9: 集体资产 | P9: 损毁 | Q9: 在用 | R9: 出租 | S9: 经营性资产 | T9: 低效 | U9: 林芝市察隅县上察隅镇荣玉村股份经济合作社 | W9: 否
A10: 540425201919026 | B10: 察隅县 | C10: 5404252019190260003 | D10: 铁丝网围栏 | E10: 43922 | F10: 荣玉村 | G10: 786米 | H10: 10 | I10: 1 | J10: 69200 | K10: 32870 | L10: 36330 | M10: 固定资产 | N10: 构筑物 | O10: 集体资产 | P10: 损坏 | Q10: 在用 | R10: 出租 | S10: 经营性资产 | T10: 低效 | U10: 林芝市察隅县上察隅镇荣玉村股份经济合作社 | W10: 否
A11: 540425201819013 | B11: 察隅县 | C11: 5404252018190130001 | D11: 石斛 | E11: 43435 | F11: 西巴村 | G11: 丛 | H11: 10 | I11: 60000 | J11: 450000 | K11: 273750 | L11: 176250 | M11: 固定资产 | N11: 林木 | O11: 集体资产 | P11: 损坏 | Q11: 在用 | R11: 出租 | S11: 经营性资产 | T11: 低效 | U11: 林芝市察隅县上察隅镇西巴村股份经济合作社 | W11: 否
A12: 540425201919023 | B12: 察隅县 | C12: 5404252019190230001 | D12: 秧耙生产车间 | E12: 43862 | F12: 迟巴村 | G12: 栋 | H12: 20 | I12: 1 | J12: 1667000 | K12: 409804.17 | L12: 1257195.8 | M12: 固定资产 | N12: 房屋建筑物 | O12: 集体资产 | P12: 正常 | Q12: 不再用 | R12: 闲置 | S12: 经营性资产 | T12: 闲置 | U12: - | W12: 否
A13: 540425201919023 | B13: 察隅县 | C13: 5404252019190230002 | D13: 石磨机 | E13: 43862 | F13: 迟巴村 | G13: 台 | H13: 5 | I13: 2 | J13: 160000 | K13: 160000 | L13: 0 | M13: 固定资产 | N13: 机器设备 | O13: 集体资产 | P13: 损毁 | Q13: 不再用 | R13: 损毁 | S13: 经营性资产 | T13: 闲置 | U13: - | W13: 否
A14: 540425201919023 | B14: 察隅县 | C14: 5404252019190230003 | D14: 混合机 | E14: 43862 | F14: 迟巴村 | G14: 台 | H14: 5 | I14: 1 | J14: 81000 | K14: 81000 | L14: 0 | M14: 固定资产 | N14: 机器设备 | O14: 集体资产 | P14: 损毁 | Q14: 不再用 | R14: 损毁 | S14: 经营性资产 | T14: 闲置 | U14: - | W14: 否
A15: 540425201919023 | B15: 察隅县 | C15: 5404252019190230004 | D15: 脱皮机 | E15: 43862 | F15: 迟巴村 | G15: 台 | H15: 5 | I15: 1 | J15: 60000 | K15: 60000 | L15: 0 | M15: 固定资产 | N15: 机器设备 | O15: 集体资产 | P15: 损毁 | Q15: 不再用 | R15: 损毁 | S15: 经营性资产 | T15: 闲置 | U15: - | W15: 否
... A27: 540425201907013 | B27: 察隅县 | C27: 5404252019070130001 | D27: 饲料仓库 | E27: 43831 | F27: 自更村 | G27: 栋 | H27: 20 | I27: 1 | J27: 300000 | K27: 75000 | L27: 225000 | M27: 固定资产 | N27: 房屋建筑物 | O27: 集体资产 | P27: 正常 | Q27: 不再用 | R27: 闲置 | S27: 经营性资产 | T27: 闲置 | U27: 林芝市察隅县下察隅镇自更村股份经济合作社 | W27: 否
A28: 540425202019029 | B28: 察隅县 | C28: 5404252020190290001 | D28: 灵芝 | E28: 43800 | F28: 龙布村 | G28: 亩 | H28: 10 | I28: 8 | J28: 500000 | K28: - | L28: - | M28: 生物资产 | N28: 林木 | O28: 集体资产 | P28: 正常 | Q28: 不再用 | R28: 闲置 | S28: 经营性资产 | T28: 闲置 | U28: 林芝市察隅县察瓦龙乡龙布村股份经济合作社 | W28: 否
A29: 540425202019029 | B29: 察隅县 | C29: 5404252020190290001 | D29: 灵芝 | E29: 44166 | F29: 龙布村 | G29: 亩 | H29: 10 | I29: 8 | J29: 500000 | K29: - | L29: - | M29: 生物资产 | N29: 林木 | O29: 集体资产 | P29: 正常 | Q29: 不再用 | R29: 闲置 | S29: 经营性资产 | T29: 闲置 | U29: 林芝市察隅县察瓦龙乡龙布村股份经济合作社 | W29: 否
A30: 540425201811001 | B30: 察隅县 | C30: 5404252018110010001 | D30: 重楼 | E30: 43435 | F30: 龙布村 | G30: 株 | H30: 10 | I30: 280000 | J30: 280000 | K30: 280000 | L30: 0 | M30: 生物资产 | N30: 林木 | O30: 集体资产 | P30: 损毁 | Q30: 不再用 | R30: 已死亡 | S30: 经营性资产 | T30: 闲置 | U30: 林芝市察隅县察瓦龙乡龙布村股份经济合作社 | W30: 否
A31: 540425201807011 | B31: 察隅县 | C31: 54042520180701110001 | D31: 猪舍 | E31: 2019.11 | F31: 俄玉村 | G31: 105.7㎡ | H31: 20 | I31: 1 | J31: 71137.23 | K31: 18377.12 | L31: 52760.11 | M31: 固定资产 | N31: 房屋建筑物 | O31: 集体资产 | P31: 正常 | Q31: 不在用 | R31: 闲置 | S31: 经营性资产 | T31: 闲置 | U31: 林芝市察隅县古拉乡俄玉村股份经济合作社 | W31: 否
A32: 540425201807011 | B32: 察隅县 | C32: 54042520180701110002 | D32: 育种室和隔离室 | E32: 2019.11 | F32: 俄玉村 | G32: 164.16㎡ | H32: 20 | I32: 1 | J32: 126916.49 | K32: 32786.76 | L32: 94129.73 | M32: 固定资产 | N32: 房屋建筑物 | O32: 集体资产 | P32: 正常 | Q32: 不在用 | R32: 闲置 | S32: 经营性资产 | T32: 闲置 | U32: 林芝市察隅县古拉乡俄玉村股份经济合作社 | W32: 否
A33: 540425201807011 | B33: 察隅县 | C33: 54042520180701110003 | D33: 仓库及管理用房 | E33: 2019.11 | F33: 俄玉村 | G33: 64.84㎡ | H33: 20 | I33: 1 | J33: 111146.28 | K33: 28712.79 | L33: 82433.49 | M33: 固定资产 | N33: 房屋建筑物 | O33: 集体资产 | P33: 正常 | Q33: 不在用 | R33: 闲置 | S33: 经营性资产 | T33: 闲置 | U33: 林芝市察隅县古拉乡俄玉村股份经济合作社 | W33: 否
A34: 540425201807011 | B34: 察隅县 | C34: 54042520180701110004 | D34: 围墙 | E34: 2019.11 | F34: 俄玉村 | G34: 200m | H34: 10 | I34: 1 | J34: 64000 | K34: 33066.67 | L34: 30933.33 | M34: 固定资产 | N34: 构筑物 | O34: 集体资产 | P34: 正常 | Q34: 不在用 | R34: 闲置 | S34: 经营性资产 | T34: 闲置 | U34: 林芝市察隅县古拉乡俄玉村股份经济合作社 | W34: 否
A35: 540425201807011 | B35: 察隅县 | C35: 54042520180701120001 | D35: 藏香猪 | E35: 2019.11 | F35: 俄玉村 | G35: 头 | H35: 3 | I35: 104 | J35: 102000 | L35: 0 | M35: 生物资产 | N35: 牲畜（禽） | O35: 集体资产 | P35: 损毁 | Q35: 不在用 | R35: 已死亡 | S35: 经营性资产 | T35: 闲置 | U35: 林芝市察隅县古拉乡俄玉村股份经济合作社 | W35: 否
A36: 540425201917017 | B36: 察隅县 | C36: 54042520191701710001 | D36: 家庭旅馆 | E36: 2015.12 | F36: 觉布如村 | G36: 栋 | H36: 20 | I36: 1 | J36: 600000 | K36: 272500 | L36: 327500 | M36: 固定资产 | N36: 房屋建筑物 | O36: 集体资产 | P36: 正常 | Q36: 不在用 | R36: 闲置 | S36: 经营性资产 | T36: 闲置 | U36: 林芝市察隅县古拉乡觉布如村股份经济合作社 | W36: 否
A37: 540425202120032 | B37: 察隅县 | C37: 54042520212003320002 | D37: 石榴（存活） | E37: 2021.12 | F37: 则巴村 | G37: 株 | H37: 10 | I37: 1384 | J37: 285898.97 | K37: 88152.18 | L37: 197746.79 | M37: 生物资产 | N37: 林木 | O37: 集体资产 | P37: 正常 | Q37: 不在用 | R37: 闲置 | S37: 经营性资产 | T37: 低效 | U37: 林芝市察隅县古拉乡则巴村股份经济合作社 | W37: 否
A38: 540425202120032 | B38: 察隅县 | C38: 54042520212003310001 | D38: 灌溉工程 | E38: 2021.12 | F38: 则巴村 | G38: 项 | H38: 10 | I38: 1 | J38: 374135.07 | K38: 115358.31 | L38: 258776.76 | M38: 固定资产 | N38: 构筑物 | O38: 集体资产 | P38: 正常 | Q38: 不在用 | R38: 闲置 | S38: 经营性资产 | T38: 低效 | U38: 林芝市察隅县古拉乡则巴村股份经济合作社 | W38: 否
A39: 540425202120032 | B39: 察隅县 | C39: 54042520212003310002 | D39: 网围栏 | E39: 2021.12 | F39: 则巴村 | G39: 2199m | H39: 10 | I39: 1 | J39: 195639.97 | K39: 60322.32 | L39: 135317.65 | M39: 固定资产 | N39: 构筑物 | O39: 集体资产 | P39: 正常 | Q39: 不在用 | R39: 闲置 | S39: 经营性资产 | T39: 低效 | U39: 林芝市察隅县古拉乡则巴村股份经济合作社 | W39: 否
A40: 540425201919022 | B40: 察隅县 | C40: 54042520191902210001 | D40: 液压榨油机 | E40: 2019.7 | F40: 则巴村 | G40: 台 | H40: 10 | I40: 1 | J40: 28800 | K40: 15840 | L40: 12960 | M40: 固定资产 | N40: 机器设备 | O40: 集体资产 | P40: 损坏 | Q40: 不在用 | R40: 损毁 | S40: 经营性资产 | T40: 闲置 | U40: 林芝市察隅县古拉乡则巴村股份经济合作社 | W40: 否
A41: 540425201919022 | B41: 察隅县 | C41: 54042520191902210002 | D41: 剥壳机 | E41: 2019.7 | F41: 则巴村 | G41: 台 | H41: 10 | I41: 2 | J41: 15000 | K41: 8250 | L41: 6750 | M41: 固定资产 | N41: 机器设备 | O41: 集体资产 | P41: 正常 | Q41: 不在用 | R41: 闲置 | S41: 经营性资产 | T41: 闲置 | U41: 林芝市察隅县古拉乡则巴村股份经济合作社 | W41: 否
A42: 540425201919022 | B42: 察隅县 | C42: 54042520191902210003 | D42: 分拣机 | E42: 2019.7 | F42: 则巴村 | G42: 台 | H42: 10 | I42: 1 | J42: 14500 | K42: 7975 | L42: 6525 | M42: 固定资产 | N42: 机器设备 | O42: 集体资产 | P42: 正常 | Q42: 不在用 | R42: 闲置 | S42: 经营性资产 | T42: 闲置 | U42: 林芝市察隅县古拉乡则巴村股份经济合作社 | W42: 否
A43: 540425201919022 | B43: 察隅县 | C43: 54042520191902210004 | D43: 烘干机 | E43: 2019.7 | F43: 则巴村 | G43: 台 | H43: 10 | I43: 1 | J43: 13500 | K43: 7425 | L43: 6075 | M43: 固定资产 | N43: 机器设备 | O43: 集体资产 | P43: 正常 | Q43: 不在用 | R43: 闲置 | S43: 经营性资产 | T43: 闲置 | U43: 林芝市察隅县古拉乡则巴村股份经济合作社 | W43: 否
A44: 540425201919022 | B44: 察隅县 | C44: 54042520191902210005 | D44: 过滤器 | E44: 2019.7 | F44: 则巴村 | G44: 台 | H44: 10 | I44: 2 | J44: 24000 | K44: 13200 | L44: 10800 | M44: 固定资产 | N44: 机器设备 | O44: 集体资产 | P44: 正常 | Q44: 不在用 | R44: 闲置 | S44: 经营性资产 | T44: 闲置 | U44: 林芝市察隅县古拉乡则巴村股份经济合作社 | W44: 否
A45: 540425201919022 | B45: 察隅县 | C45: 54042520191902210006 | D45: 核桃粉碎机 | E45: 2019.7 | F45: 则巴村 | G45: 台 | H45: 10 | I45: 1 | J45: 12500 | K45: 6875 | L45: 5625 | M45: 固定资产 | N45: 机器设备 | O45: 集体资产 | P45: 正常 | Q45: 不在用 | R45: 闲置 | S45: 经营性资产 | T45: 闲置 | U45: 林芝市察隅县古拉乡则巴村股份经济合作社 | W45: 否
A46: 540425201919022 | B46: 察隅县 | C46: 54042520191902210007 | D46: 包装机 | E46: 2019.7 | F46: 则巴村 | G46: 台 | H46: 10 | I46: 2 | J46: 19000 | K46: 10450 | L46: 8550 | M46: 固定资产 | N46: 机器设备 | O46: 集体资产 | P46: 正常 | Q46: 不在用 | R46: 闲置 | S46: 经营性资产 | T46: 闲置 | U46: 林芝市察隅县古拉乡则巴村股份经济合作社 | W46: 否
A47: 540425201919022 | B47: 察隅县 | C47: 54042520191902210008 | D47: 变压器 | E47: 2019.7 | F47: 则巴村 | G47: 台 | H47: 10 | I47: 1 | J47: 21400 | K47: 11770 | L47: 9630 | M47: 固定资产 | N47: 机器设备 | O47: 集体资产 | P47: 正常 | Q47: 不在用 | R47: 闲置 | S47: 经营性资产 | T47: 闲置 | U47: 林芝市察隅县古拉乡则巴村股份经济合作社 | W47: 否
... A93: 540425201907016 | B93: 察隅县 | C93: 54042520190701610001 | D93: 猪舍 | E93: 2020.03 | F93: 扎那村 | G93: 栋 | H93: 20 | I93: 1 | J93: 366700 | K93: 177238.33 | L93: 189461.67 | M93: 固定资产 | N93: 房屋建筑物 | O93: 集体资产 | P93: 正常 | Q93: 不在用 | R93: 闲置 | S93: 经营性资产 | T93: 闲置 | U93: 林芝市察隅县察瓦龙乡扎那村股份经济合作社 | W93: 否
A94: 540425201907016 | B94: 察隅县 | C94: 54042520190701620001 | D94: 藏香猪 | E94: 2020.03 | F94: 扎那村 | G94: 头 | H94: 3 | I94: 33 | J94: 115500 | L94: 0 | M94: 生物资产 | N94: 牲畜（禽） | O94: 集体资产 | P94: 正常 | Q94: 不在用 | R94: 闲置 | S94: 经营性资产 | T94: 闲置 | U94: 林芝市察隅县察瓦龙乡扎那村股份经济合作社 | W94: 否
A95: 540425201907016 | B95: 察隅县 | C95: 54042520190701610002 | D95: 饲料加工机 | E95: 2020.03 | F95: 扎那村 | G95: 台 | H95: 10 | I95: 1 | J95: 10000 | K95: 4833.33 | L95: 5166.67 | M95: 固定资产 | N95: 机器设备 | O95: 集体资产 | P95: 正常 | Q95: 不在用 | R95: 闲置 | S95: 经营性资产 | T95: 闲置 | U95: 林芝市察隅县察瓦龙乡扎那村股份经济合作社 | W95: 否
A96: 540425201907016 | B96: 察隅县 | C96: 54042520190701610003 | D96: 柴油发电机 | E96: 2020.03 | F96: 扎那村 | G96: 台 | H96: 10 | I96: 1 | J96: 7800 | K96: 3770 | L96: 4030 | M96: 固定资产 | N96: 机器设备 | O96: 集体资产 | P96: 正常 | Q96: 不在用 | R96: 闲置 | S96: 经营性资产 | T96: 闲置 | U96: 林芝市察隅县察瓦龙乡扎那村股份经济合作社 | W96: 否
A97: 540425201820016 | B97: 察隅县 | C97: 54042520182001620001 | D97: 石榴（存活） | E97: 2019.03 | F97: 龙布村 | G97: 珠 | H97: 10 | I97: 3622 | J97: 362240 | K97: 211306.7 | L97: 150933.3 | M97: 生物资产 | N97: 林木 | O97: 集体资产 | P97: 正常 | Q97: 不在用 | R97: 闲置 | S97: 经营性资产 | T97: 闲置 | U97: 林芝市察隅县察瓦龙乡龙布村股份经济合作社 | W97: 否
A98: 540425201820016 | B98: 察隅县 | C98: 54042520182001620002 | D98: 石榴（未存活） | E98: 2019.03 | F98: 龙布村 | G98: 珠 | H98: 10 | I98: 5434 | J98: 543360 | K98: 543360 | L98: 0 | M98: 生物资产 | N98: 林木 | O98: 集体资产 | P98: 损毁 | Q98: 不在用 | R98: 已死亡 | S98: 经营性资产 | T98: 闲置 | U98: 林芝市察隅县察瓦龙乡龙布村股份经济合作社 | W98: 否
